Workbook

Sheet Dashboard
B2: PLUME PARAGLIDERS
B3: Business Plan 2025-2031 • Tableau de Bord Exécutif
B6: 📊 INDICATEURS CLÉS | K6: 💼 PLAN DE FINANCEMENT
B7: 📅 CRÉATION | C7: 18 décembre 2025 | K7: JB Chandelier | L7: =Financement!B5 -> 104000 | M7: 55%
B8: Capital social | D8: Plan de financement | F8: Seuil rentabilité | H8: Marge nette/aile | K8: Thomas Pierre-Bes | L8: =Financement!B6 -> 85000 | M8: 45%
B9: =Financement!C7 -> 100000 | D9: =L12 -> 428000 | F9: =MAX('Seuil Rentabilité'!B21:D21) -> 204 | H9: =ROUND('Seuil Rentabilité'!B8,0)&" €" -> 1080 € | K9: Emprunt 4 ans | L9: ='Emprunt Bancaire'!B4 -> 189000
K10: Avoir EURL JB (2027) | L10: =Financement!B19 -> 50000
B12: 📈 SCÉNARIOS DE VENTES (Nombre d'ailes) | K12: TOTAL | L12: =SUM(L7:L10) -> 428000
C13: 2025 | D13: 2026 | E13: 2027 | F13: 2028 | G13: 2029 | H13: 2030 | I13: 2031
B14: 🟠 Réaliste | C14: 0 | D14: 75 | E14: 250 | F14: 550 | G14: 800 | H14: 1000 | I14: 1000 | K14: 📋 CHARGES FIXES / AN
B15: 🔴 Point Mort | C15: ='Analyse Point Mort'!B19 -> 0 | D15: ='Analyse Point Mort'!C19 -> 0 | E15: ='Analyse Point Mort'!D19 -> 139 | F15: ='Analyse Point Mort'!E19 -> 242 | G15: ='Analyse Point Mort'!F19 -> 242 | H15: ='Analyse Point Mort'!G19 -> 187 | I15: ='Analyse Point Mort'!H19 -> 187 | K15: Masse salariale | L15: ='Charges Fixes Plume'!D13 -> 83496
K16: Investissement R&D | L16: ='Charges Fixes Plume'!D38 -> 75128.734
K17: Exploitation | L17: ='Charges Fixes Plume'!D29 -> 50157.6
K19: TOTAL | L19: ='Charges Fixes Plume'!D57 -> 208782.33
B20: 💰 RÉSULTATS PRÉVISIONNELS - SCÉNARIO RÉALISTE
C21: 2025 | D21: 2026 | E21: 2027 | F21: 2028 | G21: 2029 | H21: 2030 | I21: 2031 | K21: 🏦 EMPRUNT BANCAIRE
B22: Chiffre d'affaires | C22: ='Compte de Résultat'!B13 -> 0 | D22: ='Compte de Résultat'!C13 -> 192906.25 | E22: ='Compte de Résultat'!D13 -> 643020.83 | F22: ='Compte de Résultat'!E13 -> 1414645.8 | G22: ='Compte de Résultat'!F13 -> 2057666.7 | H22: ='Compte de Résultat'!G13 -> 2572083.3 | I22: ='Compte de Résultat'!H13 -> 2700687.5 | K22: Montant | L22: ='Emprunt Bancaire'!B4 -> 189000
B23: bénéfice net | C23: ='Compte de Résultat'!B34 -> -8857.8558 | D23: ='Compte de Résultat'!C34 -> -128458.89 | E23: ='Compte de Résultat'!D34 -> 50265.066 | F23: ='Compte de Résultat'!E34 -> 382760.59 | G23: ='Compte de Résultat'!F34 -> 518386.01 | H23: ='Compte de Résultat'!G34 -> 690585.36 | I23: ='Compte de Résultat'!H34 -> 756513.57 | K23: Durée | L23: ='Emprunt Bancaire'!B5 -> 4
B24: Trésorerie cumulée | C24: ='Compte de Résultat'!B45 -> 91142.144 | D24: ='Compte de Résultat'!C45 -> 177292.44 | E24: ='Compte de Résultat'!D45 -> 195238.27 | F24: ='Compte de Résultat'!E45 -> 497335.69 | G24: ='Compte de Résultat'!F45 -> 1038336.3 | H24: ='Compte de Résultat'!G45 -> 1904663 | I24: ='Compte de Résultat'!H45 -> 2974177.6 | K24: Taux | L24: ='Emprunt Bancaire'!B6 -> 0.045
K25: Échéance/an | L25: ='Emprunt Bancaire'!D11 -> 52398.71
K27: ✅ POINTS CLÉS
K28: ✓ Rentabilité dès 2027
B29: "Le plan est présenté en euros constants (base 2025). L'inflation n'est pas modélisée séparément : les hausses de charges (salaires, matières, logistique) seront répercutées dans les prix de vente, maintenant les marges unitaires stables. Cette approche conservatrice sous-estime légèrement la rentabilité réelle, le remboursement d'emprunt étant fixe en euros nominaux." | K29: ✓ Seuil : ailes/an | L29: =F9 -> 204
K30: ✓ Marge brute | L30: ='Marges Produits'!G49 -> 0.42780787
K31: ✓ Tréso toujours positive
K32: ✓ Emprunt remboursé 2030

Sheet Frais de lancement
A1: PLUME PARAGLIDERS - CHARGES FIXES
A2: lancement
A5: 1. FRAIS DE LANCEMENT (One-shot)
A6: Poste | B6: Montant (€)
A7: Charte Graphique | B7: 500
A8: Création d'entreprise (Avocat) | B8: 3303
A9: SOUS-TOTAL LANCEMENT | B9: =SUM(B7:B8) -> 3803

Sheet Charges Fixes Plume
A1: PLUME PARAGLIDERS - CHARGES FIXES
A5: 1. MASSE SALARIALE ANNUELLE
A6: Note: ZFRR + ACRE. JB: prestation EURL 1 800€/mois. Thomas: 1 400€ brut/mois (coût employeur ~18 500€/an)
A7: Collaborateur | B7: Nb mois | C7: Type | D7: Charge annuelle (€) | F7: Mois décaissement | G7: Janvier | H7: Février | I7: Mars | J7: Avril | K7: Mai | L7: Juin | M7: Juillet | N7: Août | O7: Septembre | P7: Octobre | Q7: Novembre | R7: Décembre
A8: Manu Laly (pilote test) | B8: 10 | C8: Prestation | D8: 10000 | F8: Sauf Jul-Août | G8: =$D$8/10 -> 1000 | H8: =$D$8/10 -> 1000 | I8: =$D$8/10 -> 1000 | J8: =$D$8/10 -> 1000 | K8: =$D$8/10 -> 1000 | L8: =$D$8/10 -> 1000 | M8: 0 | N8: 0 | O8: =$D$8/10 -> 1000 | P8: =$D$8/10 -> 1000 | Q8: =$D$8/10 -> 1000 | R8: =$D$8/10 -> 1000
A9: Yann Freund (conception accessoire) | B9: 3 | C9: Prestation | D9: 6000 | F9: Jan à Mars | G9: =$D$9/3 -> 2000 | H9: =$D$9/3 -> 2000 | I9: =$D$9/3 -> 2000 | J9: 0 | K9: 0 | L9: 0 | M9: 0 | N9: 0 | O9: 0 | P9: 0 | Q9: 0 | R9: 0
A10: Jean-Baptiste Chandelier (president) | B10: 12 | C10: Prestation EURL | D10: 21600 | F10: Tous les mois | G10: =$D$10/12 -> 1800 | H10: =$D$10/12 -> 1800 | I10: =$D$10/12 -> 1800 | J10: =$D$10/12 -> 1800 | K10: =$D$10/12 -> 1800 | L10: =$D$10/12 -> 1800 | M10: =$D$10/12 -> 1800 | N10: =$D$10/12 -> 1800 | ... R10: =$D$10/12 -> 1800
A11: Thomas Pierre-Bes (directeur) | B11: 12 | C11: Salaire | D11: 18500 | F11: Tous les mois | G11: =$D$11/12 -> 1541.6667 | H11: =$D$11/12 -> 1541.6667 | I11: =$D$11/12 -> 1541.6667 | J11: =$D$11/12 -> 1541.6667 | K11: =$D$11/12 -> 1541.6667 | L11: =$D$11/12 -> 1541.6667 | M11: =$D$11/12 -> 1541.6667 | N11: =$D$11/12 -> 1541.6667 | ... R11: =$D$11/12 -> 1541.6667
A12: Jim Nougarolles (pilot test & R&D) | B12: 12 | C12: Prestation | D12: 27396 | F12: 1 mois sur 2 | G12: =$D$12/6 -> 4566 | H12: 0 | I12: =$D$12/6 -> 4566 | J12: 0 | K12: =$D$12/6 -> 4566 | L12: 0 | M12: =$D$12/6 -> 4566 | N12: 0 | O12: =$D$12/6 -> 4566 | P12: 0 | Q12: =$D$12/6 -> 4566 | R12: 0
A13: SOUS-TOTAL MASSE SALARIALE | D13: =SUM(D8:D12) -> 83496 | G13: =SUM(G8:G12) -> 10907.667 | H13: =SUM(H8:H12) -> 6341.6667 | I13: =SUM(I8:I12) -> 10907.667 | J13: =SUM(J8:J12) -> 4341.6667 | K13: =SUM(K8:K12) -> 8907.6667 | L13: =SUM(L8:L12) -> 4341.6667 | M13: =SUM(M8:M12) -> 7907.6667 | N13: =SUM(N8:N12) -> 3341.6667 | ... R13: =SUM(R8:R12) -> 4341.6667
A15: 2. CHARGES D'EXPLOITATION ANNUELLES (hors masse salariale)
A16: Poste | C16: Catégorie | D16: Montant (€/an) | E16: Fréquence | F16: Mois décaissement | G16: Janvier | H16: Février | I16: Mars | J16: Avril | K16: Mai | L16: Juin | M16: Juillet | N16: Août | O16: Septembre | P16: Octobre | Q16: Novembre | R16: Décembre
A17: OVH Website | C17: License | D17: 50 | E17: Annuel | F17: Décembre | G17: =IF($E17="Mensuel",$D17/12,IF($E17="Annuel",IF(G$16=$F17,$D17,0),IF($E17="Trimestriel",IF(OR(G$16="Janvier",G$16="Avril",G$16="Juillet",G$16="Octobre"),$D17/4,0),0))) -> 0 | H17: =IF($E17="Mensuel",$D17/12,IF($E17="Annuel",IF(H$16=$F17,$D17,0),IF($E17="Trimestriel",IF(OR(H$16="Janvier",H$16="Avril",H$16="Juillet",H$16="Octobre"),$D17/4,0),0))) -> 0 | I17: =IF($E17="Mensuel",$D17/12,IF($E17="Annuel",IF(I$16=$F17,$D17,0),IF($E17="Trimestriel",IF(OR(I$16="Janvier",I$16="Avril",I$16="Juillet",I$16="Octobre"),$D17/4,0),0))) -> 0 | J17: =IF($E17="Mensuel",$D17/12,IF($E17="Annuel",IF(J$16=$F17,$D17,0),IF($E17="Trimestriel",IF(OR(J$16="Janvier",J$16="Avril",J$16="Juillet",J$16="Octobre"),$D17/4,0),0))) -> 0 | K17: =IF($E17="Mensuel",$D17/12,IF($E17="Annuel",IF(K$16=$F17,$D17,0),IF($E17="Trimestriel",IF(OR(K$16="Janvier",K$16="Avril",K$16="Juillet",K$16="Octobre"),$D17/4,0),0))) -> 0 | L17: =IF($E17="Mensuel",$D17/12,IF($E17="Annuel",IF(L$16=$F17,$D17,0),IF($E17="Trimestriel",IF(OR(L$16="Janvier",L$16="Avril",L$16="Juillet",L$16="Octobre"),$D17/4,0),0))) -> 0 | M17: =IF($E17="Mensuel",$D17/12,IF($E17="Annuel",IF(M$16=$F17,$D17,0),IF($E17="Trimestriel",IF(OR(M$16="Janvier",M$16="Avril",M$16="Juillet",M$16="Octobre"),$D17/4,0),0))) -> 0 | N17: =IF($E17="Mensuel",$D17/12,IF($E17="Annuel",IF(N$16=$F17,$D17,0),IF($E17="Trimestriel",IF(OR(N$16="Janvier",N$16="Avril",N$16="Juillet",N$16="Octobre"),$D17/4,0),0))) -> 0 | ... R17: =IF($E17="Mensuel",$D17/12,IF($E17="Annuel",IF(R$16=$F17,$D17,0),IF($E17="Trimestriel",IF(OR(R$16="Janvier",R$16="Avril",R$16="Juillet",R$16="Octobre"),$D17/4,0),0))) -> 50
A18: Déplacements / Nourriture / Logement | C18: Déplacement | D18: 10000 | E18: Mensuel | F18: Tous les mois | G18: =IF($E18="Mensuel",$D18/12,IF($E18="Annuel",IF(G$16=$F18,$D18,0),IF($E18="Trimestriel",IF(OR(G$16="Janvier",G$16="Avril",G$16="Juillet",G$16="Octobre"),$D18/4,0),0))) -> 833.33333 | H18: =IF($E18="Mensuel",$D18/12,IF($E18="Annuel",IF(H$16=$F18,$D18,0),IF($E18="Trimestriel",IF(OR(H$16="Janvier",H$16="Avril",H$16="Juillet",H$16="Octobre"),$D18/4,0),0))) -> 833.33333 | I18: =IF($E18="Mensuel",$D18/12,IF($E18="Annuel",IF(I$16=$F18,$D18,0),IF($E18="Trimestriel",IF(OR(I$16="Janvier",I$16="Avril",I$16="Juillet",I$16="Octobre"),$D18/4,0),0))) -> 833.33333 | J18: =IF($E18="Mensuel",$D18/12,IF($E18="Annuel",IF(J$16=$F18,$D18,0),IF($E18="Trimestriel",IF(OR(J$16="Janvier",J$16="Avril",J$16="Juillet",J$16="Octobre"),$D18/4,0),0))) -> 833.33333 | K18: =IF($E18="Mensuel",$D18/12,IF($E18="Annuel",IF(K$16=$F18,$D18,0),IF($E18="Trimestriel",IF(OR(K$16="Janvier",K$16="Avril",K$16="Juillet",K$16="Octobre"),$D18/4,0),0))) -> 833.33333 | L18: =IF($E18="Mensuel",$D18/12,IF($E18="Annuel",IF(L$16=$F18,$D18,0),IF($E18="Trimestriel",IF(OR(L$16="Janvier",L$16="Avril",L$16="Juillet",L$16="Octobre"),$D18/4,0),0))) -> 833.33333 | M18: =IF($E18="Mensuel",$D18/12,IF($E18="Annuel",IF(M$16=$F18,$D18,0),IF($E18="Trimestriel",IF(OR(M$16="Janvier",M$16="Avril",M$16="Juillet",M$16="Octobre"),$D18/4,0),0))) -> 833.33333 | N18: =IF($E18="Mensuel",$D18/12,IF($E18="Annuel",IF(N$16=$F18,$D18,0),IF($E18="Trimestriel",IF(OR(N$16="Janvier",N$16="Avril",N$16="Juillet",N$16="Octobre"),$D18/4,0),0))) -> 833.33333 | ... R18: =IF($E18="Mensuel",$D18/12,IF($E18="Annuel",IF(R$16=$F18,$D18,0),IF($E18="Trimestriel",IF(OR(R$16="Janvier",R$16="Avril",R$16="Juillet",R$16="Octobre"),$D18/4,0),0))) -> 833.33333
A19: Adobe | C19: Logiciel | D19: 660 | E19: Mensuel | F19: Tous les mois | G19: =IF($E19="Mensuel",$D19/12,IF($E19="Annuel",IF(G$16=$F19,$D19,0),IF($E19="Trimestriel",IF(OR(G$16="Janvier",G$16="Avril",G$16="Juillet",G$16="Octobre"),$D19/4,0),0))) -> 55 | H19: =IF($E19="Mensuel",$D19/12,IF($E19="Annuel",IF(H$16=$F19,$D19,0),IF($E19="Trimestriel",IF(OR(H$16="Janvier",H$16="Avril",H$16="Juillet",H$16="Octobre"),$D19/4,0),0))) -> 55 | I19: =IF($E19="Mensuel",$D19/12,IF($E19="Annuel",IF(I$16=$F19,$D19,0),IF($E19="Trimestriel",IF(OR(I$16="Janvier",I$16="Avril",I$16="Juillet",I$16="Octobre"),$D19/4,0),0))) -> 55 | J19: =IF($E19="Mensuel",$D19/12,IF($E19="Annuel",IF(J$16=$F19,$D19,0),IF($E19="Trimestriel",IF(OR(J$16="Janvier",J$16="Avril",J$16="Juillet",J$16="Octobre"),$D19/4,0),0))) -> 55 | K19: =IF($E19="Mensuel",$D19/12,IF($E19="Annuel",IF(K$16=$F19,$D19,0),IF($E19="Trimestriel",IF(OR(K$16="Janvier",K$16="Avril",K$16="Juillet",K$16="Octobre"),$D19/4,0),0))) -> 55 | L19: =IF($E19="Mensuel",$D19/12,IF($E19="Annuel",IF(L$16=$F19,$D19,0),IF($E19="Trimestriel",IF(OR(L$16="Janvier",L$16="Avril",L$16="Juillet",L$16="Octobre"),$D19/4,0),0))) -> 55 | M19: =IF($E19="Mensuel",$D19/12,IF($E19="Annuel",IF(M$16=$F19,$D19,0),IF($E19="Trimestriel",IF(OR(M$16="Janvier",M$16="Avril",M$16="Juillet",M$16="Octobre"),$D19/4,0),0))) -> 55 | N19: =IF($E19="Mensuel",$D19/12,IF($E19="Annuel",IF(N$16=$F19,$D19,0),IF($E19="Trimestriel",IF(OR(N$16="Janvier",N$16="Avril",N$16="Juillet",N$16="Octobre"),$D19/4,0),0))) -> 55 | ... R19: =IF($E19="Mensuel",$D19/12,IF($E19="Annuel",IF(R$16=$F19,$D19,0),IF($E19="Trimestriel",IF(OR(R$16="Janvier",R$16="Avril",R$16="Juillet",R$16="Octobre"),$D19/4,0),0))) -> 55
A20: Microsoft Teams / Cloud / Suite Office | C20: Logiciel | D20: 777.6 | E20: Mensuel | F20: Tous les mois | G20: =IF($E20="Mensuel",$D20/12,IF($E20="Annuel",IF(G$16=$F20,$D20,0),IF($E20="Trimestriel",IF(OR(G$16="Janvier",G$16="Avril",G$16="Juillet",G$16="Octobre"),$D20/4,0),0))) -> 64.8 | H20: =IF($E20="Mensuel",$D20/12,IF($E20="Annuel",IF(H$16=$F20,$D20,0),IF($E20="Trimestriel",IF(OR(H$16="Janvier",H$16="Avril",H$16="Juillet",H$16="Octobre"),$D20/4,0),0))) -> 64.8 | I20: =IF($E20="Mensuel",$D20/12,IF($E20="Annuel",IF(I$16=$F20,$D20,0),IF($E20="Trimestriel",IF(OR(I$16="Janvier",I$16="Avril",I$16="Juillet",I$16="Octobre"),$D20/4,0),0))) -> 64.8 | J20: =IF($E20="Mensuel",$D20/12,IF($E20="Annuel",IF(J$16=$F20,$D20,0),IF($E20="Trimestriel",IF(OR(J$16="Janvier",J$16="Avril",J$16="Juillet",J$16="Octobre"),$D20/4,0),0))) -> 64.8 | K20: =IF($E20="Mensuel",$D20/12,IF($E20="Annuel",IF(K$16=$F20,$D20,0),IF($E20="Trimestriel",IF(OR(K$16="Janvier",K$16="Avril",K$16="Juillet",K$16="Octobre"),$D20/4,0),0))) -> 64.8 | L20: =IF($E20="Mensuel",$D20/12,IF($E20="Annuel",IF(L$16=$F20,$D20,0),IF($E20="Trimestriel",IF(OR(L$16="Janvier",L$16="Avril",L$16="Juillet",L$16="Octobre"),$D20/4,0),0))) -> 64.8 | M20: =IF($E20="Mensuel",$D20/12,IF($E20="Annuel",IF(M$16=$F20,$D20,0),IF($E20="Trimestriel",IF(OR(M$16="Janvier",M$16="Avril",M$16="Juillet",M$16="Octobre"),$D20/4,0),0))) -> 64.8 | N20: =IF($E20="Mensuel",$D20/12,IF($E20="Annuel",IF(N$16=$F20,$D20,0),IF($E20="Trimestriel",IF(OR(N$16="Janvier",N$16="Avril",N$16="Juillet",N$16="Octobre"),$D20/4,0),0))) -> 64.8 | ... R20: =IF($E20="Mensuel",$D20/12,IF($E20="Annuel",IF(R$16=$F20,$D20,0),IF($E20="Trimestriel",IF(OR(R$16="Janvier",R$16="Avril",R$16="Juillet",R$16="Octobre"),$D20/4,0),0))) -> 64.8
A21: Loyer Briançon (3bis Route de Gap) | C21: Frais fixe | D21: 9600 | E21: Mensuel | F21: Tous les mois | G21: =IF($E21="Mensuel",$D21/12,IF($E21="Annuel",IF(G$16=$F21,$D21,0),IF($E21="Trimestriel",IF(OR(G$16="Janvier",G$16="Avril",G$16="Juillet",G$16="Octobre"),$D21/4,0),0))) -> 800 | H21: =IF($E21="Mensuel",$D21/12,IF($E21="Annuel",IF(H$16=$F21,$D21,0),IF($E21="Trimestriel",IF(OR(H$16="Janvier",H$16="Avril",H$16="Juillet",H$16="Octobre"),$D21/4,0),0))) -> 800 | I21: =IF($E21="Mensuel",$D21/12,IF($E21="Annuel",IF(I$16=$F21,$D21,0),IF($E21="Trimestriel",IF(OR(I$16="Janvier",I$16="Avril",I$16="Juillet",I$16="Octobre"),$D21/4,0),0))) -> 800 | J21: =IF($E21="Mensuel",$D21/12,IF($E21="Annuel",IF(J$16=$F21,$D21,0),IF($E21="Trimestriel",IF(OR(J$16="Janvier",J$16="Avril",J$16="Juillet",J$16="Octobre"),$D21/4,0),0))) -> 800 | K21: =IF($E21="Mensuel",$D21/12,IF($E21="Annuel",IF(K$16=$F21,$D21,0),IF($E21="Trimestriel",IF(OR(K$16="Janvier",K$16="Avril",K$16="Juillet",K$16="Octobre"),$D21/4,0),0))) -> 800 | L21: =IF($E21="Mensuel",$D21/12,IF($E21="Annuel",IF(L$16=$F21,$D21,0),IF($E21="Trimestriel",IF(OR(L$16="Janvier",L$16="Avril",L$16="Juillet",L$16="Octobre"),$D21/4,0),0))) -> 800 | M21: =IF($E21="Mensuel",$D21/12,IF($E21="Annuel",IF(M$16=$F21,$D21,0),IF($E21="Trimestriel",IF(OR(M$16="Janvier",M$16="Avril",M$16="Juillet",M$16="Octobre"),$D21/4,0),0))) -> 800 | N21: =IF($E21="Mensuel",$D21/12,IF($E21="Annuel",IF(N$16=$F21,$D21,0),IF($E21="Trimestriel",IF(OR(N$16="Janvier",N$16="Avril",N$16="Juillet",N$16="Octobre"),$D21/4,0),0))) -> 800 | ... R21: =IF($E21="Mensuel",$D21/12,IF($E21="Annuel",IF(R$16=$F21,$D21,0),IF($E21="Trimestriel",IF(OR(R$16="Janvier",R$16="Avril",R$16="Juillet",R$16="Octobre"),$D21/4,0),0))) -> 800
A22: Loyer bureau/atelier Embrun | C22: Frais fixe | D22: 3600 | E22: Mensuel | F22: Tous les mois | G22: =IF($E22="Mensuel",$D22/12,IF($E22="Annuel",IF(G$16=$F22,$D22,0),IF($E22="Trimestriel",IF(OR(G$16="Janvier",G$16="Avril",G$16="Juillet",G$16="Octobre"),$D22/4,0),0))) -> 300 | H22: =IF($E22="Mensuel",$D22/12,IF($E22="Annuel",IF(H$16=$F22,$D22,0),IF($E22="Trimestriel",IF(OR(H$16="Janvier",H$16="Avril",H$16="Juillet",H$16="Octobre"),$D22/4,0),0))) -> 300 | I22: =IF($E22="Mensuel",$D22/12,IF($E22="Annuel",IF(I$16=$F22,$D22,0),IF($E22="Trimestriel",IF(OR(I$16="Janvier",I$16="Avril",I$16="Juillet",I$16="Octobre"),$D22/4,0),0))) -> 300 | J22: =IF($E22="Mensuel",$D22/12,IF($E22="Annuel",IF(J$16=$F22,$D22,0),IF($E22="Trimestriel",IF(OR(J$16="Janvier",J$16="Avril",J$16="Juillet",J$16="Octobre"),$D22/4,0),0))) -> 300 | K22: =IF($E22="Mensuel",$D22/12,IF($E22="Annuel",IF(K$16=$F22,$D22,0),IF($E22="Trimestriel",IF(OR(K$16="Janvier",K$16="Avril",K$16="Juillet",K$16="Octobre"),$D22/4,0),0))) -> 300 | L22: =IF($E22="Mensuel",$D22/12,IF($E22="Annuel",IF(L$16=$F22,$D22,0),IF($E22="Trimestriel",IF(OR(L$16="Janvier",L$16="Avril",L$16="Juillet",L$16="Octobre"),$D22/4,0),0))) -> 300 | M22: =IF($E22="Mensuel",$D22/12,IF($E22="Annuel",IF(M$16=$F22,$D22,0),IF($E22="Trimestriel",IF(OR(M$16="Janvier",M$16="Avril",M$16="Juillet",M$16="Octobre"),$D22/4,0),0))) -> 300 | N22: =IF($E22="Mensuel",$D22/12,IF($E22="Annuel",IF(N$16=$F22,$D22,0),IF($E22="Trimestriel",IF(OR(N$16="Janvier",N$16="Avril",N$16="Juillet",N$16="Octobre"),$D22/4,0),0))) -> 300 | ... R22: =IF($E22="Mensuel",$D22/12,IF($E22="Annuel",IF(R$16=$F22,$D22,0),IF($E22="Trimestriel",IF(OR(R$16="Janvier",R$16="Avril",R$16="Juillet",R$16="Octobre"),$D22/4,0),0))) -> 300
A23: Indemnités kilométriques Thomas (Embrun ↔ Briançon, 12 480 km/an) | C23: Déplacement | D23: 5850 | E23: Mensuel | F23: Tous les mois | G23: =IF($E23="Mensuel",$D23/12,IF($E23="Annuel",IF(G$16=$F23,$D23,0),IF($E23="Trimestriel",IF(OR(G$16="Janvier",G$16="Avril",G$16="Juillet",G$16="Octobre"),$D23/4,0),0))) -> 487.5 | H23: =IF($E23="Mensuel",$D23/12,IF($E23="Annuel",IF(H$16=$F23,$D23,0),IF($E23="Trimestriel",IF(OR(H$16="Janvier",H$16="Avril",H$16="Juillet",H$16="Octobre"),$D23/4,0),0))) -> 487.5 | I23: =IF($E23="Mensuel",$D23/12,IF($E23="Annuel",IF(I$16=$F23,$D23,0),IF($E23="Trimestriel",IF(OR(I$16="Janvier",I$16="Avril",I$16="Juillet",I$16="Octobre"),$D23/4,0),0))) -> 487.5 | J23: =IF($E23="Mensuel",$D23/12,IF($E23="Annuel",IF(J$16=$F23,$D23,0),IF($E23="Trimestriel",IF(OR(J$16="Janvier",J$16="Avril",J$16="Juillet",J$16="Octobre"),$D23/4,0),0))) -> 487.5 | K23: =IF($E23="Mensuel",$D23/12,IF($E23="Annuel",IF(K$16=$F23,$D23,0),IF($E23="Trimestriel",IF(OR(K$16="Janvier",K$16="Avril",K$16="Juillet",K$16="Octobre"),$D23/4,0),0))) -> 487.5 | L23: =IF($E23="Mensuel",$D23/12,IF($E23="Annuel",IF(L$16=$F23,$D23,0),IF($E23="Trimestriel",IF(OR(L$16="Janvier",L$16="Avril",L$16="Juillet",L$16="Octobre"),$D23/4,0),0))) -> 487.5 | M23: =IF($E23="Mensuel",$D23/12,IF($E23="Annuel",IF(M$16=$F23,$D23,0),IF($E23="Trimestriel",IF(OR(M$16="Janvier",M$16="Avril",M$16="Juillet",M$16="Octobre"),$D23/4,0),0))) -> 487.5 | N23: =IF($E23="Mensuel",$D23/12,IF($E23="Annuel",IF(N$16=$F23,$D23,0),IF($E23="Trimestriel",IF(OR(N$16="Janvier",N$16="Avril",N$16="Juillet",N$16="Octobre"),$D23/4,0),0))) -> 487.5 | ... R23: =IF($E23="Mensuel",$D23/12,IF($E23="Annuel",IF(R$16=$F23,$D23,0),IF($E23="Trimestriel",IF(OR(R$16="Janvier",R$16="Avril",R$16="Juillet",R$16="Octobre"),$D23/4,0),0))) -> 487.5
A24: Notion | C24: Gestion | D24: 570 | E24: Annuel | F24: Février | G24: =IF($E24="Mensuel",$D24/12,IF($E24="Annuel",IF(G$16=$F24,$D24,0),IF($E24="Trimestriel",IF(OR(G$16="Janvier",G$16="Avril",G$16="Juillet",G$16="Octobre"),$D24/4,0),0))) -> 0 | H24: =IF($E24="Mensuel",$D24/12,IF($E24="Annuel",IF(H$16=$F24,$D24,0),IF($E24="Trimestriel",IF(OR(H$16="Janvier",H$16="Avril",H$16="Juillet",H$16="Octobre"),$D24/4,0),0))) -> 570 | I24: =IF($E24="Mensuel",$D24/12,IF($E24="Annuel",IF(I$16=$F24,$D24,0),IF($E24="Trimestriel",IF(OR(I$16="Janvier",I$16="Avril",I$16="Juillet",I$16="Octobre"),$D24/4,0),0))) -> 0 | J24: =IF($E24="Mensuel",$D24/12,IF($E24="Annuel",IF(J$16=$F24,$D24,0),IF($E24="Trimestriel",IF(OR(J$16="Janvier",J$16="Avril",J$16="Juillet",J$16="Octobre"),$D24/4,0),0))) -> 0 | K24: =IF($E24="Mensuel",$D24/12,IF($E24="Annuel",IF(K$16=$F24,$D24,0),IF($E24="Trimestriel",IF(OR(K$16="Janvier",K$16="Avril",K$16="Juillet",K$16="Octobre"),$D24/4,0),0))) -> 0 | L24: =IF($E24="Mensuel",$D24/12,IF($E24="Annuel",IF(L$16=$F24,$D24,0),IF($E24="Trimestriel",IF(OR(L$16="Janvier",L$16="Avril",L$16="Juillet",L$16="Octobre"),$D24/4,0),0))) -> 0 | M24: =IF($E24="Mensuel",$D24/12,IF($E24="Annuel",IF(M$16=$F24,$D24,0),IF($E24="Trimestriel",IF(OR(M$16="Janvier",M$16="Avril",M$16="Juillet",M$16="Octobre"),$D24/4,0),0))) -> 0 | N24: =IF($E24="Mensuel",$D24/12,IF($E24="Annuel",IF(N$16=$F24,$D24,0),IF($E24="Trimestriel",IF(OR(N$16="Janvier",N$16="Avril",N$16="Juillet",N$16="Octobre"),$D24/4,0),0))) -> 0 | ... R24: =IF($E24="Mensuel",$D24/12,IF($E24="Annuel",IF(R$16=$F24,$D24,0),IF($E24="Trimestriel",IF(OR(R$16="Janvier",R$16="Avril",R$16="Juillet",R$16="Octobre"),$D24/4,0),0))) -> 0
A25: AI Assistant | C25: Logiciel | D25: 5400 | E25: Mensuel | F25: Tous les mois | G25: =IF($E25="Mensuel",$D25/12,IF($E25="Annuel",IF(G$16=$F25,$D25,0),IF($E25="Trimestriel",IF(OR(G$16="Janvier",G$16="Avril",G$16="Juillet",G$16="Octobre"),$D25/4,0),0))) -> 450 | H25: =IF($E25="Mensuel",$D25/12,IF($E25="Annuel",IF(H$16=$F25,$D25,0),IF($E25="Trimestriel",IF(OR(H$16="Janvier",H$16="Avril",H$16="Juillet",H$16="Octobre"),$D25/4,0),0))) -> 450 | I25: =IF($E25="Mensuel",$D25/12,IF($E25="Annuel",IF(I$16=$F25,$D25,0),IF($E25="Trimestriel",IF(OR(I$16="Janvier",I$16="Avril",I$16="Juillet",I$16="Octobre"),$D25/4,0),0))) -> 450 | J25: =IF($E25="Mensuel",$D25/12,IF($E25="Annuel",IF(J$16=$F25,$D25,0),IF($E25="Trimestriel",IF(OR(J$16="Janvier",J$16="Avril",J$16="Juillet",J$16="Octobre"),$D25/4,0),0))) -> 450 | K25: =IF($E25="Mensuel",$D25/12,IF($E25="Annuel",IF(K$16=$F25,$D25,0),IF($E25="Trimestriel",IF(OR(K$16="Janvier",K$16="Avril",K$16="Juillet",K$16="Octobre"),$D25/4,0),0))) -> 450 | L25: =IF($E25="Mensuel",$D25/12,IF($E25="Annuel",IF(L$16=$F25,$D25,0),IF($E25="Trimestriel",IF(OR(L$16="Janvier",L$16="Avril",L$16="Juillet",L$16="Octobre"),$D25/4,0),0))) -> 450 | M25: =IF($E25="Mensuel",$D25/12,IF($E25="Annuel",IF(M$16=$F25,$D25,0),IF($E25="Trimestriel",IF(OR(M$16="Janvier",M$16="Avril",M$16="Juillet",M$16="Octobre"),$D25/4,0),0))) -> 450 | N25: =IF($E25="Mensuel",$D25/12,IF($E25="Annuel",IF(N$16=$F25,$D25,0),IF($E25="Trimestriel",IF(OR(N$16="Janvier",N$16="Avril",N$16="Juillet",N$16="Octobre"),$D25/4,0),0))) -> 450 | ... R25: =IF($E25="Mensuel",$D25/12,IF($E25="Annuel",IF(R$16=$F25,$D25,0),IF($E25="Trimestriel",IF(OR(R$16="Janvier",R$16="Avril",R$16="Juillet",R$16="Octobre"),$D25/4,0),0))) -> 450
A26: Glider Plan | C26: Logiciel | D26: 4650 | E26: Annuel | F26: Janvier | G26: =IF($E26="Mensuel",$D26/12,IF($E26="Annuel",IF(G$16=$F26,$D26,0),IF($E26="Trimestriel",IF(OR(G$16="Janvier",G$16="Avril",G$16="Juillet",G$16="Octobre"),$D26/4,0),0))) -> 4650 | H26: =IF($E26="Mensuel",$D26/12,IF($E26="Annuel",IF(H$16=$F26,$D26,0),IF($E26="Trimestriel",IF(OR(H$16="Janvier",H$16="Avril",H$16="Juillet",H$16="Octobre"),$D26/4,0),0))) -> 0 | I26: =IF($E26="Mensuel",$D26/12,IF($E26="Annuel",IF(I$16=$F26,$D26,0),IF($E26="Trimestriel",IF(OR(I$16="Janvier",I$16="Avril",I$16="Juillet",I$16="Octobre"),$D26/4,0),0))) -> 0 | J26: =IF($E26="Mensuel",$D26/12,IF($E26="Annuel",IF(J$16=$F26,$D26,0),IF($E26="Trimestriel",IF(OR(J$16="Janvier",J$16="Avril",J$16="Juillet",J$16="Octobre"),$D26/4,0),0))) -> 0 | K26: =IF($E26="Mensuel",$D26/12,IF($E26="Annuel",IF(K$16=$F26,$D26,0),IF($E26="Trimestriel",IF(OR(K$16="Janvier",K$16="Avril",K$16="Juillet",K$16="Octobre"),$D26/4,0),0))) -> 0 | L26: =IF($E26="Mensuel",$D26/12,IF($E26="Annuel",IF(L$16=$F26,$D26,0),IF($E26="Trimestriel",IF(OR(L$16="Janvier",L$16="Avril",L$16="Juillet",L$16="Octobre"),$D26/4,0),0))) -> 0 | M26: =IF($E26="Mensuel",$D26/12,IF($E26="Annuel",IF(M$16=$F26,$D26,0),IF($E26="Trimestriel",IF(OR(M$16="Janvier",M$16="Avril",M$16="Juillet",M$16="Octobre"),$D26/4,0),0))) -> 0 | N26: =IF($E26="Mensuel",$D26/12,IF($E26="Annuel",IF(N$16=$F26,$D26,0),IF($E26="Trimestriel",IF(OR(N$16="Janvier",N$16="Avril",N$16="Juillet",N$16="Octobre"),$D26/4,0),0))) -> 0 | ... R26: =IF($E26="Mensuel",$D26/12,IF($E26="Annuel",IF(R$16=$F26,$D26,0),IF($E26="Trimestriel",IF(OR(R$16="Janvier",R$16="Avril",R$16="Juillet",R$16="Octobre"),$D26/4,0),0))) -> 0
A27: Investissement matériel | C27: Achat | D27: 5000 | E27: Mensuel | F27: Tous les mois | G27: =IF($E27="Mensuel",$D27/12,IF($E27="Annuel",IF(G$16=$F27,$D27,0),IF($E27="Trimestriel",IF(OR(G$16="Janvier",G$16="Avril",G$16="Juillet",G$16="Octobre"),$D27/4,0),0))) -> 416.66667 | H27: =IF($E27="Mensuel",$D27/12,IF($E27="Annuel",IF(H$16=$F27,$D27,0),IF($E27="Trimestriel",IF(OR(H$16="Janvier",H$16="Avril",H$16="Juillet",H$16="Octobre"),$D27/4,0),0))) -> 416.66667 | I27: =IF($E27="Mensuel",$D27/12,IF($E27="Annuel",IF(I$16=$F27,$D27,0),IF($E27="Trimestriel",IF(OR(I$16="Janvier",I$16="Avril",I$16="Juillet",I$16="Octobre"),$D27/4,0),0))) -> 416.66667 | J27: =IF($E27="Mensuel",$D27/12,IF($E27="Annuel",IF(J$16=$F27,$D27,0),IF($E27="Trimestriel",IF(OR(J$16="Janvier",J$16="Avril",J$16="Juillet",J$16="Octobre"),$D27/4,0),0))) -> 416.66667 | K27: =IF($E27="Mensuel",$D27/12,IF($E27="Annuel",IF(K$16=$F27,$D27,0),IF($E27="Trimestriel",IF(OR(K$16="Janvier",K$16="Avril",K$16="Juillet",K$16="Octobre"),$D27/4,0),0))) -> 416.66667 | L27: =IF($E27="Mensuel",$D27/12,IF($E27="Annuel",IF(L$16=$F27,$D27,0),IF($E27="Trimestriel",IF(OR(L$16="Janvier",L$16="Avril",L$16="Juillet",L$16="Octobre"),$D27/4,0),0))) -> 416.66667 | M27: =IF($E27="Mensuel",$D27/12,IF($E27="Annuel",IF(M$16=$F27,$D27,0),IF($E27="Trimestriel",IF(OR(M$16="Janvier",M$16="Avril",M$16="Juillet",M$16="Octobre"),$D27/4,0),0))) -> 416.66667 | N27: =IF($E27="Mensuel",$D27/12,IF($E27="Annuel",IF(N$16=$F27,$D27,0),IF($E27="Trimestriel",IF(OR(N$16="Janvier",N$16="Avril",N$16="Juillet",N$16="Octobre"),$D27/4,0),0))) -> 416.66667 | ... R27: =IF($E27="Mensuel",$D27/12,IF($E27="Annuel",IF(R$16=$F27,$D27,0),IF($E27="Trimestriel",IF(OR(R$16="Janvier",R$16="Avril",R$16="Juillet",R$16="Octobre"),$D27/4,0),0))) -> 416.66667
A28: Comptabilité | C28: Gestion | D28: 4000 | E28: Trimestriel | F28: Jan/Avr/Jul/Oct | G28: =IF($E28="Mensuel",$D28/12,IF($E28="Annuel",IF(G$16=$F28,$D28,0),IF($E28="Trimestriel",IF(OR(G$16="Janvier",G$16="Avril",G$16="Juillet",G$16="Octobre"),$D28/4,0),0))) -> 1000 | H28: =IF($E28="Mensuel",$D28/12,IF($E28="Annuel",IF(H$16=$F28,$D28,0),IF($E28="Trimestriel",IF(OR(H$16="Janvier",H$16="Avril",H$16="Juillet",H$16="Octobre"),$D28/4,0),0))) -> 0 | I28: =IF($E28="Mensuel",$D28/12,IF($E28="Annuel",IF(I$16=$F28,$D28,0),IF($E28="Trimestriel",IF(OR(I$16="Janvier",I$16="Avril",I$16="Juillet",I$16="Octobre"),$D28/4,0),0))) -> 0 | J28: =IF($E28="Mensuel",$D28/12,IF($E28="Annuel",IF(J$16=$F28,$D28,0),IF($E28="Trimestriel",IF(OR(J$16="Janvier",J$16="Avril",J$16="Juillet",J$16="Octobre"),$D28/4,0),0))) -> 1000 | K28: =IF($E28="Mensuel",$D28/12,IF($E28="Annuel",IF(K$16=$F28,$D28,0),IF($E28="Trimestriel",IF(OR(K$16="Janvier",K$16="Avril",K$16="Juillet",K$16="Octobre"),$D28/4,0),0))) -> 0 | L28: =IF($E28="Mensuel",$D28/12,IF($E28="Annuel",IF(L$16=$F28,$D28,0),IF($E28="Trimestriel",IF(OR(L$16="Janvier",L$16="Avril",L$16="Juillet",L$16="Octobre"),$D28/4,0),0))) -> 0 | M28: =IF($E28="Mensuel",$D28/12,IF($E28="Annuel",IF(M$16=$F28,$D28,0),IF($E28="Trimestriel",IF(OR(M$16="Janvier",M$16="Avril",M$16="Juillet",M$16="Octobre"),$D28/4,0),0))) -> 1000 | N28: =IF($E28="Mensuel",$D28/12,IF($E28="Annuel",IF(N$16=$F28,$D28,0),IF($E28="Trimestriel",IF(OR(N$16="Janvier",N$16="Avril",N$16="Juillet",N$16="Octobre"),$D28/4,0),0))) -> 0 | ... R28: =IF($E28="Mensuel",$D28/12,IF($E28="Annuel",IF(R$16=$F28,$D28,0),IF($E28="Trimestriel",IF(OR(R$16="Janvier",R$16="Avril",R$16="Juillet",R$16="Octobre"),$D28/4,0),0))) -> 0
A29: SOUS-TOTAL EXPLOITATION | D29: =SUM(D17:D28) -> 50157.6 | G29: =SUM(G17:G28) -> 9057.3 | H29: =SUM(H17:H28) -> 3977.3 | I29: =SUM(I17:I28) -> 3407.3 | J29: =SUM(J17:J28) -> 4407.3 | K29: =SUM(K17:K28) -> 3407.3 | L29: =SUM(L17:L28) -> 3407.3 | M29: =SUM(M17:M28) -> 4407.3 | N29: =SUM(N17:N28) -> 3407.3 | ... R29: =SUM(R17:R28) -> 3457.3
A32: 3. INVESTISSEMENT R&D ANNUEL
A33: Poste | B33: Nb protos | C33: Prix unitaire (€) | D33: Coût total (€) | F33: Mois décaissement | G33: Janvier | H33: Février | I33: Mars | J33: Avril | K33: Mai | L33: Juin | M33: Juillet | N33: Août | O33: Septembre | P33: Octobre | Q33: Novembre | R33: Décembre
A34: Proto recherche | B34: 24 | C34: ='Marges Produits'!E49*1.2 -> 1258.551 | D34: =B34*C34 -> 30205.224 | F34: 2 protos/mois | G34: 10000 | H34: 0 | I34: 0 | J34: 0 | K34: =$D$34/12 -> 2517.102 | L34: =$D$34/12 -> 2517.102 | M34: =$D$34/12 -> 2517.102 | N34: =$D$34/12 -> 2517.102 | O34: =$D$34/12 -> 2517.102 | P34: =$D$34/12 -> 2517.102 | Q34: =$D$34/12 -> 2517.102 | R34: =$D$34/12 -> 2517.102
A35: Veille concurrentielle | B35: 2 | C35: 2500 | D35: =B35*C35 -> 5000 | F35: Jan + Jul | G35: =$C$35 -> 2500 | H35: 0 | I35: 0 | J35: 0 | K35: 0 | L35: 0 | M35: =$C$35 -> 2500 | N35: 0 | O35: 0 | P35: 0 | Q35: 0 | R35: 0
A36: Pré-série homologation | B36: 10 | C36: =C34 -> 1258.551 | D36: =B36*C36 -> 12585.51 | F36: Avr + Août | G36: 0 | H36: 0 | I36: 0 | J36: =$D$36/2 -> 6292.755 | K36: 0 | L36: 0 | M36: 0 | N36: =$D$36/2 -> 6292.755 | O36: 0 | P36: 0 | Q36: 0 | R36: 0
A37: Homologation | B37: 2 | C37: 13669 | D37: =B37*C37 -> 27338 | F37: Avr + Août | G37: 0 | H37: 0 | I37: 0 | J37: =$C$37 -> 13669 | K37: 0 | L37: 0 | M37: 0 | N37: =C37 -> 13669 | O37: 0 | P37: 0 | Q37: 0 | R37: 0
A38: SOUS-TOTAL R&D | D38: =SUM(D34:D37) -> 75128.734 | G38: =SUM(G34:G37) -> 12500 | H38: =SUM(H34:H37) -> 0 | I38: =SUM(I34:I37) -> 0 | J38: =SUM(J34:J37) -> 19961.755 | K38: =SUM(K34:K37) -> 2517.102 | L38: =SUM(L34:L37) -> 2517.102 | M38: =SUM(M34:M37) -> 5017.102 | N38: =SUM(N34:N37) -> 22478.857 | ... R38: =SUM(R34:R37) -> 2517.102
A41: 4. CHARGES DE CROISSANCE
A42: ⚡ Déclencheur : activées à partir de 2029 (dès que N-1 > 500 ailes vendues)
A43: Poste | C43: Catégorie | D43: Montant (€/an) | E43: Fréquence | F43: Mois décaissement | G43: Janvier | H43: Février | I43: Mars | J43: Avril | K43: Mai | L43: Juin | M43: Juillet | N43: Août | O43: Septembre | P43: Octobre | Q43: Novembre | R43: Décembre
A44: Revalorisation JB (EURL : 1 800 → 3 000€/mois) | C44: Prestation | D44: 14400 | E44: Mensuel | F44: Tous les mois | G44: =$D44/12 -> 1200 | H44: =$D44/12 -> 1200 | I44: =$D44/12 -> 1200 | J44: =$D44/12 -> 1200 | K44: =$D44/12 -> 1200 | L44: =$D44/12 -> 1200 | M44: =$D44/12 -> 1200 | N44: =$D44/12 -> 1200 | ... R44: =$D44/12 -> 1200
A45: Revalorisation Thomas (1 400 → 3 200€ brut/mois) | C45: Salaire | D45: 23500 | E45: Mensuel | F45: Tous les mois | G45: =$D45/12 -> 1958.3333 | H45: =$D45/12 -> 1958.3333 | I45: =$D45/12 -> 1958.3333 | J45: =$D45/12 -> 1958.3333 | K45: =$D45/12 -> 1958.3333 | L45: =$D45/12 -> 1958.3333 | M45: =$D45/12 -> 1958.3333 | N45: =$D45/12 -> 1958.3333 | ... R45: =$D45/12 -> 1958.3333
A46: Jim — passage salarié (presta 27 396 → salarié 42 000€) | C46: Salaire | D46: 14604 | E46: Mensuel | F46: Tous les mois | G46: =$D46/12 -> 1217 | H46: =$D46/12 -> 1217 | I46: =$D46/12 -> 1217 | J46: =$D46/12 -> 1217 | K46: =$D46/12 -> 1217 | L46: =$D46/12 -> 1217 | M46: =$D46/12 -> 1217 | N46: =$D46/12 -> 1217 | ... R46: =$D46/12 -> 1217
A47: Assistant Logistique / SAV (embauche CDI, 2 000€ net) | C47: Salaire | D47: 34000 | E47: Mensuel | F47: Tous les mois | G47: =$D47/12 -> 2833.3333 | H47: =$D47/12 -> 2833.3333 | I47: =$D47/12 -> 2833.3333 | J47: =$D47/12 -> 2833.3333 | K47: =$D47/12 -> 2833.3333 | L47: =$D47/12 -> 2833.3333 | M47: =$D47/12 -> 2833.3333 | N47: =$D47/12 -> 2833.3333 | ... R47: =$D47/12 -> 2833.3333
A48: Budget Marketing & Salons | C48: Marketing | D48: 50000 | E48: Mensuel | F48: Tous les mois | G48: =$D48/12 -> 4166.6667 | H48: =$D48/12 -> 4166.6667 | I48: =$D48/12 -> 4166.6667 | J48: =$D48/12 -> 4166.6667 | K48: =$D48/12 -> 4166.6667 | L48: =$D48/12 -> 4166.6667 | M48: =$D48/12 -> 4166.6667 | N48: =$D48/12 -> 4166.6667 | ... R48: =$D48/12 -> 4166.6667
A49: SOUS-TOTAL CROISSANCE | D49: =SUM(D44:D48) -> 136504 | G49: =SUM(G44:G48) -> 11375.333 | H49: =SUM(H44:H48) -> 11375.333 | I49: =SUM(I44:I48) -> 11375.333 | J49: =SUM(J44:J48) -> 11375.333 | K49: =SUM(K44:K48) -> 11375.333 | L49: =SUM(L44:L48) -> 11375.333 | M49: =SUM(M44:M48) -> 11375.333 | N49: =SUM(N44:N48) -> 11375.333 | ... R49: =SUM(R44:R48) -> 11375.333
A51: RÉCAPITULATIF GÉNÉRAL | G51: Janvier | H51: Février | I51: Mars | J51: Avril | K51: Mai | L51: Juin | M51: Juillet | N51: Août | O51: Septembre | P51: Octobre | Q51: Novembre | R51: Décembre
A52: Masse salariale annuelle | D52: =D13 -> 83496 | G52: =G13 -> 10907.667 | H52: =H13 -> 6341.6667 | I52: =I13 -> 10907.667 | J52: =J13 -> 4341.6667 | K52: =K13 -> 8907.6667 | L52: =L13 -> 4341.6667 | M52: =M13 -> 7907.6667 | N52: =N13 -> 3341.6667 | ... R52: =R13 -> 4341.6667
A53: Charges d'exploitation annuelles | D53: =D29 -> 50157.6 | G53: =G29 -> 9057.3 | H53: =H29 -> 3977.3 | I53: =I29 -> 3407.3 | J53: =J29 -> 4407.3 | K53: =K29 -> 3407.3 | L53: =L29 -> 3407.3 | M53: =M29 -> 4407.3 | N53: =N29 -> 3407.3 | ... R53: =R29 -> 3457.3
A54: Investissement R&D annuel | D54: =D38 -> 75128.734 | G54: =G38 -> 12500 | H54: =H38 -> 0 | I54: =I38 -> 0 | J54: =J38 -> 19961.755 | K54: =K38 -> 2517.102 | L54: =L38 -> 2517.102 | M54: =M38 -> 5017.102 | N54: =N38 -> 22478.857 | ... R54: =R38 -> 2517.102
A55: Charges de croissance (2029+) | D55: =D49 -> 136504 | G55: =$D$55/12 -> 11375.333 | H55: =$D$55/12 -> 11375.333 | I55: =$D$55/12 -> 11375.333 | J55: =$D$55/12 -> 11375.333 | K55: =$D$55/12 -> 11375.333 | L55: =$D$55/12 -> 11375.333 | M55: =$D$55/12 -> 11375.333 | N55: =$D$55/12 -> 11375.333 | ... R55: =$D$55/12 -> 11375.333
A57: TOTAL CHARGES FIXES ANNÉE 1 | D57: =SUM(D52:D54) -> 208782.33 | G57: =G52+G53+G54 -> 32464.967 | H57: =H52+H53+H54 -> 10318.967 | I57: =I52+I53+I54 -> 14314.967 | J57: =J52+J53+J54 -> 28710.722 | K57: =K52+K53+K54 -> 14832.069 | L57: =L52+L53+L54 -> 10266.069 | M57: =M52+M53+M54 -> 17332.069 | N57: =N52+N53+N54 -> 29227.824 | ... R57: =R52+R53+R54 -> 10316.069
A58: 🚀 TOTAL CHARGES FIXES — PHASE 2 ( si N-1 > 500 ailes) | D58: =SUM(D52:D55) -> 345286.33 | G58: =SUM(G52:G55) -> 43840.3 | H58: =SUM(H52:H55) -> 21694.3 | I58: =SUM(I52:I55) -> 25690.3 | J58: =SUM(J52:J55) -> 40086.055 | K58: =SUM(K52:K55) -> 26207.402 | L58: =SUM(L52:L55) -> 21641.402 | M58: =SUM(M52:M55) -> 28707.402 | N58: =SUM(N52:N55) -> 40603.157 | ... R58: =SUM(R52:R55) -> 21691.402

Sheet Charges Variables
A1: CHARGES VARIABLES - PLUME PARAGLIDERS
A2: Charges liées au chiffre d'affaires
A4: CHARGES VARIABLES
A5: Poste | B5: Base de calcul | C5: Pourcentage
A7: Stock ( 66% aile stock / 33% aile démo ) | B7: Nb voiles vendues (forecast) par an | C7: 0.25
A8: Assurance | B8: % du chiffre d'affaire | C8: 0.008
A12: Transporteur
A13: Transport Thaïlande → Europe | B13: Par aile | C13: 40.57
A14: Transport stock → Europe | B14: Par aile | C14: 18.88
A16: Stockage
A17: Stockage | B17: Par aile | C17: 6.47
A19: Taxe douanière
A20: Frais de douane | B20: Prix usine | C20: 0.027
A21: Frais de dédouanement | B21: Prix usine | C21: 0.02
A23: Frais de paiement
A24: Stripe | C24: 0.015
A25: Briddge | C25: 0.011
A27: Marge des écoles partenaires
A28: marge ecole partenaire | C28: 0.19

Sheet Emprunt Bancaire
A1: EMPRUNT BANCAIRE - PLUME PARAGLIDERS
A3: CARACTÉRISTIQUES DU PRÊT
A4: Montant de l'emprunt | B4: 189000
A5: Durée | B5: 4 | C5: ans
A6: Taux d'intérêt | B6: 0.045
A7: Taux d'assurance | B7: 0.0036
A9: ÉCHÉANCIER DE REMBOURSEMENT
A10: Période | B10: Prêt Annuel (€) | C10: Assurance Annuelle (€) | D10: Total Annuel (€)
A11: Mois 1 - 48 | B11: =SUM('Emprunt Mensualité'!E27:F27) -> 51718.31 | C11: ='Emprunt Mensualité'!G27 -> 680.4 | D11: =B11+C11 -> 52398.71
A13: SYNTHÈSE SUR 4 ANS
A14: Mensualité totale | B14: =B27 -> 4367
A15: Coût total du crédit | B15: ='Emprunt Mensualité'!H63 -> 209594.88
A16: dont Intérêts | B16: ='Emprunt Mensualité'!F63 -> 17873.24
A17: dont Assurance | B17: ='Emprunt Mensualité'!G63 -> 2721.6
A19: IMPACT ANNUEL SUR TRÉSORERIE
A20: Charge annuelle de remboursement | B20: =D11 -> 52398.71
A24: DÉTAIL MENSUALITÉ CORRIGÉ
A25: Mensualité prêt (capital + intérêts) | B25: 4310
A26: Assurance mensuelle | B26: =ROUND(B4*B7/12,0) -> 57
A27: TOTAL MENSUALITÉ | B27: =B25+B26 -> 4367
A30: INTÉRÊTS ANNUELS (pour Compte de Résultat)
A31: Année | B31: Intérêts | C31: Assurance | D31: Total charges fin.
A32: 2026 | B32: 5289.03 | C32: 453.6 | D32: 5742.63
A33: 2027 | B33: 6261.51 | C33: 680.4 | D33: 6941.91
A34: 2028 | B34: 4173.24 | C34: 680.4 | D34: 4853.64
A35: 2029 | B35: 1989.02 | C35: 680.4 | D35: 2669.42
A36: 2030 | B36: 160.42 | C36: 226.8 | D36: 387.22
A37: Total intérêts | B37: =SUM(B32:B36) -> 17873.22 | C37: =SUM(C32:C36) -> 2721.6 | D37: =SUM(D32:D36) -> 20594.82
A38: Note: Seuls les intérêts sont des charges dans le Compte de Résultat.
A39: Le remboursement du capital reste dans le Plan de Trésorerie.
A42: ━━━━━━━━━━━━━━━━━━━━━━━━━━━━━━━━━━━━━━━━━━━━━━━━━━━━━━━━━━━━━━━━
A43: TABLEAU D'AMORTISSEMENT - CAPITAL RESTANT DÛ (CRD)
A44: Fin d'année | B44: Capital remboursé | C44: Intérêts payés | D44: CRD début période
A45: 2025
A46: 2026 (déblocage Mai) | B46: 29190 | C46: 5289 | D46: 189000
A47: 2027 | B47: 45457 | C47: 6262 | D47: 159810
A48: 2028 | B48: 47545 | C48: 4173 | D48: 114353
A49: 2029 | B49: 49729 | C49: 1989 | D49: 66808
A50: 2030 | B50: 17079 | C50: 160 | D50: 17079
A51: TOTAL | B51: 189000 | C51: 17873
A53: ⚙ Réconciliation avec le Bilan Prévisionnel :
A54: Le CRD début 2026 = 189 000 € (déblocage prévu mai 2026)
A55: Le CRD début 2027 = 159 810 € = CRD fin 2026 après remboursements
A56: Note: Le bilan utilise des CRD ajustés pour le décalage comptable

Sheet Emprunt Mensualité
A1: TABLEAU DES MENSUALITÉS - PLUME PARAGLIDERS
A2: Emprunt : 189 000 € | Taux : 4.50% | Durée : 48 mois | Début : Mai 2026
A4: N° | B4: Mois | C4: Année | D4: CRD début | E4: Capital | F4: Intérêts | G4: Assurance | H4: Mensualité totale | I4: CRD fin
A5: 1 | B5: Mai | C5: 2026 | D5: 189000 | E5: 3601.11 | F5: 708.75 | G5: 56.7 | H5: 4366.56 | I5: 185398.89
A6: 2 | B6: Juin | C6: 2026 | D6: 185398.89 | E6: 3614.61 | F6: 695.25 | G6: 56.7 | H6: 4366.56 | I6: 181784.28
A7: 3 | B7: Juillet | C7: 2026 | D7: 181784.28 | E7: 3628.17 | F7: 681.69 | G7: 56.7 | H7: 4366.56 | I7: 178156.11
A8: 4 | B8: Août | C8: 2026 | D8: 178156.11 | E8: 3641.77 | F8: 668.09 | G8: 56.7 | H8: 4366.56 | I8: 174514.34
A9: 5 | B9: Septembre | C9: 2026 | D9: 174514.34 | E9: 3655.43 | F9: 654.43 | G9: 56.7 | H9: 4366.56 | I9: 170858.91
A10: 6 | B10: Octobre | C10: 2026 | D10: 170858.91 | E10: 3669.14 | F10: 640.72 | G10: 56.7 | H10: 4366.56 | I10: 167189.77
A11: 7 | B11: Novembre | C11: 2026 | D11: 167189.77 | E11: 3682.9 | F11: 626.96 | G11: 56.7 | H11: 4366.56 | I11: 163506.87
A12: 8 | B12: Décembre | C12: 2026 | D12: 163506.87 | E12: 3696.71 | F12: 613.15 | G12: 56.7 | H12: 4366.56 | I12: 159810.16
B13: Sous-total 2026 | E13: =SUM(E5:E12) -> 29189.84 | F13: =SUM(F5:F12) -> 5289.04 | G13: =SUM(G5:G12) -> 453.6 | H13: =SUM(H5:H12) -> 34932.48
A15: 9 | B15: Janvier | C15: 2027 | D15: 159810.16 | E15: 3710.57 | F15: 599.29 | G15: 56.7 | H15: 4366.56 | I15: 156099.59
A16: 10 | B16: Février | C16: 2027 | D16: 156099.59 | E16: 3724.49 | F16: 585.37 | G16: 56.7 | H16: 4366.56 | I16: 152375.11
A17: 11 | B17: Mars | C17: 2027 | D17: 152375.11 | E17: 3738.45 | F17: 571.41 | G17: 56.7 | H17: 4366.56 | I17: 148636.66
A18: 12 | B18: Avril | C18: 2027 | D18: 148636.66 | E18: 3752.47 | F18: 557.39 | G18: 56.7 | H18: 4366.56 | I18: 144884.18
A19: 13 | B19: Mai | C19: 2027 | D19: 144884.18 | E19: 3766.54 | F19: 543.32 | G19: 56.7 | H19: 4366.56 | I19: 141117.64
A20: 14 | B20: Juin | C20: 2027 | D20: 141117.64 | E20: 3780.67 | F20: 529.19 | G20: 56.7 | H20: 4366.56 | I20: 137336.97
A21: 15 | B21: Juillet | C21: 2027 | D21: 137336.97 | E21: 3794.85 | F21: 515.01 | G21: 56.7 | H21: 4366.56 | I21: 133542.13
A22: 16 | B22: Août | C22: 2027 | D22: 133542.13 | E22: 3809.08 | F22: 500.78 | G22: 56.7 | H22: 4366.56 | I22: 129733.05
A23: 17 | B23: Septembre | C23: 2027 | D23: 129733.05 | E23: 3823.36 | F23: 486.5 | G23: 56.7 | H23: 4366.56 | I23: 125909.69
A24: 18 | B24: Octobre | C24: 2027 | D24: 125909.69 | E24: 3837.7 | F24: 472.16 | G24: 56.7 | H24: 4366.56 | I24: 122071.99
A25: 19 | B25: Novembre | C25: 2027 | D25: 122071.99 | E25: 3852.09 | F25: 457.77 | G25: 56.7 | H25: 4366.56 | I25: 118219.91
A26: 20 | B26: Décembre | C26: 2027 | D26: 118219.91 | E26: 3866.53 | F26: 443.32 | G26: 56.7 | H26: 4366.56 | I26: 114353.37
B27: Sous-total 2027 | E27: =SUM(E15:E26) -> 45456.8 | F27: =SUM(F15:F26) -> 6261.51 | G27: =SUM(G15:G26) -> 680.4 | H27: =SUM(H15:H26) -> 52398.72 | J27: =SUM(E27:F27) -> 51718.31
A29: 21 | B29: Janvier | C29: 2028 | D29: 114353.37 | E29: 3881.03 | F29: 428.83 | G29: 56.7 | H29: 4366.56 | I29: 110472.34
A30: 22 | B30: Février | C30: 2028 | D30: 110472.34 | E30: 3895.59 | F30: 414.27 | G30: 56.7 | H30: 4366.56 | I30: 106576.75
A31: 23 | B31: Mars | C31: 2028 | D31: 106576.75 | E31: 3910.2 | F31: 399.66 | G31: 56.7 | H31: 4366.56 | I31: 102666.55
A32: 24 | B32: Avril | C32: 2028 | D32: 102666.55 | E32: 3924.86 | F32: 385 | G32: 56.7 | H32: 4366.56 | I32: 98741.69
A33: 25 | B33: Mai | C33: 2028 | D33: 98741.69 | E33: 3939.58 | F33: 370.28 | G33: 56.7 | H33: 4366.56 | I33: 94802.12
A34: 26 | B34: Juin | C34: 2028 | D34: 94802.12 | E34: 3954.35 | F34: 355.51 | G34: 56.7 | H34: 4366.56 | I34: 90847.77
A35: 27 | B35: Juillet | C35: 2028 | D35: 90847.77 | E35: 3969.18 | F35: 340.68 | G35: 56.7 | H35: 4366.56 | I35: 86878.59
A36: 28 | B36: Août | C36: 2028 | D36: 86878.59 | E36: 3984.06 | F36: 325.79 | G36: 56.7 | H36: 4366.56 | I36: 82894.52
A37: 29 | B37: Septembre | C37: 2028 | D37: 82894.52 | E37: 3999 | F37: 310.85 | G37: 56.7 | H37: 4366.56 | I37: 78895.52
A38: 30 | B38: Octobre | C38: 2028 | D38: 78895.52 | E38: 4014 | F38: 295.86 | G38: 56.7 | H38: 4366.56 | I38: 74881.52
A39: 31 | B39: Novembre | C39: 2028 | D39: 74881.52 | E39: 4029.05 | F39: 280.81 | G39: 56.7 | H39: 4366.56 | I39: 70852.46
A40: 32 | B40: Décembre | C40: 2028 | D40: 70852.46 | E40: 4044.16 | F40: 265.7 | G40: 56.7 | H40: 4366.56 | I40: 66808.3
B41: Sous-total 2028 | E41: =SUM(E29:E40) -> 47545.06 | F41: =SUM(F29:F40) -> 4173.24 | G41: =SUM(G29:G40) -> 680.4 | H41: =SUM(H29:H40) -> 52398.72
A43: 33 | B43: Janvier | C43: 2029 | D43: 66808.3 | E43: 4059.33 | F43: 250.53 | G43: 56.7 | H43: 4366.56 | I43: 62748.97
A44: 34 | B44: Février | C44: 2029 | D44: 62748.97 | E44: 4074.55 | F44: 235.31 | G44: 56.7 | H44: 4366.56 | I44: 58674.42
A45: 35 | B45: Mars | C45: 2029 | D45: 58674.42 | E45: 4089.83 | F45: 220.03 | G45: 56.7 | H45: 4366.56 | I45: 54584.59
A46: 36 | B46: Avril | C46: 2029 | D46: 54584.59 | E46: 4105.17 | F46: 204.69 | G46: 56.7 | H46: 4366.56 | I46: 50479.43
A47: 37 | B47: Mai | C47: 2029 | D47: 50479.43 | E47: 4120.56 | F47: 189.3 | G47: 56.7 | H47: 4366.56 | I47: 46358.87
A48: 38 | B48: Juin | C48: 2029 | D48: 46358.87 | E48: 4136.01 | F48: 173.85 | G48: 56.7 | H48: 4366.56 | I48: 42222.85
A49: 39 | B49: Juillet | C49: 2029 | D49: 42222.85 | E49: 4151.52 | F49: 158.34 | G49: 56.7 | H49: 4366.56 | I49: 38071.33
A50: 40 | B50: Août | C50: 2029 | D50: 38071.33 | E50: 4167.09 | F50: 142.77 | G50: 56.7 | H50: 4366.56 | I50: 33904.24
A51: 41 | B51: Septembre | C51: 2029 | D51: 33904.24 | E51: 4182.72 | F51: 127.14 | G51: 56.7 | H51: 4366.56 | I51: 29721.52
A52: 42 | B52: Octobre | C52: 2029 | D52: 29721.52 | E52: 4198.4 | F52: 111.46 | G52: 56.7 | H52: 4366.56 | I52: 25523.12
A53: 43 | B53: Novembre | C53: 2029 | D53: 25523.12 | E53: 4214.15 | F53: 95.71 | G53: 56.7 | H53: 4366.56 | I53: 21308.97
A54: 44 | B54: Décembre | C54: 2029 | D54: 21308.97 | E54: 4229.95 | F54: 79.91 | G54: 56.7 | H54: 4366.56 | I54: 17079.02
B55: Sous-total 2029 | E55: =SUM(E43:E54) -> 49729.28 | F55: =SUM(F43:F54) -> 1989.04 | G55: =SUM(G43:G54) -> 680.4 | H55: =SUM(H43:H54) -> 52398.72
A57: 45 | B57: Janvier | C57: 2030 | D57: 17079.02 | E57: 4245.81 | F57: 64.05 | G57: 56.7 | H57: 4366.56 | I57: 12833.21
A58: 46 | B58: Février | C58: 2030 | D58: 12833.21 | E58: 4261.73 | F58: 48.12 | G58: 56.7 | H58: 4366.56 | I58: 8571.47
A59: 47 | B59: Mars | C59: 2030 | D59: 8571.47 | E59: 4277.72 | F59: 32.14 | G59: 56.7 | H59: 4366.56 | I59: 4293.76
A60: 48 | B60: Avril | C60: 2030 | D60: 4293.76 | E60: 4293.76 | F60: 16.1 | G60: 56.7 | H60: 4366.56 | I60: 0
B61: Sous-total 2030 | E61: =SUM(E57:E60) -> 17079.02 | F61: =SUM(F57:F60) -> 160.41 | G61: =SUM(G57:G60) -> 226.8 | H61: =SUM(H57:H60) -> 17466.24
B63: TOTAL GÉNÉRAL | E63: =E13+E27+E41+E55+E61 -> 189000 | F63: =F13+F27+F41+F55+F61 -> 17873.24 | G63: =G13+G27+G41+G55+G61 -> 2721.6 | H63: =H13+H27+H41+H55+H61 -> 209594.88

Sheet AFFECTATION EMPRUNT 
A1: 🏦 AFFECTATION DE L'EMPRUNT BANCAIRE — 189 000 €
A2: Emprunt Banque Populaire • 4 ans • Taux 4,5% • Échéance mensuelle 4 367 €
A4: Poste de financement | B4: Montant (€) | C4: % Emprunt | D4: Détail / Justification
A5: Homologation EN (pré-séries + tests labo) | B5: 35000 | C5: =B5/189000 -> 0.18518519 | D5: Pré-séries 10 ailes × 2 modèles + tests Air Turquoise. Obligatoire pour commercialiser (norme EN 926).
A6: Stock de lancement (ailes certifiées) | B6: 110000 | C6: =B6/189000 -> 0.58201058 | D6: ~105 ailes × coût de revient 1 049€. Actif physique tangible, stocké en France, valeur de revente > coût.
A7: Fonds de roulement (charges fixes 3 mois) | B7: 30000 | C7: =B7/189000 -> 0.15873016 | D7: Couverture charges fixes incompressibles avant montée en CA (salaires, loyers, assurances).
A8: Marge de sécurité | B8: 14000 | C8: =B8/189000 -> 0.074074074 | D8: Buffer 7% pour aléas logistiques, surcoûts qualité, ou retard de livraison usine.
A9: TOTAL EMPRUNT | B9: =SUM(B5:B8) -> 189000 | C9: =SUM(C5:C8) -> 1
A12: 📝 Les montants ci-dessus sont indicatifs. L'affectation réelle sera ajustée selon le calendrier de déblocage (mai 2026) et l'avancement des homologations EN.
A14: 📦 58% de l'emprunt finance du stock physique (ailes certifiées EN, stockées en France). En cas de défaillance, ces actifs conservent une valeur de revente estimée à 60-80% du coût d'acquisition.

Sheet Marges Produits
A1: MARGES PRODUITS - PLUME PARAGLIDERS
A3: 1. VENTE SCHOOL PACK (Vente directe écoles)
A4: Paiement immédiat via site PLUME
A5: Modèle | B5: A+ Classic
A6: Prix de vente TTC | B6: 2155
A7: Prix de vente HT | B7: =B6/1.2 -> 1795.8333
A8: Marge Partenaire | B8: 0
A10: Prix usine (aile + bags + goodies) | B10: =838+150 -> 988
A11: Transports Asie - europe | B11: ='Charges Variables'!C13 -> 40.57
A12: stockage | B12: ='Charges Variables'!C17 -> 6.47
A13: Transport Stock Europe | B13: ='Charges Variables'!C14 -> 18.88
A14: Frais de douane (2,7%) | B14: =ROUND(B10*'Charges Variables'!C20,2) -> 26.68
A15: Frais de dédouanement (2%) | B15: =ROUND(B10*'Charges Variables'!C21,2) -> 19.76
A16: Total des couts de reviens | B16: =SUM(B10:B15) -> 1100.36
A17: Frais payment | B17: 0
A19: MARGE BRUTE (€) | B19: =B7-B16-B17 -> 695.47333
A20: MARGE BRUTE (%) | B20: =1/B7*B19 -> 0.38727053
A22: 2. VENTE B2B2C (Site internet avec partenaires)
A23: Marge partenaire : 19% du prix HT
A24: Modèle | B24: A+ DLS | C24: B- Ultra | D24: K2- Ultra
A25: Prix de vente TTC | B25: 3450 | C25: 4200 | D25: 2800
A26: Prix de vente HT | B26: =B25/1.2 -> 2875 | C26: =C25/1.2 -> 3500 | D26: =D25/1.2 -> 2333.3333
A30: Prix usine ( aile+sac+goodies) | B30: =838+150 -> 988 | C30: 1099 | D30: 680
A31: Transports Asie - europe | B31: ='Charges Variables'!$C$13 -> 40.57 | C31: ='Charges Variables'!$C$13 -> 40.57 | D31: ='Charges Variables'!$C$13 -> 40.57
A32: stockage | B32: ='Charges Variables'!$C$17 -> 6.47 | C32: ='Charges Variables'!$C$17 -> 6.47 | D32: ='Charges Variables'!$C$17 -> 6.47
A33: Transport Stock Europe | B33: ='Charges Variables'!$C$14 -> 18.88 | C33: ='Charges Variables'!$C$14 -> 18.88 | D33: ='Charges Variables'!$C$14 -> 18.88
A34: Frais de douane (2,7%) | B34: =ROUND(B30*'Charges Variables'!$C$20,2) -> 26.68 | C34: =ROUND(C30*'Charges Variables'!$C$20,2) -> 29.67 | D34: =ROUND(D30*'Charges Variables'!$C$20,2) -> 18.36
A35: Frais de dédouanement (2%) | B35: =ROUND(B30*'Charges Variables'!$C$21,2) -> 19.76 | C35: =ROUND(C30*'Charges Variables'!$C$21,2) -> 21.98 | D35: =ROUND(D30*'Charges Variables'!$C$21,2) -> 13.6
A36: Total des couts de reviens | B36: =SUM(B30:B35) -> 1100.36 | C36: =SUM(C30:C35) -> 1216.57 | D36: =SUM(D30:D35) -> 777.88
A37: Frais payment | B37: =0.015*B25 -> 51.75 | C37: =0.015*C25 -> 63 | D37: =0.015*D25 -> 42
A38: Marge Partenaire (19%) | B38: =B26*'Charges Variables'!$C$28 -> 546.25 | C38: =C26*'Charges Variables'!$C$28 -> 665 | D38: =D26*'Charges Variables'!$C$28 -> 443.33333
A39: MARGE BRUTE (€) | B39: =B26-B38-B36-B37 -> 1176.64 | C39: =C26-C38-C36-C37 -> 1555.43 | D39: =D26-D38-D36-D37 -> 1070.12
A40: MARGE BRUTE (%) | B40: =1/B26*B39 -> 0.40926609 | C40: =1/C26*C39 -> 0.44440857 | D40: =1/D26*D39 -> 0.45862286
A42: 3. Hypothèse 1 de la répartition des ventes
A43: Canal de vente | B43: Produit | C43: Prix HT | D43: Marge € | E43: Cout de reviens | F43: Proportions des ventes | G43: Marge Brute
A44: School Pack | B44: A+ Classic | C44: =B7 -> 1795.8333 | D44: =B19 -> 695.47333 | E44: =B16 -> 1100.36 | F44: 0.3 | G44: =B20 -> 0.38727053
A45: B2B2C | B45: A+ Classic | C45: =B26 -> 2875 | D45: =B39 -> 1176.64 | E45: =B36 -> 1100.36 | F45: 0.2 | G45: =B40 -> 0.40926609
A46: B2B2C | B46: B- Ultra | C46: =C26 -> 3500 | D46: =C39 -> 1555.43 | E46: =C36 -> 1216.57 | F46: 0.25 | G46: =C40 -> 0.44440857
A47: B2B2C | B47: K2- Ultra | C47: =D26 -> 2333.3333 | D47: =D39 -> 1070.12 | E47: =D36 -> 777.88 | F47: 0.25 | G47: =D40 -> 0.45862286
A49: Hypothese 1: prix moyen / produit | C49: =(C44*F44)+(C45*F45)+(C46*F46)+(C47*F47) -> 2572.0833 | D49: =(D44*F44)+(D45*F45)+(D46*F46)+(D47*F47) -> 1100.3575 | E49: =(E44*F44)+(E45*F45)+(E46*F46)+(E47*F47) -> 1048.7925 | G49: =1/C49*D49 -> 0.42780787
A51: hypothese 2 "+1000ailes/an" : prix moyen / produit + 5% | C51: =C49*1.05 -> 2700.6875 | D51: =C51-(C49-D49) -> 1228.9617 | E51: =E49 -> 1048.7925 | G51: =1/C51*D51 -> 0.45505512

Sheet Financement
A1: FINANCEMENT & MONTAGE SOCIÉTÉ - PLUME PARAGLIDERS
A3: MONTAGE SOCIÉTÉ - CAPITAL SOCIAL
A4: Associé / Source | B4: Apport total | C4: Capital social | D4: Part capital
A5: Jean-Baptiste Chandelier | B5: 104000 | C5: 55000 | D5: 0.55
A6: Thomas Pierre-Bes | B6: 85000 | C6: 45000 | D6: 0.45
A7: Sous-total Associés | B7: =SUM(B5:B6) -> 189000 | C7: =SUM(C5:C6) -> 100000 | D7: =SUM(D5:D6) -> 1
A8: correspond aux comptes courants d'associés (89k€).
A11: FINANCEMENTS EXTERNES
A12: Source | B12: Montant | C12: Type | D12: Année
A13: Banque Populaire - Emprunt 1/1 | B13: ='Emprunt Bancaire'!B4 -> 189000 | C13: Emprunt 4 ans | D13: 2026
A14: Sous-total Financements Externes | B14: =B13 -> 189000
A17: APPORT COMPLÉMENTAIRE ANNÉE 2
A18: Source | B18: Montant | C18: Objet | D18: Année
A19: Avoir EURL JB Chandelier | B19: 50000 | C19: Marketing & Tests | D19: 2027
A20: Note: Prestation externe pour fonds de roulement
A22: RÉCAPITULATIF FINANCEMENT TOTAL
A23: Apports associés (Année 1) | B23: =B7 -> 189000
A24: Financements externes (Année 1) | B24: =B14 -> 189000
A25: Avoir EURL JB Chandelier (Année 2) | B25: =B19 -> 50000
A26: TOTAL FINANCEMENT | B26: =SUM(B23:B25) -> 428000
A28: FLUX DE FINANCEMENT PAR ANNÉE
A29: Année | B29: Entrées | C29: Détail
A30: 2025 | B30: 0
A31: 2026 | B31: =B23+B24 -> 378000 | C31: Associés + Emprunt
A32: 2027 | B32: =B25 -> 50000 | C32: Avoir EURL JB Chandelier
A33: 2028+ | B33: 0 | C33: -
A38: 📅 CALENDRIER DE DÉBLOCAGE (Création 18/12/2025)
A39: Decembre 2025 | B39: Capital social | C39: 100000
A40: Janvier 2026 | B40: Comptes courants associés | C40: 89000
A41: Mai 2026 | B41: Emprunt Banque Populaire | C41: 189000
A42: Mars 2027 | B42: Avoir EURL JB | C42: 50000
A47: Sécurité financière des fondateurs
A48: Les fondateurs disposent de revenus complémentaires qui assurent leur stabilité personnelle pendant la phase de lancement :
A50: JB Chandelier — revenus via son EURL Chandelier (prestations vidéo, droits d'image, partenariats Salewa, Blacksheep, Serre Chevalier), revenus patrimoniaux personnels, brevets d'État parapente/ski.
A52: Thomas Pierre-Bes — auto-entrepreneur (R&D parapente, impression 3D, prestations vidéo), brevets d'État kitesurf.
A54: La rémunération via Plume Paragliders est volontairement contenue pour préserver la trésorerie. Les comptes courants d'associés (89 000 €) seront remboursés une fois la rentabilité atteinte, avec revalorisation progressive des rémunérations à partir du seuil de ~180 ailes/an.
A56: Le capital de 100 000 € est dimensionné au juste besoin de la phase de lancement. JB Chandelier dispose par ailleurs d'un patrimoine personnel significatif, mobilisable en renfort si nécessaire pour accompagner l'atteinte de la rentabilité.

Sheet Scénarios
A1: SCÉNARIOS DE VENTES - PLUME PARAGLIDERS
A3: Répartition des ventes
A4: {='Marges Produits'!A43:F43} -> Canal de vente | B4: Produit | C4: Prix HT | D4: Marge € | E4: Cout de reviens | F4: Proportions des ventes
A5: {='Marges Produits'!A44:F44} -> School Pack | B5: A+ Classic | C5: 1795.8333 | D5: 695.47333 | E5: 1100.36 | F5: 0.3
A6: {='Marges Produits'!A45:F45} -> B2B2C | B6: A+ Classic | C6: 2875 | D6: 1176.64 | E6: 1100.36 | F6: 0.2
A7: {='Marges Produits'!A46:F46} -> B2B2C | B7: B- Ultra | C7: 3500 | D7: 1555.43 | E7: 1216.57 | F7: 0.25
A8: {='Marges Produits'!A47:F47} -> B2B2C | B8: K2- Ultra | C8: 2333.3333 | D8: 1070.12 | E8: 777.88 | F8: 0.25
A10: {='Marges Produits'!A49:E49} -> Hypothese 1: prix moyen / produit | B10: 0 | C10: 2572.0833 | D10: 1100.3575 | E10: 1048.7925
A13: VOLUMES DE VENTES (Nombre d'ailes)
A14: Année | B14: 2025 | C14: 2026 | D14: 2027 | E14: 2028 | F14: 2029 | G14: 2030 | H14: 2031
A16: 🟠 RÉALISTE | B16: 0 | C16: 75 | D16: 250 | E16: 550 | F16: 800 | G16: 1000 | H16: 1000
A17: 🔴 POINT MORT (minimum syndical) | B17: ='Analyse Point Mort'!B19 -> 0 | C17: ='Analyse Point Mort'!C19 -> 0 | D17: ='Analyse Point Mort'!D19 -> 139 | E17: ='Analyse Point Mort'!E19 -> 242 | F17: ='Analyse Point Mort'!F19 -> 242 | G17: ='Analyse Point Mort'!G19 -> 187 | H17: ='Analyse Point Mort'!H19 -> 187
A19: SCÉNARIO RÉALISTE - DÉTAIL
A20: Volume TOTAL | B20: =B16 -> 0 | C20: =C16 -> 75 | D20: =D16 -> 250 | E20: =E16 -> 550 | F20: =F16 -> 800 | G20: =G16 -> 1000 | H20: =H16 -> 1000
A21: résultat net | B21: ='Compte de Résultat'!B34 -> -8857.8558 | C21: ='Compte de Résultat'!C34 -> -128458.89 | D21: ='Compte de Résultat'!D34 -> 50265.066 | E21: ='Compte de Résultat'!E34 -> 382760.59 | F21: ='Compte de Résultat'!F34 -> 518386.01 | G21: ='Compte de Résultat'!G34 -> 690585.36 | H21: ='Compte de Résultat'!H34 -> 756513.57
A22: CA TOTAL (HT) | B22: ='Compte de Résultat'!B13 -> 0 | C22: ='Compte de Résultat'!C13 -> 192906.25 | D22: ='Compte de Résultat'!D13 -> 643020.83 | E22: ='Compte de Résultat'!E13 -> 1414645.8 | F22: ='Compte de Résultat'!F13 -> 2057666.7 | G22: ='Compte de Résultat'!G13 -> 2572083.3 | H22: ='Compte de Résultat'!H13 -> 2700687.5
A29: COMPARAISON CA TOTAL (HT)
A31: 🟠 CA Réaliste | B31: =B22 -> 0 | C31: =C22 -> 192906.25 | D31: =D22 -> 643020.83 | E31: =E22 -> 1414645.8 | F31: =F22 -> 2057666.7 | G31: =G22 -> 2572083.3 | H31: =H22 -> 2700687.5
A34: 📌 STRATÉGIE PLAFOND 1000 AILES
A35: Au-delà de 1000 ailes/an, l'objectif n'est plus d'augmenter le volume mais la marge.
A36: Stratégie : produire légèrement moins que la demande pour valoriser le produit et augmenter le prix.
A37: Cette limitation volontaire de la production permet de renforcer le positionnement premium.

Sheet Plan Trésorerie Mensuel
A1: PLAN DE TRÉSORERIE MENSUEL - PLUME PARAGLIDERS
A2: Création : 18 décembre 2025 • Délais de financement réalistes
A4: 📅 ANNÉE 2026 : LANCEMENT
B5: Déc 25 | C5: Jan | D5: Fév | E5: Mar | F5: Avr | G5: Mai | H5: Juin | I5: Juil | J5: Août | K5: Sept | L5: Oct | M5: Nov | N5: Déc | O5: TOTAL
A6: ENTRÉES
A7: Capital social | B7: =Dashboard!B9 -> 100000 | C7: 0 | D7: 0 | E7: 0 | F7: 0 | G7: 0 | H7: 0 | I7: 0 | J7: 0 | K7: 0 | L7: 0 | M7: 0 | N7: 0 | O7: =SUM(B7:N7) -> 100000
A8: Comptes courants associés | B8: 0 | C8: 89000 | D8: 0 | E8: 0 | F8: 0 | G8: 0 | H8: 0 | I8: 0 | J8: 0 | K8: 0 | L8: 0 | M8: 0 | N8: 0 | O8: =SUM(B8:N8) -> 89000
A9: Emprunt bancaire | B9: 0 | C9: 0 | D9: 0 | F9: 0 | G9: ='Emprunt Bancaire'!B4 -> 189000 | H9: 0 | I9: 0 | J9: 0 | K9: 0 | L9: 0 | M9: 0 | N9: 0 | O9: =SUM(B9:N9) -> 189000
O10: =SUM(O8:O9) -> 278000
A12: CA Ventes (HT) | B12: 0 | C12: =C35*'Marges Produits'!$C$49 -> 0 | D12: =D35*'Marges Produits'!$C$49 -> 0 | E12: =E35*'Marges Produits'!$C$49 -> 0 | F12: =F35*'Marges Produits'!$C$49 -> 12860.417 | G12: =G35*'Marges Produits'!$C$49 -> 18004.583 | H12: =H35*'Marges Produits'!$C$49 -> 23148.75 | I12: =I35*'Marges Produits'!$C$49 -> 30865 | J12: =J35*'Marges Produits'!$C$49 -> 30865 | ... N12: =N35*'Marges Produits'!$C$49 -> 12860.417 | O12: =SUM(B12:N12) -> 192906.25
A13: Total entrées | B13: =SUM(B7:B12) -> 100000 | C13: =SUM(C7:C12) -> 89000 | D13: =SUM(D7:D12) -> 0 | E13: =SUM(E7:E12) -> 0 | F13: =SUM(F7:F12) -> 12860.417 | G13: =SUM(G7:G12) -> 207004.58 | H13: =SUM(H7:H12) -> 23148.75 | I13: =SUM(I7:I12) -> 30865 | ... N13: =SUM(N7:N12) -> 12860.417 | O13: =SUM(B13:N13) -> 570906.25
A15: SORTIES
A16: Frais création | B16: ='Frais de lancement'!B9 -> 3803 | C16: 0 | D16: 0 | E16: 0 | F16: 0 | G16: 0 | H16: 0 | I16: 0 | J16: 0 | K16: 0 | L16: 0 | M16: 0 | N16: 0 | O16: =SUM(B16:N16) -> 3803
A17: Frais prototype | B17: 0 | C17: ='Charges Fixes Plume'!G34 -> 10000 | D17: ='Charges Fixes Plume'!H34 -> 0 | E17: ='Charges Fixes Plume'!I34 -> 0 | F17: ='Charges Fixes Plume'!J34 -> 0 | G17: ='Charges Fixes Plume'!K34 -> 2517.102 | H17: ='Charges Fixes Plume'!L34 -> 2517.102 | I17: ='Charges Fixes Plume'!M34 -> 2517.102 | J17: ='Charges Fixes Plume'!N34 -> 2517.102 | ... N17: ='Charges Fixes Plume'!R34 -> 2517.102 | O17: =SUM(B17:N17) -> 30136.816
A18: Veille concurrentielle | B18: 0 | C18: 2500 | D18: 0 | E18: 0 | F18: 0 | G18: 0 | H18: 0 | I18: 2500 | J18: 0 | K18: 0 | L18: 0 | M18: 0 | N18: 0 | O18: =SUM(B18:N18) -> 5000
A19: Masse salariale | B19: ='Charges Fixes Plume'!R$13/2 -> 2170.8333 | C19: ='Charges Fixes Plume'!G13 -> 10907.667 | D19: ='Charges Fixes Plume'!H13 -> 6341.6667 | E19: ='Charges Fixes Plume'!I13 -> 10907.667 | F19: ='Charges Fixes Plume'!J13 -> 4341.6667 | G19: ='Charges Fixes Plume'!K13 -> 8907.6667 | H19: ='Charges Fixes Plume'!L13 -> 4341.6667 | I19: ='Charges Fixes Plume'!M13 -> 7907.6667 | J19: ='Charges Fixes Plume'!N13 -> 3341.6667 | ... N19: ='Charges Fixes Plume'!R13 -> 4341.6667 | O19: =SUM(B19:N19) -> 85666.833
A20: CHARGES DE CROISSANCE ( si n-1 = + 500ailes)
A21: Charges exploitation | B21: ='Charges Fixes Plume'!R$29/2 -> 1728.65 | C21: ='Charges Fixes Plume'!G29 -> 9057.3 | D21: ='Charges Fixes Plume'!H29 -> 3977.3 | E21: ='Charges Fixes Plume'!I29 -> 3407.3 | F21: ='Charges Fixes Plume'!J29 -> 4407.3 | G21: ='Charges Fixes Plume'!K29 -> 3407.3 | H21: ='Charges Fixes Plume'!L29 -> 3407.3 | I21: ='Charges Fixes Plume'!M29 -> 4407.3 | J21: ='Charges Fixes Plume'!N29 -> 3407.3 | ... N21: ='Charges Fixes Plume'!R29 -> 3457.3 | O21: =SUM(B21:N21) -> 51886.25
A22: Pré-série homologation (10) | B22: 0 | C22: 0 | D22: 0 | E22: ='Charges Fixes Plume'!C36*4 -> 5034.204 | F22: 0 | G22: =4*'Charges Fixes Plume'!$C$36 -> 5034.204 | H22: 0 | I22: 0 | K22: 0 | L22: 0 | M22: 0 | N22: 0 | O22: =SUM(B22:N22) -> 10068.408
A23: Tests homologation EN | B23: 0 | C23: 0 | D23: 0 | F23: 11172 | G23: 0 | H23: ='Charges Fixes Plume'!C37 -> 13669 | I23: 0 | K23: 0 | L23: 0 | M23: 0 | N23: 0 | O23: =SUM(B23:N23) -> 24841
A24: Production stock parapente | B24: 0 | C24: =C34*'Marges Produits'!$E$49 -> 0 | D24: =D34*'Marges Produits'!$E$49 -> 0 | E24: =E34*'Marges Produits'!$E$49 -> 0 | F24: =F34*'Marges Produits'!$E$49 -> 10487.925 | G24: =G34*'Marges Produits'!$E$49 -> 20975.85 | H24: =H34*'Marges Produits'!$E$49 -> 20975.85 | I24: =I34*'Marges Produits'!$E$49 -> 18878.265 | J24: =J34*'Marges Produits'!$E$49 -> 10487.925 | ... N24: =N34*'Marges Produits'!$E$49 -> 0 | O24: =SUM(B24:N24) -> 94391.325
A25: Remboursement emprunt | B25: 0 | C25: 0 | D25: 0 | E25: 0 | G25: ='Emprunt Bancaire'!$B$27 -> 4367 | H25: ='Emprunt Bancaire'!$B$27 -> 4367 | I25: ='Emprunt Bancaire'!$B$27 -> 4367 | J25: ='Emprunt Bancaire'!$B$27 -> 4367 | K25: ='Emprunt Bancaire'!$B$27 -> 4367 | L25: ='Emprunt Bancaire'!$B$27 -> 4367 | M25: ='Emprunt Bancaire'!$B$27 -> 4367 | N25: ='Emprunt Bancaire'!$B$27 -> 4367 | O25: =SUM(B25:N25) -> 34936
A26: Assurance RC (0.8% CA) | B26: =B12*0.008 -> 0 | C26: =C12*0.008 -> 0 | D26: =D12*0.008 -> 0 | E26: =E12*0.008 -> 0 | F26: =F12*0.008 -> 102.88333 | G26: =G12*0.008 -> 144.03667 | H26: =H12*0.008 -> 185.19 | I26: =I12*0.008 -> 246.92 | ... N26: =N12*0.008 -> 102.88333 | O26: =SUM(B26:N26) -> 1543.25
A27: imprévue: 15% de total sortie | B27: {=SUM(B16:B26*0.15)} -> 1155.3725 | C27: {=SUM(C16:C26*0.15)} -> 4869.745 | D27: {=SUM(D16:D26*0.15)} -> 1547.845 | E27: {=SUM(E16:E26*0.15)} -> 2902.3756 | F27: {=SUM(F16:F26*0.15)} -> 4576.7662 | G27: {=SUM(G16:G26*0.15)} -> 6802.9739 | H27: {=SUM(H16:H26*0.15)} -> 7419.4663 | I27: {=SUM(I16:I26*0.15)} -> 6123.638 | ... N27: {=SUM(N16:N26*0.15)} -> 2217.8928 | O27: =SUM(B27:N27) -> 51340.932
A28: Total sorties | B28: =SUM(B16:B27) -> 8857.8558 | C28: =SUM(C16:C27) -> 37334.712 | D28: =SUM(D16:D27) -> 11866.812 | E28: =SUM(E16:E27) -> 22251.546 | F28: =SUM(F16:F27) -> 35088.541 | G28: =SUM(G16:G27) -> 52156.133 | H28: =SUM(H16:H27) -> 56882.575 | I28: =SUM(I16:I27) -> 46947.892 | ... N28: =SUM(N16:N27) -> 17003.845 | O28: =SUM(B28:N28) -> 393613.81
A30: FLUX MENSUEL | B30: =B13-B28 -> 91142.144 | C30: =C13-C28 -> 51665.288 | D30: =D13-D28 -> -11866.812 | E30: =E13-E28 -> -22251.546 | F30: =F13-F28 -> -22228.125 | G30: =G13-G28 -> 154848.45 | H30: =H13-H28 -> -33733.825 | I30: =I13-I28 -> -16082.892 | ... N30: =N13-N28 -> -4143.4281 | O30: =SUM(C30:N30) -> 86150.291
A31: TRÉSORERIE CUMULÉE | B31: =B30 -> 91142.144 | C31: =B31+C30 -> 142807.43 | D31: =C31+D30 -> 130940.62 | E31: =D31+E30 -> 108689.07 | F31: =E31+F30 -> 86460.95 | G31: =F31+G30 -> 241309.4 | H31: =G31+H30 -> 207575.58 | I31: =H31+I30 -> 191492.68 | J31: =I31+J30 -> 194334.58 | ... N31: =M31+N30 -> 177292.44
A33: 📦 Volumes
A34: Production (nb ailes) | B34: 0 | C34: 0 | D34: 0 | E34: 0 | F34: 10 | G34: 20 | H34: 20 | I34: 18 | J34: 10 | K34: 7 | L34: 5 | M34: 0 | N34: 0 | O34: =SUM(B34:N34) -> 90
A35: Ventes (nb ailes) | B35: 0 | C35: 0 | D35: 0 | E35: 0 | F35: 5 | G35: 7 | H35: 9 | I35: 12 | J35: 12 | K35: 10 | L35: 10 | M35: 5 | N35: 5 | O35: =SUM(B35:N35) -> 75
A36: Stock fin de mois | B36: 0 | C36: =(C34+B36)-C35 -> 0 | D36: =(D34+C36)-D35 -> 0 | E36: =(E34+D36)-E35 -> 0 | F36: =(F34+E36)-F35 -> 5 | G36: =(G34+F36)-G35 -> 18 | H36: =(H34+G36)-H35 -> 29 | I36: =(I34+H36)-I35 -> 35 | J36: =(J34+I36)-J35 -> 33 | ... N36: =(N34+M36)-N35 -> 15
A39: 📅 ANNÉE 2027 : CROISSANCE | B39: 📅 ANNÉE 2027 : CROISSANCE | N39: 📅 ANNÉE 2028 : CROISSANCE | Z39: 📅 ANNÉE 2029 : CROISSANCE | AL39: 📅 ANNÉE 2030 : CROISSANCE | AX39: 📅 ANNÉE 2031 : CROISSANCE
B40: Jan | C40: Fév | D40: Mar | E40: Avr | F40: Mai | G40: Juin | H40: Juil | I40: Août | J40: Sept | K40: Oct | L40: Nov | M40: Déc | N40: Jan | O40: Fév | P40: Mar | Q40: Avr | R40: Mai | S40: Juin | T40: Juil | U40: Août | V40: Sept | W40: Oct | X40: Nov | Y40: Déc | Z40: Jan | AA40: Fév | AB40: Mar | AC40: Avr | AD40: Mai | AE40: Juin | AF40: Juil | AG40: Août | AH40: Sept | AI40: Oct | AJ40: Nov | AK40: Déc | AL40: Jan | AM40: Fév | AN40: Mar | AO40: Avr | AP40: Mai | AQ40: Juin | AR40: Juil | AS40: Août | AT40: Sept | AU40: Oct | AV40: Nov | AW40: Déc | AX40: Jan | AY40: Fév | AZ40: Mar | BA40: Avr | BB40: Mai | BC40: Juin | BD40: Juil | BE40: Août | BF40: Sept | BG40: Oct | BH40: Nov | BI40: Déc
A41: ENTRÉES
A42: Apport | B42: 0 | C42: 0 | D42: 50000 | E42: 0 | F42: 0 | G42: 0 | H42: 0 | I42: 0 | J42: 0 | K42: 0 | L42: 0 | M42: 0
A43: CA Ventes (HT) | B43: =B65*'Marges Produits'!$C$49 -> 12860.417 | C43: =C65*'Marges Produits'!$C$49 -> 25720.833 | D43: =D65*'Marges Produits'!$C$49 -> 38581.25 | E43: =E65*'Marges Produits'!$C$49 -> 64302.083 | F43: =F65*'Marges Produits'!$C$49 -> 90022.917 | G43: =G65*'Marges Produits'!$C$49 -> 90022.917 | H43: =H65*'Marges Produits'!$C$49 -> 90022.917 | I43: =I65*'Marges Produits'!$C$49 -> 77162.5 | ... AW43: =AW65*'Marges Produits'!$C$49 -> 97739.167 | AX43: =AX65*(('Marges Produits'!$C$51)) -> 135034.38 | AY43: =AY65*(('Marges Produits'!$C$51)) -> 151238.5 | AZ43: =AZ65*(('Marges Produits'!$C$51)) -> 218755.69 | BA43: =BA65*(('Marges Produits'!$C$51)) -> 286272.88 | BB43: =BB65*(('Marges Produits'!$C$51)) -> 337585.94 | BC43: =BC65*(('Marges Produits'!$C$51)) -> 337585.94 | BD43: =BD65*(('Marges Produits'!$C$51)) -> 337585.94 | BE43: =BE65*(('Marges Produits'!$C$51)) -> 286272.88 | ... BI43: =BI65*(('Marges Produits'!$C$51)) -> 102626.13
A44: Total entrées | B44: =SUM(B42:B43) -> 12860.417 | C44: =SUM(C42:C43) -> 25720.833 | D44: =SUM(D42:D43) -> 88581.25 | E44: =SUM(E42:E43) -> 64302.083 | F44: =SUM(F42:F43) -> 90022.917 | G44: =SUM(G42:G43) -> 90022.917 | H44: =SUM(H42:H43) -> 90022.917 | I44: =SUM(I42:I43) -> 77162.5 | ... BI44: =SUM(BI42:BI43) -> 102626.13
A46: SORTIES
A47: Frais prototype | B47: ='Charges Fixes Plume'!$C$34*2 -> 2517.102 | C47: ='Charges Fixes Plume'!$C$34*2 -> 2517.102 | D47: ='Charges Fixes Plume'!$C$34*2 -> 2517.102 | E47: ='Charges Fixes Plume'!$C$34*2 -> 2517.102 | F47: ='Charges Fixes Plume'!$C$34*2 -> 2517.102 | G47: ='Charges Fixes Plume'!$C$34*2 -> 2517.102 | H47: ='Charges Fixes Plume'!$C$34*2 -> 2517.102 | I47: ='Charges Fixes Plume'!$C$34*2 -> 2517.102 | ... BI47: ='Charges Fixes Plume'!$C$34*2 -> 2517.102
A48: Veille concurrentielle | B48: 2500 | C48: 0 | D48: 0 | E48: 0 | F48: 0 | G48: 0 | H48: 2500 | I48: 0 | J48: 0 | K48: 0 | L48: 0 | M48: 0 | N48: =B48 -> 2500 | O48: =C48 -> 0 | P48: =D48 -> 0 | Q48: =E48 -> 0 | R48: =F48 -> 0 | S48: =G48 -> 0 | T48: =H48 -> 2500 | U48: =I48 -> 0 | ... BI48: =AW48 -> 0
A49: Masse salariale | B49: =C19 -> 10907.667 | C49: =D19 -> 6341.6667 | D49: =E19 -> 10907.667 | E49: =F19 -> 4341.6667 | F49: =G19 -> 8907.6667 | G49: =H19 -> 4341.6667 | H49: =I19 -> 7907.6667 | I49: =J19 -> 3341.6667 | ... M49: =N19 -> 4341.6667 | N49: =B49 -> 10907.667 | O49: =C49 -> 6341.6667 | P49: =D49 -> 10907.667 | Q49: =E49 -> 4341.6667 | R49: =F49 -> 8907.6667 | S49: =G49 -> 4341.6667 | T49: =H49 -> 7907.6667 | U49: =I49 -> 3341.6667 | ... BI49: =AW49 -> 4341.6667
A50: CHARGES DE CROISSANCE ( si n-1 = + 500ailes) | B50: =IF($O$35>499,'Charges Fixes Plume'!G55,0) -> 0 | C50: =IF($O$35>499,'Charges Fixes Plume'!H55,0) -> 0 | D50: =IF($O$35>499,'Charges Fixes Plume'!I55,0) -> 0 | E50: =IF($O$35>499,'Charges Fixes Plume'!J55,0) -> 0 | F50: =IF($O$35>499,'Charges Fixes Plume'!K55,0) -> 0 | G50: =IF($O$35>499,'Charges Fixes Plume'!L55,0) -> 0 | H50: =IF($O$35>499,'Charges Fixes Plume'!M55,0) -> 0 | I50: =IF($O$35>499,'Charges Fixes Plume'!N55,0) -> 0 | ... M50: =IF($O$35>499,'Charges Fixes Plume'!R55,0) -> 0 | N50: =IF($M$68>499,'Charges Fixes Plume'!G55,0) -> 0 | O50: =IF($M$68>499,'Charges Fixes Plume'!H55,0) -> 0 | P50: =IF($M$68>499,'Charges Fixes Plume'!I55,0) -> 0 | Q50: =IF($M$68>499,'Charges Fixes Plume'!J55,0) -> 0 | R50: =IF($M$68>499,'Charges Fixes Plume'!K55,0) -> 0 | S50: =IF($M$68>499,'Charges Fixes Plume'!L55,0) -> 0 | T50: =IF($M$68>499,'Charges Fixes Plume'!M55,0) -> 0 | U50: =IF($M$68>499,'Charges Fixes Plume'!N55,0) -> 0 | ... Y50: =IF($M$68>499,'Charges Fixes Plume'!R55,0) -> 0 | Z50: =IF($Y$68>499,'Charges Fixes Plume'!G55,0) -> 11375.333 | AA50: =IF($Y$68>499,'Charges Fixes Plume'!H55,0) -> 11375.333 | AB50: =IF($Y$68>499,'Charges Fixes Plume'!I55,0) -> 11375.333 | AC50: =IF($Y$68>499,'Charges Fixes Plume'!J55,0) -> 11375.333 | AD50: =IF($Y$68>499,'Charges Fixes Plume'!K55,0) -> 11375.333 | AE50: =IF($Y$68>499,'Charges Fixes Plume'!L55,0) -> 11375.333 | AF50: =IF($Y$68>499,'Charges Fixes Plume'!M55,0) -> 11375.333 | AG50: =IF($Y$68>499,'Charges Fixes Plume'!N55,0) -> 11375.333 | ... AK50: =IF($Y$68>499,'Charges Fixes Plume'!R55,0) -> 11375.333 | AL50: =IF($AK$68>499,'Charges Fixes Plume'!G55,0) -> 11375.333 | AM50: =IF($AK$68>499,'Charges Fixes Plume'!H55,0) -> 11375.333 | AN50: =IF($AK$68>499,'Charges Fixes Plume'!I55,0) -> 11375.333 | AO50: =IF($AK$68>499,'Charges Fixes Plume'!J55,0) -> 11375.333 | AP50: =IF($AK$68>499,'Charges Fixes Plume'!K55,0) -> 11375.333 | AQ50: =IF($AK$68>499,'Charges Fixes Plume'!L55,0) -> 11375.333 | AR50: =IF($AK$68>499,'Charges Fixes Plume'!M55,0) -> 11375.333 | AS50: =IF($AK$68>499,'Charges Fixes Plume'!N55,0) -> 11375.333 | ... AW50: =IF($AK$68>499,'Charges Fixes Plume'!R55,0) -> 11375.333 | AX50: =IF($AW$68>499,'Charges Fixes Plume'!G55,0) -> 11375.333 | AY50: =IF($AW$68>499,'Charges Fixes Plume'!H55,0) -> 11375.333 | AZ50: =IF($AW$68>499,'Charges Fixes Plume'!I55,0) -> 11375.333 | BA50: =IF($AW$68>499,'Charges Fixes Plume'!J55,0) -> 11375.333 | BB50: =IF($AW$68>499,'Charges Fixes Plume'!K55,0) -> 11375.333 | BC50: =IF($AW$68>499,'Charges Fixes Plume'!L55,0) -> 11375.333 | BD50: =IF($AW$68>499,'Charges Fixes Plume'!M55,0) -> 11375.333 | BE50: =IF($AW$68>499,'Charges Fixes Plume'!N55,0) -> 11375.333 | ... BI50: =IF($AW$68>499,'Charges Fixes Plume'!R55,0) -> 11375.333
A51: Charges exploitation | B51: =C21 -> 9057.3 | C51: =D21 -> 3977.3 | D51: =E21 -> 3407.3 | E51: =F21 -> 4407.3 | F51: =G21 -> 3407.3 | G51: =H21 -> 3407.3 | H51: =I21 -> 4407.3 | I51: =J21 -> 3407.3 | ... M51: =N21 -> 3457.3 | N51: =B51 -> 9057.3 | O51: =C51 -> 3977.3 | P51: =D51 -> 3407.3 | Q51: =E51 -> 4407.3 | R51: =F51 -> 3407.3 | S51: =G51 -> 3407.3 | T51: =H51 -> 4407.3 | U51: =I51 -> 3407.3 | ... BI51: =AW51 -> 3457.3
A52: Pré-série homologation (10) | B52: =C22 -> 0 | C52: =D22 -> 0 | D52: =E22 -> 5034.204 | E52: =F22 -> 0 | F52: =G22 -> 5034.204 | G52: =H22 -> 0 | H52: =I22 -> 0 | I52: =J22 -> 0 | ... M52: =N22 -> 0 | N52: =B52 -> 0 | O52: =C52 -> 0 | P52: =D52 -> 5034.204 | Q52: =E52 -> 0 | R52: =F52 -> 5034.204 | S52: =G52 -> 0 | T52: =H52 -> 0 | U52: =I52 -> 0 | ... BI52: =AW52 -> 0
A53: Tests homologation EN | B53: =C23 -> 0 | C53: =D23 -> 0 | D53: =E23 -> 0 | E53: =20142 -> 20142 | F53: =G23 -> 0 | G53: =H23 -> 13669 | H53: =I23 -> 0 | I53: =J23 -> 0 | J53: =K23 -> 0 | K53: =L23 -> 0 | L53: =M23 -> 0 | M53: =N23 -> 0 | N53: =B53 -> 0 | O53: =C53 -> 0 | P53: =D53 -> 0 | Q53: =G53 -> 13669 | R53: =F53 -> 0 | S53: =G53 -> 13669 | T53: =H53 -> 0 | U53: =I53 -> 0 | V53: =J53 -> 0 | W53: =K53 -> 0 | X53: =L53 -> 0 | Y53: =M53 -> 0 | ... BI53: =AW53 -> 0
A54: Production de stock | B54: =B64*'Marges Produits'!$E$49 -> 20975.85 | C54: =C64*'Marges Produits'!$E$49 -> 26219.812 | D54: =D64*'Marges Produits'!$E$49 -> 31463.775 | E54: =E64*'Marges Produits'!$E$49 -> 36707.738 | F54: =F64*'Marges Produits'!$E$49 -> 52439.625 | G54: =G64*'Marges Produits'!$E$49 -> 38805.323 | H54: =H64*'Marges Produits'!$E$49 -> 36707.738 | I54: =I64*'Marges Produits'!$E$49 -> 31463.775 | ... BI54: =BI64*'Marges Produits'!$E$49 -> 0
A55: Remboursement emprunt | B55: ='Emprunt Bancaire'!$B$27 -> 4367 | C55: ='Emprunt Bancaire'!$B$27 -> 4367 | D55: ='Emprunt Bancaire'!$B$27 -> 4367 | E55: ='Emprunt Bancaire'!$B$27 -> 4367 | F55: ='Emprunt Bancaire'!$B$27 -> 4367 | G55: ='Emprunt Bancaire'!$B$27 -> 4367 | H55: ='Emprunt Bancaire'!$B$27 -> 4367 | I55: ='Emprunt Bancaire'!$B$27 -> 4367 | ... AP55: ='Emprunt Bancaire'!$B$27 -> 4367
A56: Assurance RC (0.8% CA) | B56: =B43*0.008 -> 102.88333 | C56: =C43*0.008 -> 205.76667 | D56: =D43*0.008 -> 308.65 | E56: =E43*0.008 -> 514.41667 | F56: =F43*0.008 -> 720.18333 | G56: =G43*0.008 -> 720.18333 | H56: =H43*0.008 -> 720.18333 | I56: =I43*0.008 -> 617.3 | ... BI56: =BI43*0.008 -> 821.009
A57: imprévue: 15% de total sortie | B57: =(SUM(B47:B56)*0.15) -> 7564.1703 | C57: =(SUM(C47:C56)*0.15) -> 6544.2972 | D57: =(SUM(D47:D56)*0.15) -> 8700.8546 | E57: =(SUM(E47:E56)*0.15) -> 10949.583 | F57: =(SUM(F47:F56)*0.15) -> 11608.962 | G57: =(SUM(G47:G56)*0.15) -> 10174.136 | H57: =(SUM(H47:H56)*0.15) -> 8869.0484 | I57: =(SUM(I47:I56)*0.15) -> 6857.1216 | ... BI57: =(SUM(BI47:BI56)*0.15) -> 3376.8616
A58: Total sorties | B58: =SUM(B47:B57) -> 57991.972 | C58: =SUM(C47:C57) -> 50172.945 | D58: =SUM(D47:D57) -> 66706.552 | E58: =SUM(E47:E57) -> 83946.806 | F58: =SUM(F47:F57) -> 89002.043 | G58: =SUM(G47:G57) -> 78001.711 | H58: =SUM(H47:H57) -> 67996.038 | I58: =SUM(I47:I57) -> 52571.265 | ... BI58: =SUM(BI47:BI57) -> 25889.273
A60: FLUX MENSUEL | B60: =B44-B58 -> -45131.556 | C60: =C44-C58 -> -24452.112 | D60: =D44-D58 -> 21874.698 | E60: =E44-E58 -> -19644.723 | F60: =F44-F58 -> 1020.8735 | G60: =G44-G58 -> 12021.206 | H60: =H44-H58 -> 22026.879 | I60: =I44-I58 -> 24591.235 | ... BI60: =BI44-BI58 -> 76736.852
A61: TRÉSORERIE CUMULÉE | B61: =N31+B60 -> 132160.88 | C61: =B61+C60 -> 107708.77 | D61: =C61+D60 -> 129583.47 | E61: =D61+E60 -> 109938.74 | F61: =E61+F60 -> 110959.62 | G61: =F61+G60 -> 122980.82 | H61: =G61+H60 -> 145007.7 | I61: =H61+I60 -> 169598.94 | J61: =I61+J60 -> 181077.73 | ... BI61: =BH61+BI60 -> 2974177.6
A63: 📦 Volumes
A64: Production (nb ailes) | B64: 20 | C64: 25 | D64: 30 | E64: 35 | F64: 50 | G64: 37 | H64: 35 | I64: 30 | J64: 25 | K64: 15 | L64: 0 | M64: 0 | N64: =B64*2 -> 40 | O64: =C64*2 -> 50 | P64: 75 | Q64: 90 | R64: =F64*2 -> 100 | S64: 100 | T64: =H64*2 -> 70 | U64: =I64*2 -> 60 | V64: =J64*2 -> 50 | W64: =K64*2 -> 30 | X64: =L64*2 -> 0 | Y64: =M64*2 -> 0 | Z64: =ROUND(N64*1.3,0) -> 52 | AA64: =ROUND(O64*1.3,0) -> 65 | AB64: =ROUND(P64*1.3,0) -> 98 | AC64: =ROUND(Q64*1.3,0) -> 117 | AD64: =ROUND(R64*1.3,0) -> 130 | AE64: =ROUND(S64*1.3,0) -> 130 | AF64: =ROUND(T64*1.3,0) -> 91 | AG64: =ROUND(U64*1.3,0) -> 78 | ... AK64: =ROUND(Y64*1.3,0) -> 0 | AL64: =ROUND(Z64*1.21,0) -> 63 | AM64: =ROUND(AA64*1.21,0) -> 79 | AN64: =ROUND(AB64*1.21,0) -> 119 | AO64: =ROUND(AC64*1.21,0) -> 142 | AP64: =ROUND(AD64*1.21,0) -> 157 | AQ64: =ROUND(AE64*1.21,0) -> 157 | AR64: =ROUND(AF64*1.21,0) -> 110 | AS64: =ROUND(AG64*1.21,0) -> 94 | ... AW64: =ROUND(AK64*1.21,0) -> 0 | AX64: 50 | AY64: 100 | AZ64: 100 | BA64: 130 | BB64: 150 | BC64: 150 | BD64: 125 | BE64: 106 | BF64: 94 | BG64: 0 | BH64: 0 | BI64: 0
A65: Ventes (nb ailes) | B65: 5 | C65: 10 | D65: 15 | E65: 25 | F65: 35 | G65: 35 | H65: 35 | I65: 30 | J65: 25 | K65: 15 | L65: 10 | M65: 10 | N65: 15 | O65: 30 | P65: 50 | Q65: 60 | R65: =F65*2 -> 70 | S65: =G65*2 -> 70 | T65: =H65*2 -> 70 | U65: 65 | V65: =J65*2 -> 50 | W65: 30 | X65: =L65*2 -> 20 | Y65: =M65*2 -> 20 | Z65: 40 | AA65: 45 | AB65: 65 | AC65: 85 | AD65: 100 | AE65: 100 | AF65: 100 | AG65: 85 | AH65: =V65*1.5 -> 75 | AI65: =W65*1.5 -> 45 | AJ65: =X65*1.5 -> 30 | AK65: =Y65*1.5 -> 30 | AL65: =Z65/8*10 -> 50 | AM65: 56 | AN65: 81 | AO65: 106 | AP65: 125 | AQ65: =AE65/8*10 -> 125 | AR65: =AF65/8*10 -> 125 | AS65: 106 | AT65: 94 | AU65: 56 | AV65: 38 | AW65: 38 | AX65: 50 | AY65: 56 | AZ65: 81 | BA65: 106 | BB65: 125 | BC65: 125 | BD65: 125 | BE65: 106 | BF65: 94 | BG65: 56 | BH65: 38 | BI65: 38
A66: Stock fin de mois | B66: =N36+B64-B65 -> 30 | C66: =B66+C64-C65 -> 45 | D66: =C66+D64-D65 -> 60 | E66: =D66+E64-E65 -> 70 | F66: =E66+F64-F65 -> 85 | G66: =F66+G64-G65 -> 87 | H66: =G66+H64-H65 -> 87 | I66: =H66+I64-I65 -> 87 | J66: =I66+J64-J65 -> 87 | ... BI66: =BH66+BI64-BI65 -> 299
L67: production | M67: =SUM(B64:M64) -> 302 | X67: production | Y67: =SUM(N64:Y64) -> 665 | AJ67: production | AK67: =SUM(Z64:AK64) -> 865 | AV67: production | AW67: =SUM(AL64:AW64) -> 1047 | BH67: production | BI67: =SUM(AX64:BI64) -> 1005
L68: vente | M68: =SUM(B65:M65) -> 250 | X68: vente | Y68: =SUM(N65:Y65) -> 550 | AJ68: vente | AK68: =SUM(Z65:AK65) -> 800 | AV68: vente | AW68: =SUM(AL65:AW65) -> 1000 | BH68: vente | BI68: =SUM(AX65:BI65) -> 1000
A69: 📊 SYNTHÈSE | L69: CA vente HT | M69: =SUM(B43:M43) -> 643020.83 | X69: CA vente HT | Y69: =SUM(N43:Y43) -> 1414645.8 | AJ69: CA vente HT | AK69: =SUM(Z43:AK43) -> 2057666.7 | AV69: CA vente HT | AW69: =SUM(AL43:AW43) -> 2572083.3 | BH69: CA vente HT | BI69: =SUM(AX43:BI43) -> 2700687.5
L70: Flux annuel | M70: =SUM(B60:M60) -> 17945.84 | X70: Flux annuel | Y70: =SUM(N60:Y60) -> 302097.41 | AJ70: Flux annuel | AK70: =SUM(Z60:AK60) -> 541000.58 | AV70: Flux annuel | AW70: =SUM(AL60:AW60) -> 866326.69 | BH70: Flux annuel | BI70: =SUM(AX60:BI60) -> 1069514.6
A71: CALENDRIER FINANCEMENT
A72: 18 Déc 2025 : Capital social 100 000 €
A73: Janvier 2026 : Comptes courants 89 000 €
A74: Mai 2026 : Emprunt bancaire 189 000 €
A77: Mars 2027 : Avoir EURL JB 50 000 €
A79: ✅ Point bas trésorerie : | B79: =MIN(B61:BI61) -> 107708.77
A80: ✅ Trésorerie fin 2026 | B80: =N31 -> 177292.44
A81: ✅ Trésorerie fin 2027 | B81: =M61 -> 195238.27
A87: Information: Le prix de nos produits sera augmenté de 5 % le jour où on aura atteint le barier de 1000 ventes par an. Et si la demande est forte, ça sera augmenté de 5 % par an jusqu'à atteindre un équilibre entre la demande et les ventes
A90: 📝 NOTE MÉTHODOLOGIQUE (TVA) :
A91: Le plan de trésorerie est volontairement présenté en HT. Étant en phase de croissance,
A92: le décalage de TVA (TVA collectée sur ventes > TVA déductible sur achats) générera un excédent
A93: de trésorerie structurel (BFR négatif sur la partie fiscale). La présentation HT constitue donc
A94: un scénario 'conservateur' qui sécurise les besoins de financement.

Sheet Compte de Résultat
A1: COMPTE DE RÉSULTAT PRÉVISIONNEL - SCÉNARIO RÉALISTE
A3: PARAMÈTRES | B3: avant 1000 ailes/ans | C3: apres 1000 ailes/ans
A4: Prix moyen HT par aile | B4: ='Marges Produits'!C49 -> 2572.0833
A5: Marge brute par aile | B5: ='Marges Produits'!D49 -> 1100.3575 | C5: ='Marges Produits'!D51 -> 1228.9617
A6: Coût de revient par aile | B6: ='Marges Produits'!E49 -> 1048.7925
A7: Stock cible (% des ventes) | B7: 0.5
A8: Charges fixes exploitation | B8: ='Charges Fixes Plume'!D57 -> 208782.33
A10: CHIFFRE D'AFFAIRES
A11: Année | B11: 2025 | C11: 2026 | D11: 2027 | E11: 2028 | F11: 2029 | G11: 2030 | H11: 2031
A12: Volumes vendus | B12: ='Seuil Rentabilité'!B25 -> 0 | C12: ='Plan Trésorerie Mensuel'!O35 -> 75 | D12: ='Plan Trésorerie Mensuel'!M68 -> 250 | E12: ='Plan Trésorerie Mensuel'!Y68 -> 550 | F12: ='Plan Trésorerie Mensuel'!AK68 -> 800 | G12: ='Plan Trésorerie Mensuel'!AW68 -> 1000 | H12: ='Plan Trésorerie Mensuel'!BI68 -> 1000
A13: CA TOTAL HT | B13: ='Plan Trésorerie Mensuel'!B12 -> 0 | C13: =SUM('Plan Trésorerie Mensuel'!C12:N12) -> 192906.25 | D13: =SUM('Plan Trésorerie Mensuel'!M69) -> 643020.83 | E13: ='Plan Trésorerie Mensuel'!Y69 -> 1414645.8 | F13: ='Plan Trésorerie Mensuel'!AK69 -> 2057666.7 | G13: ='Plan Trésorerie Mensuel'!AW69 -> 2572083.3 | H13: ='Plan Trésorerie Mensuel'!BI69 -> 2700687.5
A15: MARGE BRUTE
A16: Marge brute totale | B16: =B12*$B$5 -> 0 | C16: =C12*$B$5 -> 82526.812 | D16: =D12*$B$5 -> 275089.37 | E16: =E12*$B$5 -> 605196.62 | F16: =F12*$B$5 -> 880286 | G16: =G12*$B$5 -> 1100357.5 | H16: =H12*$C$5 -> 1228961.7
A18: CHARGES FIXES
A19: Charges fixes exploitation | B19: ='Plan Trésorerie Mensuel'!B28 -> 8857.8558 | C19: =SUM('Plan Trésorerie Mensuel'!C16:N23) -> 203699.82 | D19: =SUM('Plan Trésorerie Mensuel'!B47:M53) -> 212738.23 | E19: =SUM('Plan Trésorerie Mensuel'!N47:Y53) -> 206265.23 | F19: =SUM('Plan Trésorerie Mensuel'!Z47:AK53) -> 342769.23 | G19: =SUM('Plan Trésorerie Mensuel'!AL47:AW53) -> 342769.23 | H19: =SUM('Plan Trésorerie Mensuel'!AX47:BI53) -> 342769.23
A20: Intérêts financiers + assurance prêt (2026-2029) | B20: 0 | C20: ='Emprunt Bancaire'!D32 -> 5742.63 | D20: ='Emprunt Bancaire'!D33 -> 6941.91 | E20: ='Emprunt Bancaire'!D34 -> 4853.64 | F20: ='Emprunt Bancaire'!D35 -> 2669.42 | G20: ='Emprunt Bancaire'!D36 -> 387.22 | H20: 0
A21: TOTAL CHARGES FIXES | B21: =SUM(B19:B20) -> 8857.8558 | C21: =SUM(C19:C20) -> 209442.45 | D21: =SUM(D19:D20) -> 219680.14 | E21: =SUM(E19:E20) -> 211118.87 | F21: =SUM(F19:F20) -> 345438.65 | G21: =SUM(G19:G20) -> 343156.45 | H21: =SUM(H19:H20) -> 342769.23
A23: CHARGES VARIABLES
A24: Assurance (0.8% du CA) | B24: =B13*0.008 -> 0 | C24: =C13*0.008 -> 1543.25 | D24: =D13*0.008 -> 5144.1667 | E24: =E13*0.008 -> 11317.167 | F24: =F13*0.008 -> 16461.333 | G24: =G13*0.008 -> 20576.667 | H24: =H13*0.008 -> 21605.5
A25: TOTAL CHARGES VARIABLES | B25: =B24 -> 0 | C25: =C24 -> 1543.25 | D25: =D24 -> 5144.1667 | E25: =E24 -> 11317.167 | F25: =F24 -> 16461.333 | G25: =G24 -> 20576.667 | H25: =H24 -> 21605.5
A27: RÉSULTAT D'EXPLOITATION
A28: Résultat avant réinvestissement | B28: =B16-B21-B25 -> -8857.8558 | C28: =C16-C21-C25 -> -128458.89 | D28: =D16-D21-D25 -> 50265.066 | E28: =E16-E21-E25 -> 382760.59 | F28: =F16-F21-F25 -> 518386.01 | G28: =G16-G21-G25 -> 736624.38 | H28: =H16-H21-H25 -> 864586.93
A29: Déficit reportable | B29: =MIN(0,B28) -> -8857.8558 | C29: =MIN(0,B29+C28) -> -137316.75 | D29: =MIN(0,C29+D28) -> -87051.681 | E29: =MIN(0,D29+E28) -> 0 | F29: =MIN(0,E29+F28) -> 0 | G29: =MIN(0,F29+G28) -> 0 | H29: =MIN(0,G29+H28) -> 0
A30: Taux IS effectif (ZFRR Briançon) | B30: 0 | C30: 0 | D30: 0 | E30: 0 | F30: 0 | G30: 0.0625 | H30: 0.125
A31: Impôt sur les sociétés (IS) | B31: =MAX(0,B28)*B30 -> 0 | C31: =MAX(0,B29+C28)*C30 -> 0 | D31: =MAX(0,C29+D28)*D30 -> 0 | E31: =MAX(0,D29+E28)*E30 -> 0 | F31: =MAX(0,E29+F28)*F30 -> 0 | G31: =MAX(0,F29+G28)*G30 -> 46039.024 | H31: =MAX(0,G29+H28)*H30 -> 108073.37
A32: ⚠️ ZFRR art.44 quindecies A CGI • Exo totale 5 ans + dégressive 3 ans • Plafond de minimis 300k€/3 ans (cumul avec autres aides)
A33: RÉSULTAT NET
A34: RÉSULTAT NET | B34: =B28-B31 -> -8857.8558 | C34: =C28-C31 -> -128458.89 | D34: =D28-D31 -> 50265.066 | E34: =E28-E31 -> 382760.59 | F34: =F28-F31 -> 518386.01 | G34: =G28-G31 -> 690585.36 | H34: =H28-H31 -> 756513.57
A36: BFR - VARIATION DE STOCK
A37: 💡 + = investir dans le stock / - = récupérer du stock
A38: Stock fin d'année (nb ailes — source : plan de trésorerie) | B38: =B12*$B$7 -> 0 | C38: ='Plan Trésorerie Mensuel'!N36 -> 15 | D38: ='Plan Trésorerie Mensuel'!M66 -> 67 | E38: ='Plan Trésorerie Mensuel'!Y66 -> 182 | F38: ='Plan Trésorerie Mensuel'!AK66 -> 247 | G38: ='Plan Trésorerie Mensuel'!AW66 -> 294 | H38: ='Plan Trésorerie Mensuel'!BI66 -> 299
A39: Stock cible (€ = nb ailes × coût) | B39: =B38*$B$6 -> 0 | C39: =C38*$B$6 -> 15731.888 | D39: =D38*$B$6 -> 70269.098 | E39: =E38*$B$6 -> 190880.24 | F39: =F38*$B$6 -> 259051.75 | G39: =G38*$B$6 -> 308344.99 | H39: =H38*$B$6 -> 313588.96
A40: Variation stock (impact trésorerie) | B40: =B39 -> 0 | C40: =C39-B39 -> 15731.888 | D40: =D39-C39 -> 54537.21 | E40: =E39-D39 -> 120611.14 | F40: =F39-E39 -> 68171.512 | G40: =G39-F39 -> 49293.247 | H40: =H39-G39 -> 5243.9625
A42: TRÉSORERIE au 31 decembre | B42: 2025 | C42: 2026 | D42: 2027 | E42: 2028 | F42: 2029 | G42: 2030 | H42: 2031
A43: Apports | B43: ='Plan Trésorerie Mensuel'!B7 -> 100000 | C43: =SUM('Plan Trésorerie Mensuel'!C7:N9) -> 278000 | D43: =SUM('Plan Trésorerie Mensuel'!B42:M42) -> 50000 | E43: =SUM('Plan Trésorerie Mensuel'!N42:Y42) -> 0 | F43: =SUM('Plan Trésorerie Mensuel'!Z42:AK42) -> 0 | G43: 0 | H43: 0
A44: Flux de trésorerie annuel | B44: ='Plan Trésorerie Mensuel'!B13-'Plan Trésorerie Mensuel'!B28 -> 91142.144 | C44: =SUM('Plan Trésorerie Mensuel'!C13:N13)-SUM('Plan Trésorerie Mensuel'!C28:N28) -> 86150.291 | D44: =SUM('Plan Trésorerie Mensuel'!B44:M44)-SUM('Plan Trésorerie Mensuel'!B58:M58) -> 17945.84 | E44: =SUM('Plan Trésorerie Mensuel'!N44:Y44)-SUM('Plan Trésorerie Mensuel'!N58:Y58) -> 302097.41 | F44: =SUM('Plan Trésorerie Mensuel'!Z44:AK44)-SUM('Plan Trésorerie Mensuel'!Z58:AK58) -> 541000.58 | G44: =SUM('Plan Trésorerie Mensuel'!AL44:AW44)-SUM('Plan Trésorerie Mensuel'!AL58:AW58) -> 866326.69 | H44: =SUM('Plan Trésorerie Mensuel'!AX44:BI44)-SUM('Plan Trésorerie Mensuel'!AX58:BI58) -> 1069514.6
A45: TRÉSORERIE CUMULÉE | B45: ='Plan Trésorerie Mensuel'!B31 -> 91142.144 | C45: ='Plan Trésorerie Mensuel'!N31 -> 177292.44 | D45: ='Plan Trésorerie Mensuel'!M61 -> 195238.27 | E45: ='Plan Trésorerie Mensuel'!Y61 -> 497335.69 | F45: ='Plan Trésorerie Mensuel'!AK61 -> 1038336.3 | G45: ='Plan Trésorerie Mensuel'!AW61 -> 1904663 | H45: ='Plan Trésorerie Mensuel'!BI61 -> 2974177.6

Sheet DSCR & ratio bancaires
A1: 📊 DSCR & RATIOS BANCAIRES — PLUME PARAGLIDERS
A2: Indicateurs de capacité de remboursement — Scénario Réaliste
A4: 🏦 DEBT SERVICE COVERAGE RATIO (DSCR)
A5: DSCR = (Résultat Net + Dotations aux amortissements) / Remboursement annuel de la dette
A7: Indicateur | B7: 2025 | C7: 2026 | D7: 2027 | E7: 2028 | F7: 2029 | G7: 2030 | H7: 2031
A8: Résultat net (€) | B8: ='Compte de Résultat'!B34 -> -8857.8558 | C8: ='Compte de Résultat'!C34 -> -128458.89 | D8: ='Compte de Résultat'!D34 -> 50265.066 | E8: ='Compte de Résultat'!E34 -> 382760.59 | F8: ='Compte de Résultat'!F34 -> 518386.01 | G8: ='Compte de Résultat'!G34 -> 690585.36 | H8: ='Compte de Résultat'!H34 -> 756513.57
A9: + Dotations aux amortissements (€) | B9: 0 | C9: 5000 | D9: 12000 | E9: 15000 | F9: 15000 | G9: 15000 | H9: 15000
A10: Capacité d'Autofinancement (CAF) | B10: =B8+B9 -> -8857.8558 | C10: =C8+C9 -> -123458.89 | D10: =D8+D9 -> 62265.066 | E10: =E8+E9 -> 397760.59 | F10: =F8+F9 -> 533386.01 | G10: =G8+G9 -> 705585.36 | H10: =H8+H9 -> 771513.57
A11: Service de la dette (capital + intérêts) (€) | B11: 0 | C11: =SUM('[1]Emprunt Mensualité'!E13:F13) -> 34478.88 | D11: =SUM('[1]Emprunt Mensualité'!E27:F27) -> 51718.31 | E11: =SUM('[1]Emprunt Mensualité'!E41:F41) -> 51718.3 | F11: =SUM('[1]Emprunt Mensualité'!E55:F55) -> 51718.32 | G11: =SUM('[1]Emprunt Mensualité'!E61:F61) -> 17239.43 | H11: 0
A12: 📈 DSCR (CAF / Service dette) | B12: =IF(B11=0,"N/A",IF(B10<0,"Négatif",FIXED(ROUND(B10/B11,1),1)&"x")) -> N/A | C12: =IF(C11=0,"N/A",IF(C10<0,"Négatif",FIXED(ROUND(C10/C11,1),1)&"x")) -> Négatif | D12: =IF(D11=0,"N/A",IF(D10<0,"Négatif",FIXED(ROUND(D10/D11,1),1)&"x")) -> 1,2x | E12: =IF(E11=0,"N/A",IF(E10<0,"Négatif",FIXED(ROUND(E10/E11,1),1)&"x")) -> 7,7x | F12: =IF(F11=0,"N/A",IF(F10<0,"Négatif",FIXED(ROUND(F10/F11,1),1)&"x")) -> 10,3x | G12: =IF(G11=0,"N/A",IF(G10<0,"Négatif",FIXED(ROUND(G10/G11,1),1)&"x")) -> 40,9x | H12: =IF(H11=0,"N/A",IF(H10<0,"Négatif",FIXED(ROUND(H10/H11,1),1)&"x")) -> N/A
A14: 💡 LECTURE : DSCR > 1,0x = la boîte génère assez pour rembourser • > 1,2x = zone de confort bancaire • > 2,0x = excellent
A15: ⚠️ 2026 : DSCR négatif = normal (année de lancement, résultat déficitaire prévu). L'emprunt finance cette phase. Retour > 1x dès 2027.
A17: 📋 RATIOS COMPLÉMENTAIRES
A18: Ratio | B18: 2025 | C18: 2026 | D18: 2027 | E18: 2028 | F18: 2029 | G18: 2030 | H18: 2031
A19: Ratio d'endettement (Dettes / CP) | B19: =IF('[1]Bilan Prévisionnel'!B24=0,"-",ROUND('[1]Bilan Prévisionnel'!B28/'[1]Bilan Prévisionnel'!B24,2)) -> 0.19 | C19: =IF('[1]Bilan Prévisionnel'!C24=0,"-",ROUND('[1]Bilan Prévisionnel'!C28/'[1]Bilan Prévisionnel'!C24,2)) -> 3.88 | D19: =IF('[1]Bilan Prévisionnel'!D24=0,"-",ROUND('[1]Bilan Prévisionnel'!D28/'[1]Bilan Prévisionnel'!D24,2)) -> 0.96 | E19: =IF('[1]Bilan Prévisionnel'!E24=0,"-",ROUND('[1]Bilan Prévisionnel'!E28/'[1]Bilan Prévisionnel'!E24,2)) -> 0.22 | F19: =IF('[1]Bilan Prévisionnel'!F24=0,"-",ROUND('[1]Bilan Prévisionnel'!F28/'[1]Bilan Prévisionnel'!F24,2)) -> 0.07 | G19: =IF('[1]Bilan Prévisionnel'!G24=0,"-",ROUND('[1]Bilan Prévisionnel'!G28/'[1]Bilan Prévisionnel'!G24,2)) -> 0.04 | H19: =IF('[1]Bilan Prévisionnel'!H24=0,"-",ROUND('[1]Bilan Prévisionnel'!H28/'[1]Bilan Prévisionnel'!H24,2)) -> 0.03
A20: Autonomie financière (CP / Total bilan) | B20: =IF('[1]Bilan Prévisionnel'!B30=0,"-",'[1]Bilan Prévisionnel'!B24/'[1]Bilan Prévisionnel'!B30) -> 0.83970134 | C20: =IF('[1]Bilan Prévisionnel'!C30=0,"-",'[1]Bilan Prévisionnel'!C24/'[1]Bilan Prévisionnel'!C30) -> 0.20473823 | D20: =IF('[1]Bilan Prévisionnel'!D30=0,"-",'[1]Bilan Prévisionnel'!D24/'[1]Bilan Prévisionnel'!D30) -> 0.50906262 | E20: =IF('[1]Bilan Prévisionnel'!E30=0,"-",'[1]Bilan Prévisionnel'!E24/'[1]Bilan Prévisionnel'!E30) -> 0.82017261 | F20: =IF('[1]Bilan Prévisionnel'!F30=0,"-",'[1]Bilan Prévisionnel'!F24/'[1]Bilan Prévisionnel'!F30) -> 0.93646723 | G20: =IF('[1]Bilan Prévisionnel'!G30=0,"-",'[1]Bilan Prévisionnel'!G24/'[1]Bilan Prévisionnel'!G30) -> 0.96442121 | H20: =IF('[1]Bilan Prévisionnel'!H30=0,"-",'[1]Bilan Prévisionnel'!H24/'[1]Bilan Prévisionnel'!H30) -> 0.9743159
A21: Trésorerie disponible (€) | B21: ='[1]Compte de Résultat'!B45 -> 91142.144 | C21: ='[1]Compte de Résultat'!C45 -> 177292.44 | D21: ='[1]Compte de Résultat'!D45 -> 195238.27 | E21: ='[1]Compte de Résultat'!E45 -> 497335.69 | F21: ='[1]Compte de Résultat'!F45 -> 1038336.3 | G21: ='[1]Compte de Résultat'!G45 -> 1904663 | H21: ='[1]Compte de Résultat'!H45 -> 2974177.6
A22: Marge nette (Résultat / CA) | B22: =IF('[1]Compte de Résultat'!B13=0,"N/A",'[1]Compte de Résultat'!B34/'[1]Compte de Résultat'!B13) -> N/A | C22: =IF('[1]Compte de Résultat'!C13=0,"N/A",'[1]Compte de Résultat'!C34/'[1]Compte de Résultat'!C13) -> -0.69226063 | D22: =IF('[1]Compte de Résultat'!D13=0,"N/A",'[1]Compte de Résultat'!D34/'[1]Compte de Résultat'!D13) -> 0.084322251 | E22: =IF('[1]Compte de Résultat'!E13=0,"N/A",'[1]Compte de Résultat'!E34/'[1]Compte de Résultat'!E13) -> 0.26879059 | F22: =IF('[1]Compte de Résultat'!F13=0,"N/A",'[1]Compte de Résultat'!F34/'[1]Compte de Résultat'!F13) -> 0.31704499 | G22: =IF('[1]Compte de Résultat'!G13=0,"N/A",'[1]Compte de Résultat'!G34/'[1]Compte de Résultat'!G13) -> 0.31732956 | H22: =IF('[1]Compte de Résultat'!H13=0,"N/A",'[1]Compte de Résultat'!H34/'[1]Compte de Résultat'!H13) -> 0.31502258
A23: Années restantes de remboursement | B23: _ | C23: =IF('Bilan Prévisionnel'!C26<=0,IF('Bilan Prévisionnel'!B26>0,"Soldé ✓","—"),FIXED(ROUND('Bilan Prévisionnel'!C26/('Emprunt Bancaire'!$B$4/'Emprunt Bancaire'!$B$5),1),1)&" ans") -> 3,4 ans | D23: =IF('Bilan Prévisionnel'!D26<=0,IF('Bilan Prévisionnel'!C26>0,"Soldé ✓","—"),FIXED(ROUND('Bilan Prévisionnel'!D26/('Emprunt Bancaire'!$B$4/'Emprunt Bancaire'!$B$5),1),1)&" ans") -> 2,4 ans | E23: =IF('Bilan Prévisionnel'!E26<=0,IF('Bilan Prévisionnel'!D26>0,"Soldé ✓","—"),FIXED(ROUND('Bilan Prévisionnel'!E26/('Emprunt Bancaire'!$B$4/'Emprunt Bancaire'!$B$5),1),1)&" ans") -> 1,4 ans | F23: =IF('Bilan Prévisionnel'!F26<=0,IF('Bilan Prévisionnel'!E26>0,"Soldé ✓","—"),FIXED(ROUND('Bilan Prévisionnel'!F26/('Emprunt Bancaire'!$B$4/'Emprunt Bancaire'!$B$5),1),1)&" ans") -> 0,4 ans | G23: =IF('Bilan Prévisionnel'!G26<=0,IF('Bilan Prévisionnel'!F26>0,"Soldé ✓","—"),FIXED(ROUND('Bilan Prévisionnel'!G26/('Emprunt Bancaire'!$B$4/'Emprunt Bancaire'!$B$5),1),1)&" ans") -> Soldé ✓ | H23: =IF('Bilan Prévisionnel'!H26<=0,IF('Bilan Prévisionnel'!G26>0,"Soldé ✓","—"),FIXED(ROUND('Bilan Prévisionnel'!H26/('Emprunt Bancaire'!$B$4/'Emprunt Bancaire'!$B$5),1),1)&" ans") -> —
A25: 🟢 Vert = excellent | 🟡 Jaune = acceptable | 🔴 Rouge = à surveiller | ⬜ Gris = non applicable
A27: ⚠️ DSCR — SCÉNARIO PESSIMISTE (-30% VENTES)
A28: Indicateur | B28: 2025 | C28: 2026 | D28: 2027 | E28: 2028 | F28: 2029 | G28: 2030 | H28: 2031
A29: Résultat net -30% (€) | B29: =('[1]Compte de Résultat'!B16*0.7-'[1]Compte de Résultat'!B21-'[1]Compte de Résultat'!B25*0.7)-MAX(0,'[1]Compte de Résultat'!B16*0.7-'[1]Compte de Résultat'!B21-'[1]Compte de Résultat'!B25*0.7)*'[1]Compte de Résultat'!B30 -> -8857.8558 | C29: =('[1]Compte de Résultat'!C16*0.7-'[1]Compte de Résultat'!C21-'[1]Compte de Résultat'!C25*0.7)-MAX(0,'[1]Compte de Résultat'!C16*0.7-'[1]Compte de Résultat'!C21-'[1]Compte de Résultat'!C25*0.7)*'[1]Compte de Résultat'!C30 -> -157836.47 | D29: =('[1]Compte de Résultat'!D16*0.7-'[1]Compte de Résultat'!D21-'[1]Compte de Résultat'!D25*0.7)-MAX(0,'[1]Compte de Résultat'!D16*0.7-'[1]Compte de Résultat'!D21-'[1]Compte de Résultat'!D25*0.7)*'[1]Compte de Résultat'!D30 -> -26762.598 | E29: =('[1]Compte de Résultat'!E16*0.7-'[1]Compte de Résultat'!E21-'[1]Compte de Résultat'!E25*0.7)-MAX(0,'[1]Compte de Résultat'!E16*0.7-'[1]Compte de Résultat'!E21-'[1]Compte de Résultat'!E25*0.7)*'[1]Compte de Résultat'!E30 -> 202079.65 | F29: =('[1]Compte de Résultat'!F16*0.7-'[1]Compte de Résultat'!F21-'[1]Compte de Résultat'!F25*0.7)-MAX(0,'[1]Compte de Résultat'!F16*0.7-'[1]Compte de Résultat'!F21-'[1]Compte de Résultat'!F25*0.7)*'[1]Compte de Résultat'!F30 -> 393225.51 | G29: =('[1]Compte de Résultat'!G16*0.7-'[1]Compte de Résultat'!G21-'[1]Compte de Résultat'!G25*0.7)-MAX(0,'[1]Compte de Résultat'!G16*0.7-'[1]Compte de Résultat'!G21-'[1]Compte de Résultat'!G25*0.7)*'[1]Compte de Résultat'!G30 -> 512509.71 | H29: =('[1]Compte de Résultat'!H16*0.7-'[1]Compte de Résultat'!H21-'[1]Compte de Résultat'!H25*0.7)-MAX(0,'[1]Compte de Résultat'!H16*0.7-'[1]Compte de Résultat'!H21-'[1]Compte de Résultat'!H25*0.7)*'[1]Compte de Résultat'!H30 -> 512379.67
A30: CAF -30% (€) | B30: =B29+B9 -> -8857.8558 | C30: =C29+C9 -> -152836.47 | D30: =D29+D9 -> -14762.598 | E30: =E29+E9 -> 217079.65 | F30: =F29+F9 -> 408225.51 | G30: =G29+G9 -> 527509.71 | H30: =H29+H9 -> 527379.67
A31: 📈 DSCR -30% | B31: =IF(B11=0,"N/A",IF(B30<0,"Négatif",FIXED(ROUND(B30/B11,1),1)&"x")) -> N/A | C31: =IF(C11=0,"N/A",IF(C30<0,"Négatif",FIXED(ROUND(C30/C11,1),1)&"x")) -> Négatif | D31: =IF(D11=0,"N/A",IF(D30<0,"Négatif",FIXED(ROUND(D30/D11,1),1)&"x")) -> Négatif | E31: =IF(E11=0,"N/A",IF(E30<0,"Négatif",FIXED(ROUND(E30/E11,1),1)&"x")) -> 4,2x | F31: =IF(F11=0,"N/A",IF(F30<0,"Négatif",FIXED(ROUND(F30/F11,1),1)&"x")) -> 7,9x | G31: =IF(G11=0,"N/A",IF(G30<0,"Négatif",FIXED(ROUND(G30/G11,1),1)&"x")) -> 30,6x | H31: =IF(H11=0,"N/A",IF(H30<0,"Négatif",FIXED(ROUND(H30/H11,1),1)&"x")) -> N/A
A33: 💡 Même à -30%, le DSCR repasse au-dessus de 1x dès 2028. La trésorerie ne passe jamais en négatif (point bas : 40 215€ en avril 2028).
A34: ⚠️ Dans ce scénario, 2027 est déficitaire (CAF négative). L'entreprise puise dans sa trésorerie accumulée (95k€ fin 2026) pour absorber le choc.

Sheet Bilan Prévisionnel
A1: BILAN PRÉVISIONNEL - PLUME PARAGLIDERS
A2: Projection sur 7 ans (2025-2031) - Scénario Réaliste
A3: "Le bilan prévisionnel présente une photographie patrimoniale au 31 décembre de chaque exercice. Du fait de la forte saisonnalité de l'activité (pic mars-septembre), les niveaux de trésorerie et de stock à date de clôture peuvent différer significativement des moyennes annuelles. Pour une vision dynamique de la trésorerie et de la capacité de financement mois par mois, se référer au Plan de Trésorerie Mensuel, qui constitue le document de référence opérationnel."
B4: 2025 | C4: 2026 | D4: 2027 | E4: 2028 | F4: 2029 | G4: 2030 | H4: 2031
A6: ACTIF
A7: Immobilisations incorporelles (R&D capitalisée) | B7: 0 | C7: 36113 | D7: 54169 | E7: 54169 | F7: 54169 | G7: 54169 | H7: 54169
A8: Immobilisations corporelles (Matériel) | B8: 0 | C8: 3333 | D8: 5000 | E8: 5000 | F8: 5000 | G8: 5000 | H8: 5000
A9: TOTAL ACTIF IMMOBILISÉ | B9: =SUM(B7:B8) -> 0 | C9: =SUM(C7:C8) -> 39446 | D9: =SUM(D7:D8) -> 59169 | E9: =SUM(E7:E8) -> 59169 | F9: =SUM(F7:F8) -> 59169 | G9: =SUM(G7:G8) -> 59169 | H9: =SUM(H7:H8) -> 59169
A11: Stocks | B11: 0 | C11: ='Compte de Résultat'!C38*'Marges Produits'!$E$49 -> 15731.888 | D11: ='Compte de Résultat'!D38*'Marges Produits'!$E$49 -> 70269.098 | E11: ='Compte de Résultat'!E38*'Marges Produits'!$E$49 -> 190880.24 | F11: ='Compte de Résultat'!F38*'Marges Produits'!$E$49 -> 259051.75 | G11: ='Compte de Résultat'!G38*'Marges Produits'!$E$49 -> 308344.99 | H11: ='Compte de Résultat'!H38*'Marges Produits'!$E$49 -> 313588.96
A12: Créances clients | B12: 0 | C12: 0 | D12: 0 | E12: 0 | F12: 0 | G12: 0 | H12: 0
A13: Trésorerie disponible | B13: =B24+B26+B27-B9-B11-B12 -> 108541.14 | C13: =C24+C26+C27-C9-C11-C12 -> 177515.96 | D13: =D24+D26+D27-D9-D11-D12 -> 167961.9 | E13: =E24+E26+E27-E9-E11-E12 -> 401098.66 | F13: =F24+F26+F27-F9-F11-F12 -> 815162.19 | G13: =G24+G26+G27-G9-G11-G12 -> 1449935.5 | H13: =H24+H26+H27-H9-H11-H12 -> 2203437.2
A14: TOTAL ACTIF CIRCULANT | B14: =SUM(B11:B13) -> 108541.14 | C14: =SUM(C11:C13) -> 193247.85 | D14: =SUM(D11:D13) -> 238231 | E14: =SUM(E11:E13) -> 591978.89 | F14: =SUM(F11:F13) -> 1074213.9 | G14: =SUM(G11:G13) -> 1758280.5 | H14: =SUM(H11:H13) -> 2517026.2
A16: TOTAL ACTIF | B16: =B9+B14 -> 108541.14 | C16: =C9+C14 -> 232693.85 | D16: =D9+D14 -> 297400 | E16: =E9+E14 -> 651147.89 | F16: =F9+F14 -> 1133382.9 | G16: =G9+G14 -> 1817449.5 | H16: =H9+H14 -> 2576195.2
A18: PASSIF
A19: Capital social | B19: 100000 | C19: 100000 | D19: 100000 | E19: 100000 | F19: 100000 | G19: 100000 | H19: 100000
A20: Comptes courants associés | B20: 0 | C20: 89000 | D20: 89000 | E20: 89000 | F20: 89000 | G20: 89000 | H20: 89000
A21: Avoir EURL JB Chandelier (compte courant) | B21: 0 | C21: 0 | D21: 50000 | E21: 50000 | F21: 50000 | G21: 50000 | H21: 50000
A22: Résultat de l'exercice | B22: ='Compte de Résultat'!B34 -> -8857.8558 | C22: ='Compte de Résultat'!C34 -> -128458.89 | D22: ='Compte de Résultat'!D34 -> 50265.066 | E22: ='Compte de Résultat'!E34 -> 382760.59 | F22: ='Compte de Résultat'!F34 -> 518386.01 | G22: ='Compte de Résultat'!G34 -> 690585.36 | H22: ='Compte de Résultat'!H34 -> 756513.57
A23: Report à nouveau (résultats antérieurs) | B23: 0 | C23: =B23+B22 -> -8857.8558 | D23: =C23+C22 -> -137316.75 | E23: =D23+D22 -> -87051.681 | F23: =E23+E22 -> 295708.91 | G23: =F23+F22 -> 814094.92 | H23: =G23+G22 -> 1504680.3
A24: TOTAL CAPITAUX PROPRES | B24: =B19+B25+B20+B21+B22+B23 -> 91142.144 | C24: =C19+C25+C20+C21+C22+C23 -> 51683.253 | D24: =D19+D25+D20+D21+D22+D23 -> 151948.32 | E24: =E19+E25+E20+E21+E22+E23 -> 534708.91 | F24: =F19+F25+F20+F21+F22+F23 -> 1053094.9 | G24: =G19+G25+G20+G21+G22+G23 -> 1743680.3 | H24: =H19+H25+H20+H21+H22+H23 -> 2500193.8
A25: Apport complémentaire dirigeant * | B25: 0 | C25: 0 | D25: 0 | E25: 0 | F25: 0 | G25: 0 | H25: 0
A26: Emprunt bancaire (capital restant dû) | B26: 0 | C26: ='Emprunt Bancaire'!D47 -> 159810 | D26: ='Emprunt Mensualité'!I26 -> 114353.37 | E26: ='Emprunt Mensualité'!I40 -> 66808.3 | F26: ='Emprunt Mensualité'!I54 -> 17079.02 | G26: ='Emprunt Mensualité'!I60 -> 0 | H26: 0
A27: Dettes d'exploitation | B27: =B44+B45+B46 -> 17399 | C27: =C44+C45+C46 -> 21200.594 | D27: =D44+D45+D46 -> 31098.312 | E27: =E44+E45+E46 -> 49630.688 | F27: =F44+F45+F46 -> 63209 | G27: =G44+G45+G46 -> 73769.25 | H27: =H44+H45+H46 -> 76001.312
A28: TOTAL DETTES | B28: =B26+B27 -> 17399 | C28: =C26+C27 -> 181010.59 | D28: =D26+D27 -> 145451.68 | E28: =E26+E27 -> 116438.99 | F28: =F26+F27 -> 80288.02 | G28: =G26+G27 -> 73769.25 | H28: =H26+H27 -> 76001.312
A30: TOTAL PASSIF | B30: =B24+B28 -> 108541.14 | C30: =C24+C28 -> 232693.85 | D30: =D24+D28 -> 297400 | E30: =E24+E28 -> 651147.89 | F30: =F24+F28 -> 1133382.9 | G30: =G24+G28 -> 1817449.5 | H30: =H24+H28 -> 2576195.2
B32: 0 | C32: 0 | D32: 0 | E32: 0 | F32: 0 | G32: 0 | H32: 0
A33: ━━━━━━━━━━━━━━━━━━━━━━━━━━━━━━━━━━━━━━━━━━━━━━━━━━━━━━━━━━━━━━━━━━━━━━━━━━━━━━
A34: 📊 RATIOS FINANCIERS
A35: Année | B35: 2025 | C35: 2026 | D35: 2027 | E35: 2028 | F35: 2029 | G35: 2030 | H35: 2031
A36: Ratio d'endettement (Dettes/CP) | B36: =IF(B24=0,"-",ROUND(B28/B24,2)) -> 0.19 | C36: =IF(C24=0,"-",ROUND(C28/C24,2)) -> 3.5 | D36: =IF(D24=0,"-",ROUND(D28/D24,2)) -> 0.96 | E36: =IF(E24=0,"-",ROUND(E28/E24,2)) -> 0.22 | F36: =IF(F24=0,"-",ROUND(F28/F24,2)) -> 0.08 | G36: =IF(G24=0,"-",ROUND(G28/G24,2)) -> 0.04 | H36: =IF(H24=0,"-",ROUND(H28/H24,2)) -> 0.03
A37: Autonomie financière (CP/Total) | B37: =IF(B30=0,"-",ROUND(B24/B30*100,1)&"%") -> 84% | C37: =IF(C30=0,"-",ROUND(C24/C30*100,1)&"%") -> 22,2% | D37: =IF(D30=0,"-",ROUND(D24/D30*100,1)&"%") -> 51,1% | E37: =IF(E30=0,"-",ROUND(E24/E30*100,1)&"%") -> 82,1% | F37: =IF(F30=0,"-",ROUND(F24/F30*100,1)&"%") -> 92,9% | G37: =IF(G30=0,"-",ROUND(G24/G30*100,1)&"%") -> 95,9% | H37: =IF(H30=0,"-",ROUND(H24/H30*100,1)&"%") -> 97%
A38: Trésorerie disponible (k€) | B38: =ROUND(B13/1000,0) -> 109 | C38: =ROUND(C13/1000,0) -> 178 | D38: =ROUND(D13/1000,0) -> 168 | E38: =ROUND(E13/1000,0) -> 401 | F38: =ROUND(F13/1000,0) -> 815 | G38: =ROUND(G13/1000,0) -> 1450 | H38: =ROUND(H13/1000,0) -> 2203
A40: ━━━━━━━━━━━━━━━━━━━━━━━━━━━━━━━━━━━━━━━━━━━━━━━━━━━━━━━━━━━━━━━━━━━━━━━━━━━━━━
A41: 📋 VENTILATION DES DETTES
A42: Année | B42: 2025 | C42: 2026 | D42: 2027 | E42: 2028 | F42: 2029 | G42: 2030 | H42: 2031
A43: Emprunt bancaire (CRD) | B43: =B26 -> 0 | C43: =C26 -> 159810 | D43: =D26 -> 114353.37 | E43: =E26 -> 66808.3 | F43: =F26 -> 17079.02 | G43: =G26 -> 0 | H43: =H26 -> 0
A44: Dettes fournisseurs (stock) | B44: =ROUND(B11*0.05,0) -> 0 | C44: =ROUND(C11*(3/52),0) -> 908 | D44: =ROUND(D11*(3/52),0) -> 4054 | E44: =ROUND(E11*(3/52),0) -> 11012 | F44: =ROUND(F11*(3/52),0) -> 14945 | G44: =ROUND(G11*(3/52),0) -> 17789 | H44: =ROUND(H11*(3/52),0) -> 18092
A45: Charges à payer | B45: =ROUND('Charges Fixes Plume'!D57/12,0) -> 17399 | C45: =ROUND('Charges Fixes Plume'!D57/12,0) -> 17399 | D45: =ROUND('Charges Fixes Plume'!D57/12,0) -> 17399 | E45: =ROUND('Charges Fixes Plume'!D57/12,0) -> 17399 | F45: =ROUND('Charges Fixes Plume'!D57/12,0) -> 17399 | G45: =ROUND('Charges Fixes Plume'!D57/12,0) -> 17399 | H45: =ROUND('Charges Fixes Plume'!D57/12,0) -> 17399
A46: Autres dettes (TVA, PCA, régul.) | B46: =('Compte de Résultat'!B13*0.015) -> 0 | C46: =('Compte de Résultat'!C13*0.015) -> 2893.5938 | D46: =('Compte de Résultat'!D13*0.015) -> 9645.3125 | E46: =('Compte de Résultat'!E13*0.015) -> 21219.688 | F46: =('Compte de Résultat'!F13*0.015) -> 30865 | G46: =('Compte de Résultat'!G13*0.015) -> 38581.25 | H46: =('Compte de Résultat'!H13*0.015) -> 40510.313
A47: TOTAL DETTES | B47: =SUM(B43:B46) -> 17399 | C47: =SUM(C43:C46) -> 181010.59 | D47: =SUM(D43:D46) -> 145451.68 | E47: =SUM(E43:E46) -> 116438.99 | F47: =SUM(F43:F46) -> 80288.02 | G47: =SUM(G43:G46) -> 73769.25 | H47: =SUM(H43:H46) -> 76001.312
A49: ━━━━━━━━━━━━━━━━━━━━━━━━━━━━━━━━━━━━━━━━━━━━━━━━━━━━━━━━━━━━━━━━━━━━━━━━━━━━━━
A50: 📝 NOTES
A51: * Montant conditionnel (30k€) : présenté ici comme apport CC dirigeant.
A52: Si subvention BPI obtenue, ce montant sera reclassé en subvention d'investissement.
A53: Dans les deux cas : pas de modification de la structure actionnariale (55%/45%).
A54: • Avoir EURL JB (50k€) : versement prévu janvier 2027
A55: * Ventilation indicative des dettes d'exploitation (délais standards 30j)

Sheet Seuil Rentabilité
A1: SEUIL DE RENTABILITÉ & BFR - PLUME PARAGLIDERS
A3: PARAMÈTRES DE BASE
A4: Prix moyen HT | B4: ='Marges Produits'!C49 -> 2572.0833
A5: Marge brute par aile | B5: ='Marges Produits'!D49 -> 1100.3575
A6: Coût de revient par aile | B6: ='Marges Produits'!E49 -> 1048.7925
A7: Assurance par aile (0.8% du prix) | B7: =B4*0.008 -> 20.576667
A8: Marge nette par aile (marge - assurance) | B8: =B5-B7 -> 1079.7808
A9: Stock cible (% des ventes) | B9: 0.25
A10: Charges fixes annuelles (réf Charges Fixes D50) | B10: ='Charges Fixes Plume'!D38+'Charges Fixes Plume'!D29+'Charges Fixes Plume'!D13 -> 208782.33
A13: CALCUL PAR ANNÉE
A14: Année | B14: 2025 | C14: 2026 | D14: 2027 | E14: 2028 | F14: 2029 | G14: 2030 | H14: 2031
A15: Charges fixes exploitation | B15: =SUM('Plan Trésorerie Mensuel'!B16:B23) -> 7702.4833 | C15: =SUM('Plan Trésorerie Mensuel'!C16:N23) -> 203699.82 | D15: =SUM('Plan Trésorerie Mensuel'!B47:M53) -> 212738.23 | E15: =SUM('Plan Trésorerie Mensuel'!N47:Y53) -> 206265.23 | F15: =SUM('Plan Trésorerie Mensuel'!Z47:AK53) -> 342769.23 | G15: =SUM('Plan Trésorerie Mensuel'!AL47:AW53) -> 342769.23 | H15: =SUM('Plan Trésorerie Mensuel'!AX47:BI53) -> 342769.23
A16: Intérêts financiers (2026-2029) | B16: ='Compte de Résultat'!B20 -> 0 | C16: ='Compte de Résultat'!C20 -> 5742.63 | D16: ='Compte de Résultat'!D20 -> 6941.91 | E16: ='Compte de Résultat'!E20 -> 4853.64 | F16: ='Compte de Résultat'!F20 -> 2669.42 | G16: ='Compte de Résultat'!G20 -> 387.22 | H16: ='Compte de Résultat'!H20 -> 0
A17: TOTAL CHARGES FIXES | B17: =B15+B16 -> 7702.4833 | C17: =C15+C16 -> 209442.45 | D17: =D15+D16 -> 219680.14 | E17: =E15+E16 -> 211118.87 | F17: =F15+F16 -> 345438.65 | G17: =G15+G16 -> 343156.45 | H17: =H15+H16 -> 342769.23
A19: 🔵 SEUIL DE RENTABILITÉ
A20: Seuil = Charges Fixes / Marge nette par aile
A21: SEUIL (nb ailes pour équilibre exploitation) | B21: =IF(B17=0,0,ROUNDUP(B17/$B$8,0)) -> 8 | C21: =IF(C17=0,0,ROUNDUP(C17/$B$8,0)) -> 194 | D21: =IF(D17=0,0,ROUNDUP(D17/$B$8,0)) -> 204 | E21: =IF(E17=0,0,ROUNDUP(E17/$B$8,0)) -> 196 | F21: =IF(F17=0,0,ROUNDUP(F17/$B$8,0)) -> 320 | G21: =IF(G17=0,0,ROUNDUP(G17/$B$8,0)) -> 318 | H21: =IF(H17=0,0,ROUNDUP(H17/$B$8,0)) -> 318
A23: COMPARAISON AVEC SCÉNARIOS
A24: 🔵 Seuil de rentabilité | B24: =B21 -> 8 | C24: =C21 -> 194 | D24: =D21 -> 204 | E24: =E21 -> 196 | F24: =F21 -> 320 | G24: =G21 -> 318 | H24: =H21 -> 318
A25: 🟠 Scénario Réaliste | B25: =Scénarios!B16 -> 0 | C25: =Scénarios!C16 -> 75 | D25: =Scénarios!D16 -> 250 | E25: =Scénarios!E16 -> 550 | F25: =Scénarios!F16 -> 800 | G25: =Scénarios!G16 -> 1000 | H25: =Scénarios!H16 -> 1000
A27: Écart Réaliste vs Seuil | B27: =B25-B21 -> -8 | C27: =C25-C21 -> -119 | D27: =D25-D21 -> 46 | E27: =E25-E21 -> 354 | F27: =F25-F21 -> 480 | G27: =G25-G21 -> 682 | H27: =H25-H21 -> 682
A29: BFR - GESTION DU STOCK (Scénario Réaliste)
A30: Stock = 25% des ventes. Variation = achat ou vente de stock.
A31: Stock cible (nb ailes = 25% ventes) | B31: =B25*$B$9 -> 0 | C31: =C25*$B$9 -> 18.75 | D31: =D25*$B$9 -> 62.5 | E31: =E25*$B$9 -> 137.5 | F31: =F25*$B$9 -> 200 | G31: =G25*$B$9 -> 250 | H31: =H25*$B$9 -> 250
A32: Stock cible (€ = nb ailes × coût) | B32: =B31*$B$6 -> 0 | C32: =C31*$B$6 -> 19664.859 | D32: =D31*$B$6 -> 65549.531 | E32: =E31*$B$6 -> 144208.97 | F32: =F31*$B$6 -> 209758.5 | G32: =G31*$B$6 -> 262198.12 | H32: =H31*$B$6 -> 262198.12
A33: Variation stock (+ = investir / - = récupérer) | B33: =B32 -> 0 | C33: =C32-B32 -> 19664.859 | D33: =D32-C32 -> 45884.672 | E33: =E32-D32 -> 78659.438 | F33: =F32-E32 -> 65549.531 | G33: =G32-F32 -> 52439.625 | H33: =H32-G32 -> 0
A35: 💡 Si ventes baissent → stock cible baisse → on revend du stock → tréso +
A36: 💡 Si ventes augmentent → stock cible augmente → on achète du stock → tréso -

Sheet -30% Plan Trésorerie Mensuel 
A1: PLAN DE TRÉSORERIE MENSUEL - PLUME PARAGLIDERS
A2: Création : 18 décembre 2025 • Délais de financement réalistes | E2: scenario: | F2: 0.7
A4: 📅 ANNÉE 2026 : LANCEMENT
B5: Déc 25 | C5: Jan | D5: Fév | E5: Mar | F5: Avr | G5: Mai | H5: Juin | I5: Juil | J5: Août | K5: Sept | L5: Oct | M5: Nov | N5: Déc | O5: TOTAL
A6: ENTRÉES
A7: Capital social | B7: =Dashboard!B9 -> 100000 | C7: 0 | D7: 0 | E7: 0 | F7: 0 | G7: 0 | H7: 0 | I7: 0 | J7: 0 | K7: 0 | L7: 0 | M7: 0 | N7: 0 | O7: =SUM(B7:N7) -> 100000
A8: Comptes courants associés | B8: 0 | C8: 89000 | D8: 0 | E8: 0 | F8: 0 | G8: 0 | H8: 0 | I8: 0 | J8: 0 | K8: 0 | L8: 0 | M8: 0 | N8: 0 | O8: =SUM(B8:N8) -> 89000
A9: Emprunt bancaire | B9: 0 | C9: 0 | D9: 0 | F9: 0 | G9: ='Emprunt Bancaire'!B4 -> 189000 | H9: 0 | I9: 0 | J9: 0 | K9: 0 | L9: 0 | M9: 0 | N9: 0 | O9: =SUM(B9:N9) -> 189000
O10: =SUM(O8:O9) -> 278000
A12: CA Ventes (HT) | B12: 0 | C12: =C35*'Marges Produits'!$C$49 -> 0 | D12: =D35*'Marges Produits'!$C$49 -> 0 | E12: =E35*'Marges Produits'!$C$49 -> 0 | F12: =F35*'Marges Produits'!$C$49 -> 10288.333 | G12: =G35*'Marges Produits'!$C$49 -> 12860.417 | H12: =H35*'Marges Produits'!$C$49 -> 15432.5 | I12: =I35*'Marges Produits'!$C$49 -> 20576.667 | J12: =J35*'Marges Produits'!$C$49 -> 20576.667 | ... N12: =N35*'Marges Produits'!$C$49 -> 10288.333 | O12: =SUM(B12:N12) -> 136320.42
A13: Total entrées | B13: =SUM(B7:B12) -> 100000 | C13: =SUM(C7:C12) -> 89000 | D13: =SUM(D7:D12) -> 0 | E13: =SUM(E7:E12) -> 0 | F13: =SUM(F7:F12) -> 10288.333 | G13: =SUM(G7:G12) -> 201860.42 | H13: =SUM(H7:H12) -> 15432.5 | I13: =SUM(I7:I12) -> 20576.667 | ... N13: =SUM(N7:N12) -> 10288.333 | O13: =SUM(B13:N13) -> 514320.42
A15: SORTIES
A16: Frais création | B16: ='Frais de lancement'!B9 -> 3803 | C16: 0 | D16: 0 | E16: 0 | F16: 0 | G16: 0 | H16: 0 | I16: 0 | J16: 0 | K16: 0 | L16: 0 | M16: 0 | N16: 0 | O16: =SUM(B16:N16) -> 3803
A17: Frais prototype | B17: 0 | C17: ='Charges Fixes Plume'!G34 -> 10000 | D17: ='Charges Fixes Plume'!H34 -> 0 | E17: ='Charges Fixes Plume'!I34 -> 0 | F17: ='Charges Fixes Plume'!J34 -> 0 | G17: ='Charges Fixes Plume'!K34 -> 2517.102 | H17: ='Charges Fixes Plume'!L34 -> 2517.102 | I17: ='Charges Fixes Plume'!M34 -> 2517.102 | J17: ='Charges Fixes Plume'!N34 -> 2517.102 | ... N17: ='Charges Fixes Plume'!R34 -> 2517.102 | O17: =SUM(B17:N17) -> 30136.816
A18: Veille concurrentielle | B18: 0 | C18: 2500 | D18: 0 | E18: 0 | F18: 0 | G18: 0 | H18: 0 | I18: 2500 | J18: 0 | K18: 0 | L18: 0 | M18: 0 | N18: 0 | O18: =SUM(B18:N18) -> 5000
A19: Masse salariale | B19: ='Charges Fixes Plume'!R$13/2 -> 2170.8333 | C19: ='Charges Fixes Plume'!G13 -> 10907.667 | D19: ='Charges Fixes Plume'!H13 -> 6341.6667 | E19: ='Charges Fixes Plume'!I13 -> 10907.667 | F19: ='Charges Fixes Plume'!J13 -> 4341.6667 | G19: ='Charges Fixes Plume'!K13 -> 8907.6667 | H19: ='Charges Fixes Plume'!L13 -> 4341.6667 | I19: ='Charges Fixes Plume'!M13 -> 7907.6667 | J19: ='Charges Fixes Plume'!N13 -> 3341.6667 | ... N19: ='Charges Fixes Plume'!R13 -> 4341.6667 | O19: =SUM(B19:N19) -> 85666.833
A20: CHARGES DE CROISSANCE ( si n-1 = + 500ailes)
A21: Charges exploitation | B21: ='Charges Fixes Plume'!R$29/2 -> 1728.65 | C21: ='Charges Fixes Plume'!G29 -> 9057.3 | D21: ='Charges Fixes Plume'!H29 -> 3977.3 | E21: ='Charges Fixes Plume'!I29 -> 3407.3 | F21: ='Charges Fixes Plume'!J29 -> 4407.3 | G21: ='Charges Fixes Plume'!K29 -> 3407.3 | H21: ='Charges Fixes Plume'!L29 -> 3407.3 | I21: ='Charges Fixes Plume'!M29 -> 4407.3 | J21: ='Charges Fixes Plume'!N29 -> 3407.3 | ... N21: ='Charges Fixes Plume'!R29 -> 3457.3 | O21: =SUM(B21:N21) -> 51886.25
A22: Pré-série homologation (10) | B22: 0 | C22: 0 | D22: 0 | E22: ='Charges Fixes Plume'!C36*4 -> 5034.204 | F22: 0 | G22: =4*'Charges Fixes Plume'!$C$36 -> 5034.204 | H22: 0 | I22: 0 | K22: 0 | L22: 0 | M22: 0 | N22: 0 | O22: =SUM(B22:N22) -> 10068.408
A23: Tests homologation EN | B23: 0 | C23: 0 | D23: 0 | F23: 11172 | G23: 0 | H23: ='Charges Fixes Plume'!C37 -> 13669 | I23: 0 | K23: 0 | L23: 0 | M23: 0 | N23: 0 | O23: =SUM(B23:N23) -> 24841
A24: Production stock parapente | B24: 0 | C24: =C34*'Marges Produits'!$E$49 -> 0 | D24: =D34*'Marges Produits'!$E$49 -> 0 | E24: =E34*'Marges Produits'!$E$49 -> 0 | F24: =F34*'Marges Produits'!$E$49 -> 7341.5475 | G24: =G34*'Marges Produits'!$E$49 -> 14683.095 | H24: =H34*'Marges Produits'!$E$49 -> 14683.095 | I24: =I34*'Marges Produits'!$E$49 -> 13634.302 | J24: =J34*'Marges Produits'!$E$49 -> 7341.5475 | ... N24: =N34*'Marges Produits'!$E$49 -> 0 | O24: =SUM(B24:N24) -> 67122.72
A25: Remboursement emprunt | B25: 0 | C25: 0 | D25: 0 | E25: 0 | G25: ='Emprunt Bancaire'!$B$27 -> 4367 | H25: ='Emprunt Bancaire'!$B$27 -> 4367 | I25: ='Emprunt Bancaire'!$B$27 -> 4367 | J25: ='Emprunt Bancaire'!$B$27 -> 4367 | K25: ='Emprunt Bancaire'!$B$27 -> 4367 | L25: ='Emprunt Bancaire'!$B$27 -> 4367 | M25: ='Emprunt Bancaire'!$B$27 -> 4367 | N25: ='Emprunt Bancaire'!$B$27 -> 4367 | O25: =SUM(B25:N25) -> 34936
A26: Assurance RC (0.8% CA) | B26: =B12*0.008 -> 0 | C26: =C12*0.008 -> 0 | D26: =D12*0.008 -> 0 | E26: =E12*0.008 -> 0 | F26: =F12*0.008 -> 82.306667 | G26: =G12*0.008 -> 102.88333 | H26: =H12*0.008 -> 123.46 | I26: =I12*0.008 -> 164.61333 | ... N26: =N12*0.008 -> 82.306667 | O26: =SUM(B26:N26) -> 1090.5633
A27: imprévue: 15% de total sortie | B27: {=SUM(B16:B26*0.15)} -> 1155.3725 | C27: {=SUM(C16:C26*0.15)} -> 4869.745 | D27: {=SUM(D16:D26*0.15)} -> 1547.845 | E27: {=SUM(E16:E26*0.15)} -> 2902.3756 | F27: {=SUM(F16:F26*0.15)} -> 4101.7231 | G27: {=SUM(G16:G26*0.15)} -> 5852.8877 | H27: {=SUM(H16:H26*0.15)} -> 6466.2936 | I27: {=SUM(I16:I26*0.15)} -> 5324.6977 | ... N27: {=SUM(N16:N26*0.15)} -> 2214.8063 | O27: =SUM(B27:N27) -> 47182.739
A28: Total sorties | B28: =SUM(B16:B27) -> 8857.8558 | C28: =SUM(C16:C27) -> 37334.712 | D28: =SUM(D16:D27) -> 11866.812 | E28: =SUM(E16:E27) -> 22251.546 | F28: =SUM(F16:F27) -> 31446.544 | G28: =SUM(G16:G27) -> 44872.139 | H28: =SUM(H16:H27) -> 49574.917 | I28: =SUM(I16:I27) -> 40822.682 | ... N28: =SUM(N16:N27) -> 16980.182 | O28: =SUM(B28:N28) -> 361734.33
A30: FLUX MENSUEL | B30: =B13-B28 -> 91142.144 | C30: =C13-C28 -> 51665.288 | D30: =D13-D28 -> -11866.812 | E30: =E13-E28 -> -22251.546 | F30: =F13-F28 -> -21158.211 | G30: =G13-G28 -> 156988.28 | H30: =H13-H28 -> -34142.417 | I30: =I13-I28 -> -20246.016 | ... N30: =N13-N28 -> -6691.8483 | O30: =SUM(C30:N30) -> 61443.943
A31: TRÉSORERIE CUMULÉE | B31: =B30 -> 91142.144 | C31: =B31+C30 -> 142807.43 | D31: =C31+D30 -> 130940.62 | E31: =D31+E30 -> 108689.07 | F31: =E31+F30 -> 87530.864 | G31: =F31+G30 -> 244519.14 | H31: =G31+H30 -> 210376.72 | I31: =H31+I30 -> 190130.71 | J31: =I31+J30 -> 186397.26 | ... N31: =M31+N30 -> 152586.09
A33: 📦 Volumes
A34: Production (nb ailes) | B34: =ROUND(('-30% Plan Trésorerie Mensuel '!$F$2*'Plan Trésorerie Mensuel'!B34),0) -> 0 | C34: =ROUND(('-30% Plan Trésorerie Mensuel '!$F$2*'Plan Trésorerie Mensuel'!C34),0) -> 0 | D34: =ROUND(('-30% Plan Trésorerie Mensuel '!$F$2*'Plan Trésorerie Mensuel'!D34),0) -> 0 | E34: =ROUND(('-30% Plan Trésorerie Mensuel '!$F$2*'Plan Trésorerie Mensuel'!E34),0) -> 0 | F34: =ROUND(('-30% Plan Trésorerie Mensuel '!$F$2*'Plan Trésorerie Mensuel'!F34),0) -> 7 | G34: =ROUND(('-30% Plan Trésorerie Mensuel '!$F$2*'Plan Trésorerie Mensuel'!G34),0) -> 14 | H34: =ROUND(('-30% Plan Trésorerie Mensuel '!$F$2*'Plan Trésorerie Mensuel'!H34),0) -> 14 | I34: =ROUND(('-30% Plan Trésorerie Mensuel '!$F$2*'Plan Trésorerie Mensuel'!I34),0) -> 13 | ... N34: =ROUND(('-30% Plan Trésorerie Mensuel '!$F$2*'Plan Trésorerie Mensuel'!N34),0) -> 0 | O34: =SUM(B34:N34) -> 64
A35: Ventes (nb ailes) | B35: =ROUND(('-30% Plan Trésorerie Mensuel '!$F$2*'Plan Trésorerie Mensuel'!B35),0) -> 0 | C35: =ROUND(('-30% Plan Trésorerie Mensuel '!$F$2*'Plan Trésorerie Mensuel'!C35),0) -> 0 | D35: =ROUND(('-30% Plan Trésorerie Mensuel '!$F$2*'Plan Trésorerie Mensuel'!D35),0) -> 0 | E35: =ROUND(('-30% Plan Trésorerie Mensuel '!$F$2*'Plan Trésorerie Mensuel'!E35),0) -> 0 | F35: =ROUND(('-30% Plan Trésorerie Mensuel '!$F$2*'Plan Trésorerie Mensuel'!F35),0) -> 4 | G35: =ROUND(('-30% Plan Trésorerie Mensuel '!$F$2*'Plan Trésorerie Mensuel'!G35),0) -> 5 | H35: =ROUND(('-30% Plan Trésorerie Mensuel '!$F$2*'Plan Trésorerie Mensuel'!H35),0) -> 6 | I35: =ROUND(('-30% Plan Trésorerie Mensuel '!$F$2*'Plan Trésorerie Mensuel'!I35),0) -> 8 | ... N35: =ROUND(('-30% Plan Trésorerie Mensuel '!$F$2*'Plan Trésorerie Mensuel'!N35),0) -> 4 | O35: =SUM(B35:N35) -> 53
A36: Stock fin de mois | B36: 0 | C36: =(C34+B36)-C35 -> 0 | D36: =(D34+C36)-D35 -> 0 | E36: =(E34+D36)-E35 -> 0 | F36: =(F34+E36)-F35 -> 3 | G36: =(G34+F36)-G35 -> 12 | H36: =(H34+G36)-H35 -> 20 | I36: =(I34+H36)-I35 -> 25 | J36: =(J34+I36)-J35 -> 24 | ... N36: =(N34+M36)-N35 -> 11
A39: 📅 ANNÉE 2027 : CROISSANCE | B39: 📅 ANNÉE 2027 : CROISSANCE | N39: 📅 ANNÉE 2028 : CROISSANCE | Z39: 📅 ANNÉE 2029 : CROISSANCE | AL39: 📅 ANNÉE 2030 : CROISSANCE | AX39: 📅 ANNÉE 2031 : CROISSANCE
B40: Jan | C40: Fév | D40: Mar | E40: Avr | F40: Mai | G40: Juin | H40: Juil | I40: Août | J40: Sept | K40: Oct | L40: Nov | M40: Déc | N40: Jan | O40: Fév | P40: Mar | Q40: Avr | R40: Mai | S40: Juin | T40: Juil | U40: Août | V40: Sept | W40: Oct | X40: Nov | Y40: Déc | Z40: Jan | AA40: Fév | AB40: Mar | AC40: Avr | AD40: Mai | AE40: Juin | AF40: Juil | AG40: Août | AH40: Sept | AI40: Oct | AJ40: Nov | AK40: Déc | AL40: Jan | AM40: Fév | AN40: Mar | AO40: Avr | AP40: Mai | AQ40: Juin | AR40: Juil | AS40: Août | AT40: Sept | AU40: Oct | AV40: Nov | AW40: Déc | AX40: Jan | AY40: Fév | AZ40: Mar | BA40: Avr | BB40: Mai | BC40: Juin | BD40: Juil | BE40: Août | BF40: Sept | BG40: Oct | BH40: Nov | BI40: Déc
A41: ENTRÉES
A42: Apport | B42: 0 | C42: 0 | D42: 50000 | E42: 0 | F42: 0 | G42: 0 | H42: 0 | I42: 0 | J42: 0 | K42: 0 | L42: 0 | M42: 0
A43: CA Ventes (HT) | B43: =B65*'Marges Produits'!$C$49 -> 10288.333 | C43: =C65*'Marges Produits'!$C$49 -> 18004.583 | D43: =D65*'Marges Produits'!$C$49 -> 28292.917 | E43: =E65*'Marges Produits'!$C$49 -> 46297.5 | F43: =F65*'Marges Produits'!$C$49 -> 64302.083 | G43: =G65*'Marges Produits'!$C$49 -> 64302.083 | H43: =H65*'Marges Produits'!$C$49 -> 64302.083 | I43: =I65*'Marges Produits'!$C$49 -> 54013.75 | ... AW43: =AW65*'Marges Produits'!$C$49 -> 69446.25 | AX43: =AX65*(('Marges Produits'!$C$49)*1.05) -> 94524.063 | AY43: =AY65*(('Marges Produits'!$C$49)*1.05) -> 105326.81 | AZ43: =AZ65*(('Marges Produits'!$C$49)*1.05) -> 153939.19 | BA43: =BA65*(('Marges Produits'!$C$49)*1.05) -> 199850.88 | BB43: =BB65*(('Marges Produits'!$C$49)*1.05) -> 237660.5 | BC43: =BC65*(('Marges Produits'!$C$49)*1.05) -> 237660.5 | BD43: =BD65*(('Marges Produits'!$C$49)*1.05) -> 237660.5 | BE43: =BE65*(('Marges Produits'!$C$49)*1.05) -> 199850.88 | ... BI43: =BI65*(('Marges Produits'!$C$49)*1.05) -> 72918.563
A44: Total entrées | B44: =SUM(B42:B43) -> 10288.333 | C44: =SUM(C42:C43) -> 18004.583 | D44: =SUM(D42:D43) -> 78292.917 | E44: =SUM(E42:E43) -> 46297.5 | F44: =SUM(F42:F43) -> 64302.083 | G44: =SUM(G42:G43) -> 64302.083 | H44: =SUM(H42:H43) -> 64302.083 | I44: =SUM(I42:I43) -> 54013.75 | ... BI44: =SUM(BI42:BI43) -> 72918.563
A46: SORTIES
A47: Frais prototype | B47: ='Charges Fixes Plume'!$C$34*2 -> 2517.102 | C47: ='Charges Fixes Plume'!$C$34*2 -> 2517.102 | D47: ='Charges Fixes Plume'!$C$34*2 -> 2517.102 | E47: ='Charges Fixes Plume'!$C$34*2 -> 2517.102 | F47: ='Charges Fixes Plume'!$C$34*2 -> 2517.102 | G47: ='Charges Fixes Plume'!$C$34*2 -> 2517.102 | H47: ='Charges Fixes Plume'!$C$34*2 -> 2517.102 | I47: ='Charges Fixes Plume'!$C$34*2 -> 2517.102 | ... BI47: ='Charges Fixes Plume'!$C$34*2 -> 2517.102
A48: Veille concurrentielle | B48: 2500 | C48: 0 | D48: 0 | E48: 0 | F48: 0 | G48: 0 | H48: 2500 | I48: 0 | J48: 0 | K48: 0 | L48: 0 | M48: 0 | N48: =B48 -> 2500 | O48: =C48 -> 0 | P48: =D48 -> 0 | Q48: =E48 -> 0 | R48: =F48 -> 0 | S48: =G48 -> 0 | T48: =H48 -> 2500 | U48: =I48 -> 0 | ... BI48: =AW48 -> 0
A49: Masse salariale | B49: =C19 -> 10907.667 | C49: =D19 -> 6341.6667 | D49: =E19 -> 10907.667 | E49: =F19 -> 4341.6667 | F49: =G19 -> 8907.6667 | G49: =H19 -> 4341.6667 | H49: =I19 -> 7907.6667 | I49: =J19 -> 3341.6667 | ... M49: =N19 -> 4341.6667 | N49: =B49 -> 10907.667 | O49: =C49 -> 6341.6667 | P49: =D49 -> 10907.667 | Q49: =E49 -> 4341.6667 | R49: =F49 -> 8907.6667 | S49: =G49 -> 4341.6667 | T49: =H49 -> 7907.6667 | U49: =I49 -> 3341.6667 | ... BI49: =AW49 -> 4341.6667
A50: CHARGES DE CROISSANCE ( si n-1 = + 500ailes) | B50: =IF($O$35>499,'Charges Fixes Plume'!G55,0) -> 0 | C50: =IF($O$35>499,'Charges Fixes Plume'!H55,0) -> 0 | D50: =IF($O$35>499,'Charges Fixes Plume'!I55,0) -> 0 | E50: =IF($O$35>499,'Charges Fixes Plume'!J55,0) -> 0 | F50: =IF($O$35>499,'Charges Fixes Plume'!K55,0) -> 0 | G50: =IF($O$35>499,'Charges Fixes Plume'!L55,0) -> 0 | H50: =IF($O$35>499,'Charges Fixes Plume'!M55,0) -> 0 | I50: =IF($O$35>499,'Charges Fixes Plume'!N55,0) -> 0 | ... M50: =IF($O$35>499,'Charges Fixes Plume'!R55,0) -> 0 | N50: =IF($M$68>499,'Charges Fixes Plume'!G55,0) -> 0 | O50: =IF($M$68>499,'Charges Fixes Plume'!H55,0) -> 0 | P50: =IF($M$68>499,'Charges Fixes Plume'!I55,0) -> 0 | Q50: =IF($M$68>499,'Charges Fixes Plume'!J55,0) -> 0 | R50: =IF($M$68>499,'Charges Fixes Plume'!K55,0) -> 0 | S50: =IF($M$68>499,'Charges Fixes Plume'!L55,0) -> 0 | T50: =IF($M$68>499,'Charges Fixes Plume'!M55,0) -> 0 | U50: =IF($M$68>499,'Charges Fixes Plume'!N55,0) -> 0 | ... Y50: =IF($M$68>499,'Charges Fixes Plume'!R55,0) -> 0 | Z50: =IF($Y$68>499,'Charges Fixes Plume'!G55,0) -> 0 | AA50: =IF($Y$68>499,'Charges Fixes Plume'!H55,0) -> 0 | AB50: =IF($Y$68>499,'Charges Fixes Plume'!I55,0) -> 0 | AC50: =IF($Y$68>499,'Charges Fixes Plume'!J55,0) -> 0 | AD50: =IF($Y$68>499,'Charges Fixes Plume'!K55,0) -> 0 | AE50: =IF($Y$68>499,'Charges Fixes Plume'!L55,0) -> 0 | AF50: =IF($Y$68>499,'Charges Fixes Plume'!M55,0) -> 0 | AG50: =IF($Y$68>499,'Charges Fixes Plume'!N55,0) -> 0 | ... AK50: =IF($Y$68>499,'Charges Fixes Plume'!R55,0) -> 0 | AL50: =IF($AK$68>499,'Charges Fixes Plume'!G55,0) -> 11375.333 | AM50: =IF($AK$68>499,'Charges Fixes Plume'!H55,0) -> 11375.333 | AN50: =IF($AK$68>499,'Charges Fixes Plume'!I55,0) -> 11375.333 | AO50: =IF($AK$68>499,'Charges Fixes Plume'!J55,0) -> 11375.333 | AP50: =IF($AK$68>499,'Charges Fixes Plume'!K55,0) -> 11375.333 | AQ50: =IF($AK$68>499,'Charges Fixes Plume'!L55,0) -> 11375.333 | AR50: =IF($AK$68>499,'Charges Fixes Plume'!M55,0) -> 11375.333 | AS50: =IF($AK$68>499,'Charges Fixes Plume'!N55,0) -> 11375.333 | ... AW50: =IF($AK$68>499,'Charges Fixes Plume'!R55,0) -> 11375.333 | AX50: =IF($AW$68>499,'Charges Fixes Plume'!G55,0) -> 11375.333 | AY50: =IF($AW$68>499,'Charges Fixes Plume'!H55,0) -> 11375.333 | AZ50: =IF($AW$68>499,'Charges Fixes Plume'!I55,0) -> 11375.333 | BA50: =IF($AW$68>499,'Charges Fixes Plume'!J55,0) -> 11375.333 | BB50: =IF($AW$68>499,'Charges Fixes Plume'!K55,0) -> 11375.333 | BC50: =IF($AW$68>499,'Charges Fixes Plume'!L55,0) -> 11375.333 | BD50: =IF($AW$68>499,'Charges Fixes Plume'!M55,0) -> 11375.333 | BE50: =IF($AW$68>499,'Charges Fixes Plume'!N55,0) -> 11375.333 | ... BI50: =IF($AW$68>499,'Charges Fixes Plume'!R55,0) -> 11375.333
A51: Charges exploitation | B51: =C21 -> 9057.3 | C51: =D21 -> 3977.3 | D51: =E21 -> 3407.3 | E51: =F21 -> 4407.3 | F51: =G21 -> 3407.3 | G51: =H21 -> 3407.3 | H51: =I21 -> 4407.3 | I51: =J21 -> 3407.3 | ... M51: =N21 -> 3457.3 | N51: =B51 -> 9057.3 | O51: =C51 -> 3977.3 | P51: =D51 -> 3407.3 | Q51: =E51 -> 4407.3 | R51: =F51 -> 3407.3 | S51: =G51 -> 3407.3 | T51: =H51 -> 4407.3 | U51: =I51 -> 3407.3 | ... BI51: =AW51 -> 3457.3
A52: Pré-série homologation (10) | B52: =C22 -> 0 | C52: =D22 -> 0 | D52: =E22 -> 5034.204 | E52: =F22 -> 0 | F52: =G22 -> 5034.204 | G52: =H22 -> 0 | H52: =I22 -> 0 | I52: =J22 -> 0 | ... M52: =N22 -> 0 | N52: =B52 -> 0 | O52: =C52 -> 0 | P52: =D52 -> 5034.204 | Q52: =E52 -> 0 | R52: =F52 -> 5034.204 | S52: =G52 -> 0 | T52: =H52 -> 0 | U52: =I52 -> 0 | ... BI52: =AW52 -> 0
A53: Tests homologation EN | B53: =C23 -> 0 | C53: =D23 -> 0 | D53: =E23 -> 0 | E53: =20142 -> 20142 | F53: =G23 -> 0 | G53: =H23 -> 13669 | H53: =I23 -> 0 | I53: =J23 -> 0 | J53: =K23 -> 0 | K53: =L23 -> 0 | L53: =M23 -> 0 | M53: =N23 -> 0 | N53: =B53 -> 0 | O53: =C53 -> 0 | P53: =D53 -> 0 | Q53: =G53 -> 13669 | R53: =F53 -> 0 | S53: =G53 -> 13669 | T53: =H53 -> 0 | U53: =I53 -> 0 | V53: =J53 -> 0 | W53: =K53 -> 0 | X53: =L53 -> 0 | Y53: =M53 -> 0 | ... BI53: =AW53 -> 0
A54: Production de stock | B54: =B64*'Marges Produits'!$E$49 -> 14683.095 | C54: =C64*'Marges Produits'!$E$49 -> 18878.265 | D54: =D64*'Marges Produits'!$E$49 -> 22024.643 | E54: =E64*'Marges Produits'!$E$49 -> 26219.812 | F54: =F64*'Marges Produits'!$E$49 -> 36707.738 | G54: =G64*'Marges Produits'!$E$49 -> 27268.605 | H54: =H64*'Marges Produits'!$E$49 -> 26219.812 | I54: =I64*'Marges Produits'!$E$49 -> 22024.643 | ... BI54: =BI64*'Marges Produits'!$E$49 -> 0
A55: Remboursement emprunt | B55: ='Emprunt Bancaire'!$B$27 -> 4367 | C55: ='Emprunt Bancaire'!$B$27 -> 4367 | D55: ='Emprunt Bancaire'!$B$27 -> 4367 | E55: ='Emprunt Bancaire'!$B$27 -> 4367 | F55: ='Emprunt Bancaire'!$B$27 -> 4367 | G55: ='Emprunt Bancaire'!$B$27 -> 4367 | H55: ='Emprunt Bancaire'!$B$27 -> 4367 | I55: ='Emprunt Bancaire'!$B$27 -> 4367 | ... AP55: ='Emprunt Bancaire'!$B$27 -> 4367
A56: Assurance RC (0.8% CA) | B56: =B43*0.008 -> 82.306667 | C56: =C43*0.008 -> 144.03667 | D56: =D43*0.008 -> 226.34333 | E56: =E43*0.008 -> 370.38 | F56: =F43*0.008 -> 514.41667 | G56: =G43*0.008 -> 514.41667 | H56: =H43*0.008 -> 514.41667 | I56: =I43*0.008 -> 432.11 | ... BI56: =BI43*0.008 -> 583.3485
A57: imprévue: 15% de total sortie | B57: =(SUM(B47:B56)*0.15) -> 6617.1705 | C57: =(SUM(C47:C56)*0.15) -> 5433.8056 | D57: =(SUM(D47:D56)*0.15) -> 7272.6388 | E57: =(SUM(E47:E56)*0.15) -> 9354.7892 | F57: =(SUM(F47:F56)*0.15) -> 9218.314 | G57: =(SUM(G47:G56)*0.15) -> 8412.7635 | H57: =(SUM(H47:H56)*0.15) -> 7264.9947 | I57: =(SUM(I47:I56)*0.15) -> 5413.4732 | ... BI57: =(SUM(BI47:BI56)*0.15) -> 3341.2126
A58: Total sorties | B58: =SUM(B47:B57) -> 50731.641 | C58: =SUM(C47:C57) -> 41659.176 | D58: =SUM(D47:D57) -> 55756.897 | E58: =SUM(E47:E57) -> 71720.05 | F58: =SUM(F47:F57) -> 70673.741 | G58: =SUM(G47:G57) -> 64497.854 | H58: =SUM(H47:H57) -> 55698.293 | I58: =SUM(I47:I57) -> 41503.294 | ... BI58: =SUM(BI47:BI57) -> 25615.963
A60: FLUX MENSUEL | B60: =B44-B58 -> -40443.308 | C60: =C44-C58 -> -23654.593 | D60: =D44-D58 -> 22536.019 | E60: =E44-E58 -> -25422.55 | F60: =F44-F58 -> -6371.6575 | G60: =G44-G58 -> -195.77055 | H60: =H44-H58 -> 8603.7908 | I60: =I44-I58 -> 12510.456 | ... BI60: =BI44-BI58 -> 47302.599
A61: TRÉSORERIE CUMULÉE | B61: =N31+B60 -> 112142.78 | C61: =B61+C60 -> 88488.187 | D61: =C61+D60 -> 111024.21 | E61: =D61+E60 -> 85601.656 | F61: =E61+F60 -> 79229.999 | G61: =F61+G60 -> 79034.228 | H61: =G61+H60 -> 87638.019 | I61: =H61+I60 -> 100148.47 | J61: =I61+J60 -> 102231.1 | ... BI61: =BH61+BI60 -> 1747061.9
A63: 📦 Volumes
A64: Production (nb ailes) | B64: =ROUND(($F$2*'Plan Trésorerie Mensuel'!B64),0) -> 14 | C64: =ROUND(($F$2*'Plan Trésorerie Mensuel'!C64),0) -> 18 | D64: =ROUND(($F$2*'Plan Trésorerie Mensuel'!D64),0) -> 21 | E64: =ROUND(($F$2*'Plan Trésorerie Mensuel'!E64),0) -> 25 | F64: =ROUND(($F$2*'Plan Trésorerie Mensuel'!F64),0) -> 35 | G64: =ROUND(($F$2*'Plan Trésorerie Mensuel'!G64),0) -> 26 | H64: =ROUND(($F$2*'Plan Trésorerie Mensuel'!H64),0) -> 25 | I64: =ROUND(($F$2*'Plan Trésorerie Mensuel'!I64),0) -> 21 | ... BI64: =ROUND(($F$2*'Plan Trésorerie Mensuel'!BI64),0) -> 0
A65: Ventes (nb ailes) | B65: =ROUND(($F$2*'Plan Trésorerie Mensuel'!B65),0) -> 4 | C65: =ROUND(($F$2*'Plan Trésorerie Mensuel'!C65),0) -> 7 | D65: =ROUND(($F$2*'Plan Trésorerie Mensuel'!D65),0) -> 11 | E65: =ROUND(($F$2*'Plan Trésorerie Mensuel'!E65),0) -> 18 | F65: =ROUND(($F$2*'Plan Trésorerie Mensuel'!F65),0) -> 25 | G65: =ROUND(($F$2*'Plan Trésorerie Mensuel'!G65),0) -> 25 | H65: =ROUND(($F$2*'Plan Trésorerie Mensuel'!H65),0) -> 25 | I65: =ROUND(($F$2*'Plan Trésorerie Mensuel'!I65),0) -> 21 | ... BI65: =ROUND(($F$2*'Plan Trésorerie Mensuel'!BI65),0) -> 27
A66: Stock fin de mois | B66: =N36+B64-B65 -> 21 | C66: =B66+C64-C65 -> 32 | D66: =C66+D64-D65 -> 42 | E66: =D66+E64-E65 -> 49 | F66: =E66+F64-F65 -> 59 | G66: =F66+G64-G65 -> 60 | H66: =G66+H64-H65 -> 60 | I66: =H66+I64-I65 -> 60 | J66: =I66+J64-J65 -> 60 | ... BI66: =BH66+BI64-BI65 -> 202
L67: production | M67: =SUM(B64:M64) -> 214 | X67: production | Y67: =SUM(N64:Y64) -> 466 | AJ67: production | AK67: =SUM(Z64:AK64) -> 607 | AV67: production | AW67: =SUM(AL64:AW64) -> 732 | BH67: production | BI67: =SUM(AX64:BI64) -> 704
L68: vente | M68: =SUM(B65:M65) -> 179 | X68: vente | Y68: =SUM(N65:Y65) -> 386 | AJ68: vente | AK68: =SUM(Z65:AK65) -> 563 | AV68: vente | AW68: =SUM(AL65:AW65) -> 702 | BH68: vente | BI68: =SUM(AX65:BI65) -> 702
A69: 📊 SYNTHÈSE | L69: CA vente HT | M69: =SUM(B43:M43) -> 460402.92 | X69: CA vente HT | Y69: =SUM(N43:Y43) -> 992824.17 | AJ69: CA vente HT | AK69: =SUM(Z43:AK43) -> 1448082.9 | AV69: CA vente HT | AW69: =SUM(AL43:AW43) -> 1805602.5 | BH69: CA vente HT | BI69: =SUM(AX43:BI43) -> 1895882.6
L70: Flux annuel | M70: =SUM(B60:M60) -> -56854.191 | X70: Flux annuel | Y70: =SUM(N60:Y60) -> 124172.67 | AJ70: Flux annuel | AK70: =SUM(Z60:AK60) -> 405181.33 | AV70: Flux annuel | AW70: =SUM(AL60:AW60) -> 486822.56 | BH70: Flux annuel | BI70: =SUM(AX60:BI60) -> 635153.48
A71: CALENDRIER FINANCEMENT
A72: 18 Déc 2025 : Capital social 100 000 €
A73: Janvier 2026 : Comptes courants 89 000 €
A74: Mai 2026 : Emprunt bancaire 189 000 €
A77: Mars 2027 : Avoir EURL JB 50 000 €
A79: ✅ Point bas trésorerie : | B79: =MIN(B61:BI61) -> 40215.158
A80: ✅ Trésorerie fin 2026 | B80: =N31 -> 152586.09
A81: ✅ Trésorerie fin 2027 | B81: =M61 -> 95731.896
A87: Information: Le prix de nos produits sera augmenté de 5 % le jour où on aura atteint le barier de 1000 ventes par an. ( Cette information n'est pas prise en compte dans le business plan actuel ) Et si la demande est forte, ça sera augmenté de 5 % par an jusqu'à atteindre un équilibre entre la demande et les ventes
A90: 📝 NOTE MÉTHODOLOGIQUE (TVA) :
A91: Le plan de trésorerie est volontairement présenté en HT. Étant en phase de croissance,
A92: le décalage de TVA (TVA collectée sur ventes > TVA déductible sur achats) générera un excédent
A93: de trésorerie structurel (BFR négatif sur la partie fiscale). La présentation HT constitue donc
A94: un scénario 'conservateur' qui sécurise les besoins de financement.

Sheet point mort mensuel
A1: PLAN DE TRÉSORERIE MENSUEL - PLUME PARAGLIDERS
A2: Création : 18 décembre 2025 • Délais de financement réalistes
A4: 📅 ANNÉE 2026 : LANCEMENT
B5: Déc 25 | C5: Jan | D5: Fév | E5: Mar | F5: Avr | G5: Mai | H5: Juin | I5: Juil | J5: Août | K5: Sept | L5: Oct | M5: Nov | N5: Déc | O5: TOTAL
A6: ENTRÉES
A7: Capital social | B7: =Dashboard!B9 -> 100000 | C7: 0 | D7: 0 | E7: 0 | F7: 0 | G7: 0 | H7: 0 | I7: 0 | J7: 0 | K7: 0 | L7: 0 | M7: 0 | N7: 0 | O7: =SUM(B7:N7) -> 100000
A8: Comptes courants associés | B8: 0 | C8: 89000 | D8: 0 | E8: 0 | F8: 0 | G8: 0 | H8: 0 | I8: 0 | J8: 0 | K8: 0 | L8: 0 | M8: 0 | N8: 0 | O8: =SUM(B8:N8) -> 89000
A9: Emprunt bancaire | B9: 0 | C9: 0 | D9: 0 | F9: 0 | G9: ='Emprunt Bancaire'!B4 -> 189000 | H9: 0 | I9: 0 | J9: 0 | K9: 0 | L9: 0 | M9: 0 | N9: 0 | O9: =SUM(B9:N9) -> 189000
O10: =SUM(O8:O9) -> 278000
A12: CA Ventes (HT) | B12: 0 | C12: =C34*'Marges Produits'!$C$49 -> 0 | D12: =D34*'Marges Produits'!$C$49 -> 0 | E12: =E34*'Marges Produits'!$C$49 -> 0 | F12: =F34*'Marges Produits'!$C$49 -> 0 | G12: =G34*'Marges Produits'!$C$49 -> 0 | H12: =H34*'Marges Produits'!$C$49 -> 0 | I12: =I34*'Marges Produits'!$C$49 -> 0 | J12: =J34*'Marges Produits'!$C$49 -> 0 | ... N12: =N34*'Marges Produits'!$C$49 -> 0 | O12: =SUM(B12:N12) -> 0
A13: Total entrées | B13: =SUM(B7:B12) -> 100000 | C13: =SUM(C7:C12) -> 89000 | D13: =SUM(D7:D12) -> 0 | E13: =SUM(E7:E12) -> 0 | F13: =SUM(F7:F12) -> 0 | G13: =SUM(G7:G12) -> 189000 | H13: =SUM(H7:H12) -> 0 | I13: =SUM(I7:I12) -> 0 | ... N13: =SUM(N7:N12) -> 0 | O13: =SUM(B13:N13) -> 378000
A15: SORTIES
A16: Frais création | B16: ='Frais de lancement'!B9 -> 3803 | C16: 0 | D16: 0 | E16: 0 | F16: 0 | G16: 0 | H16: 0 | I16: 0 | J16: 0 | K16: 0 | L16: 0 | M16: 0 | N16: 0 | O16: =SUM(B16:N16) -> 3803
A17: Frais prototype | B17: 0 | C17: ='Charges Fixes Plume'!G34 -> 10000 | D17: ='Charges Fixes Plume'!H34 -> 0 | E17: ='Charges Fixes Plume'!I34 -> 0 | F17: ='Charges Fixes Plume'!J34 -> 0 | G17: ='Charges Fixes Plume'!K34 -> 2517.102 | H17: ='Charges Fixes Plume'!L34 -> 2517.102 | I17: ='Charges Fixes Plume'!M34 -> 2517.102 | J17: ='Charges Fixes Plume'!N34 -> 2517.102 | ... N17: ='Charges Fixes Plume'!R34 -> 2517.102 | O17: =SUM(B17:N17) -> 30136.816
A18: Veille concurrentielle | B18: 0 | C18: 2500 | D18: 0 | E18: 0 | F18: 0 | G18: 0 | H18: 0 | I18: 2500 | J18: 0 | K18: 0 | L18: 0 | M18: 0 | N18: 0 | O18: =SUM(B18:N18) -> 5000
A19: Masse salariale | B19: ='Charges Fixes Plume'!R$13/2 -> 2170.8333 | C19: ='Charges Fixes Plume'!G13 -> 10907.667 | D19: ='Charges Fixes Plume'!H13 -> 6341.6667 | E19: ='Charges Fixes Plume'!I13 -> 10907.667 | F19: ='Charges Fixes Plume'!J13 -> 4341.6667 | G19: ='Charges Fixes Plume'!K13 -> 8907.6667 | H19: ='Charges Fixes Plume'!L13 -> 4341.6667 | I19: ='Charges Fixes Plume'!M13 -> 7907.6667 | J19: ='Charges Fixes Plume'!N13 -> 3341.6667 | ... N19: ='Charges Fixes Plume'!R13 -> 4341.6667 | O19: =SUM(B19:N19) -> 85666.833
A20: Charges exploitation | B20: ='Charges Fixes Plume'!R$29/2 -> 1728.65 | C20: ='Charges Fixes Plume'!G29 -> 9057.3 | D20: ='Charges Fixes Plume'!H29 -> 3977.3 | E20: ='Charges Fixes Plume'!I29 -> 3407.3 | F20: ='Charges Fixes Plume'!J29 -> 4407.3 | G20: ='Charges Fixes Plume'!K29 -> 3407.3 | H20: ='Charges Fixes Plume'!L29 -> 3407.3 | I20: ='Charges Fixes Plume'!M29 -> 4407.3 | J20: ='Charges Fixes Plume'!N29 -> 3407.3 | ... N20: ='Charges Fixes Plume'!R29 -> 3457.3 | O20: =SUM(B20:N20) -> 51886.25
A21: Pré-série homologation (10) | B21: 0 | C21: 0 | D21: 0 | F21: 0 | G21: 0 | H21: 0 | I21: 0 | K21: 0 | L21: 0 | M21: 0 | N21: 0 | O21: =SUM(B21:N21) -> 0
A22: Tests homologation EN | B22: 0 | C22: 0 | D22: 0 | G22: 0 | H22: 0 | I22: 0 | K22: 0 | L22: 0 | M22: 0 | N22: 0 | O22: =SUM(B22:N22) -> 0
A23: Production stock parapente | B23: 0 | C23: =C33*'Marges Produits'!$E$49 -> 0 | D23: =D33*'Marges Produits'!$E$49 -> 0 | E23: =E33*'Marges Produits'!$E$49 -> 0 | F23: =F33*'Marges Produits'!$E$49 -> 0 | G23: =G33*'Marges Produits'!$E$49 -> 0 | H23: =H33*'Marges Produits'!$E$49 -> 0 | I23: =I33*'Marges Produits'!$E$49 -> 0 | J23: =J33*'Marges Produits'!$E$49 -> 0 | ... N23: =N33*'Marges Produits'!$E$49 -> 0 | O23: =SUM(B23:N23) -> 0
A24: Remboursement emprunt | B24: 0 | C24: 0 | D24: 0 | E24: 0 | G24: ='Emprunt Bancaire'!$B$27 -> 4367 | H24: ='Emprunt Bancaire'!$B$27 -> 4367 | I24: ='Emprunt Bancaire'!$B$27 -> 4367 | J24: ='Emprunt Bancaire'!$B$27 -> 4367 | K24: ='Emprunt Bancaire'!$B$27 -> 4367 | L24: ='Emprunt Bancaire'!$B$27 -> 4367 | M24: ='Emprunt Bancaire'!$B$27 -> 4367 | N24: ='Emprunt Bancaire'!$B$27 -> 4367 | O24: =SUM(B24:N24) -> 34936
A25: Assurance RC (0.8% CA) | B25: =B12*0.008 -> 0 | C25: =C12*0.008 -> 0 | D25: =D12*0.008 -> 0 | E25: =E12*0.008 -> 0 | F25: =F12*0.008 -> 0 | G25: =G12*0.008 -> 0 | H25: =H12*0.008 -> 0 | I25: =I12*0.008 -> 0 | ... N25: =N12*0.008 -> 0 | O25: =SUM(B25:N25) -> 0
A26: imprévue: 15% de total sortie | B26: {=SUM(B16:B25*0.15)} -> 1155.3725 | C26: {=SUM(C16:C25*0.15)} -> 4869.745 | D26: {=SUM(D16:D25*0.15)} -> 1547.845 | E26: {=SUM(E16:E25*0.15)} -> 2147.245 | F26: {=SUM(F16:F25*0.15)} -> 1312.345 | G26: {=SUM(G16:G25*0.15)} -> 2879.8603 | H26: {=SUM(H16:H25*0.15)} -> 2194.9603 | I26: {=SUM(I16:I25*0.15)} -> 3254.8603 | ... N26: {=SUM(N16:N25*0.15)} -> 2202.4603 | O26: =SUM(B26:N26) -> 31714.335
A27: Total sorties | B27: =SUM(B16:B26) -> 8857.8558 | C27: =SUM(C16:C26) -> 37334.712 | D27: =SUM(D16:D26) -> 11866.812 | E27: =SUM(E16:E26) -> 16462.212 | F27: =SUM(F16:F26) -> 10061.312 | G27: =SUM(G16:G26) -> 22078.929 | H27: =SUM(H16:H26) -> 16828.029 | I27: =SUM(I16:I26) -> 24953.929 | ... N27: =SUM(N16:N26) -> 16885.529 | O27: =SUM(B27:N27) -> 243143.23
A29: FLUX MENSUEL | B29: =B13-B27 -> 91142.144 | C29: =C13-C27 -> 51665.288 | D29: =D13-D27 -> -11866.812 | E29: =E13-E27 -> -16462.212 | F29: =F13-F27 -> -10061.312 | G29: =G13-G27 -> 166921.07 | H29: =H13-H27 -> -16828.029 | I29: =I13-I27 -> -24953.929 | ... N29: =N13-N27 -> -16885.529 | O29: =SUM(C29:N29) -> 43714.622
A30: TRÉSORERIE CUMULÉE | B30: =B29 -> 91142.144 | C30: =B30+C29 -> 142807.43 | D30: =C30+D29 -> 130940.62 | E30: =D30+E29 -> 114478.41 | F30: =E30+F29 -> 104417.1 | G30: =F30+G29 -> 271338.17 | H30: =G30+H29 -> 254510.14 | I30: =H30+I29 -> 229556.21 | J30: =I30+J29 -> 213878.18 | ... N30: =M30+N29 -> 134856.77
A32: 📦 Volumes
A33: Production (nb ailes) | B33: 0 | C33: 0 | D33: 0 | E33: 0 | F33: 0 | G33: 0 | H33: 0 | I33: 0 | J33: 0 | K33: 0 | L33: 0 | M33: 0 | N33: 0 | O33: =SUM(B33:N33) -> 0
A34: Ventes (nb ailes) | B34: 0 | C34: 0 | D34: 0 | E34: 0 | F34: 0 | G34: 0 | H34: 0 | I34: 0 | J34: 0 | K34: 0 | L34: 0 | M34: 0 | N34: 0 | O34: =SUM(B34:N34) -> 0
A35: Stock fin de mois | B35: 0 | C35: =(C33+B35)-C34 -> 0 | D35: =(D33+C35)-D34 -> 0 | E35: =(E33+D35)-E34 -> 0 | F35: =(F33+E35)-F34 -> 0 | G35: =(G33+F35)-G34 -> 0 | H35: =(H33+G35)-H34 -> 0 | I35: =(I33+H35)-I34 -> 0 | J35: =(J33+I35)-J34 -> 0 | ... N35: =(N33+M35)-N34 -> 0
A38: 📅 ANNÉE 2027 : CROISSANCE | B38: 📅 ANNÉE 2027 : CROISSANCE | N38: 📅 ANNÉE 2028 : CROISSANCE | Z38: 📅 ANNÉE 2029 : CROISSANCE | AL38: 📅 ANNÉE 2030 : CROISSANCE | AX38: 📅 ANNÉE 2031 : CROISSANCE
B39: Jan | C39: Fév | D39: Mar | E39: Avr | F39: Mai | G39: Juin | H39: Juil | I39: Août | J39: Sept | K39: Oct | L39: Nov | M39: Déc | N39: Jan | O39: Fév | P39: Mar | Q39: Avr | R39: Mai | S39: Juin | T39: Juil | U39: Août | V39: Sept | W39: Oct | X39: Nov | Y39: Déc | Z39: Jan | AA39: Fév | AB39: Mar | AC39: Avr | AD39: Mai | AE39: Juin | AF39: Juil | AG39: Août | AH39: Sept | AI39: Oct | AJ39: Nov | AK39: Déc | AL39: Jan | AM39: Fév | AN39: Mar | AO39: Avr | AP39: Mai | AQ39: Juin | AR39: Juil | AS39: Août | AT39: Sept | AU39: Oct | AV39: Nov | AW39: Déc | AX39: Jan | AY39: Fév | AZ39: Mar | BA39: Avr | BB39: Mai | BC39: Juin | BD39: Juil | BE39: Août | BF39: Sept | BG39: Oct | BH39: Nov | BI39: Déc
A40: ENTRÉES
A41: Apport | B41: 0 | C41: 0 | D41: 50000 | E41: 0 | F41: 0 | G41: 0 | H41: 0 | I41: 0 | J41: 0 | K41: 0 | L41: 0 | M41: 0
A42: CA Ventes (HT) | B42: =B63*'Marges Produits'!$C$49 -> 0 | C42: =C63*'Marges Produits'!$C$49 -> 0 | D42: =D63*'Marges Produits'!$C$49 -> 0 | E42: =E63*'Marges Produits'!$C$49 -> 12860.417 | F42: =F63*'Marges Produits'!$C$49 -> 36009.167 | G42: =G63*'Marges Produits'!$C$49 -> 38581.25 | H42: =H63*'Marges Produits'!$C$49 -> 51441.667 | I42: =I63*'Marges Produits'!$C$49 -> 64302.083 | ... AW42: =AW63*'Marges Produits'!$C$49 -> 12860.417 | AX42: =AX63*(('Marges Produits'!$C$49)*1.05) -> 27006.875 | AY42: =AY63*(('Marges Produits'!$C$49)*1.05) -> 40510.313 | AZ42: =AZ63*(('Marges Produits'!$C$49)*1.05) -> 54013.75 | BA42: =BA63*(('Marges Produits'!$C$49)*1.05) -> 54013.75 | BB42: =BB63*(('Marges Produits'!$C$49)*1.05) -> 54013.75 | BC42: =BC63*(('Marges Produits'!$C$49)*1.05) -> 54013.75 | BD42: =BD63*(('Marges Produits'!$C$49)*1.05) -> 54013.75 | BE42: =BE63*(('Marges Produits'!$C$49)*1.05) -> 54013.75 | ... BI42: =BI63*(('Marges Produits'!$C$49)*1.05) -> 13503.438
A43: Total entrées | B43: =SUM(B41:B42) -> 0 | C43: =SUM(C41:C42) -> 0 | D43: =SUM(D41:D42) -> 50000 | E43: =SUM(E41:E42) -> 12860.417 | F43: =SUM(F41:F42) -> 36009.167 | G43: =SUM(G41:G42) -> 38581.25 | H43: =SUM(H41:H42) -> 51441.667 | I43: =SUM(I41:I42) -> 64302.083 | ... BI43: =SUM(BI41:BI42) -> 13503.438
A45: SORTIES
A46: Frais prototype | B46: ='Charges Fixes Plume'!$C$34*2 -> 2517.102 | C46: ='Charges Fixes Plume'!$C$34*2 -> 2517.102 | D46: ='Charges Fixes Plume'!$C$34*2 -> 2517.102 | E46: ='Charges Fixes Plume'!$C$34*2 -> 2517.102 | F46: ='Charges Fixes Plume'!$C$34*2 -> 2517.102 | G46: ='Charges Fixes Plume'!$C$34*2 -> 2517.102 | H46: ='Charges Fixes Plume'!$C$34*2 -> 2517.102 | I46: ='Charges Fixes Plume'!$C$34*2 -> 2517.102 | ... BI46: ='Charges Fixes Plume'!$C$34*2 -> 2517.102
A47: Veille concurrentielle | B47: 2500 | C47: 0 | D47: 0 | E47: 0 | F47: 0 | G47: 0 | H47: 2500 | I47: 0 | J47: 0 | K47: 0 | L47: 0 | M47: 0 | N47: =B47 -> 2500 | O47: =C47 -> 0 | P47: =D47 -> 0 | Q47: =E47 -> 0 | R47: =F47 -> 0 | S47: =G47 -> 0 | T47: =H47 -> 2500 | U47: =I47 -> 0 | ... BI47: =AW47 -> 0
A48: Masse salariale | B48: =C19 -> 10907.667 | C48: =D19 -> 6341.6667 | D48: =E19 -> 10907.667 | E48: =F19 -> 4341.6667 | F48: =G19 -> 8907.6667 | G48: =H19 -> 4341.6667 | H48: =I19 -> 7907.6667 | I48: =J19 -> 3341.6667 | ... M48: =N19 -> 4341.6667 | N48: =B48 -> 10907.667 | O48: =C48 -> 6341.6667 | P48: =D48 -> 10907.667 | Q48: =E48 -> 4341.6667 | R48: =F48 -> 8907.6667 | S48: =G48 -> 4341.6667 | T48: =H48 -> 7907.6667 | U48: =I48 -> 3341.6667 | ... BI48: =AW48 -> 4341.6667
A49: Charges exploitation | B49: =C20 -> 9057.3 | C49: =D20 -> 3977.3 | D49: =E20 -> 3407.3 | E49: =F20 -> 4407.3 | F49: =G20 -> 3407.3 | G49: =H20 -> 3407.3 | H49: =I20 -> 4407.3 | I49: =J20 -> 3407.3 | ... M49: =N20 -> 3457.3 | N49: =B49 -> 9057.3 | O49: =C49 -> 3977.3 | P49: =D49 -> 3407.3 | Q49: =E49 -> 4407.3 | R49: =F49 -> 3407.3 | S49: =G49 -> 3407.3 | T49: =H49 -> 4407.3 | U49: =I49 -> 3407.3 | ... BI49: =AW49 -> 3457.3
A50: Pré-série homologation (10) | B50: =C21 -> 0 | C50: 5034.204 | D50: =E21 -> 0 | E50: =F21 -> 0 | F50: =G21 -> 0 | G50: =H21 -> 0 | H50: =I21 -> 0 | I50: 5034.204 | J50: =K21 -> 0 | K50: =L21 -> 0 | L50: =M21 -> 0 | M50: =N21 -> 0 | N50: =B50 -> 0 | O50: =C50 -> 5034.204 | P50: =D50 -> 0 | Q50: =E50 -> 0 | R50: =F50 -> 0 | S50: =G50 -> 0 | T50: =H50 -> 0 | U50: =I50 -> 5034.204 | ... BI50: =AW50 -> 0
A51: Tests homologation EN | B51: =C22 -> 0 | C51: 13669 | D51: =E22 -> 0 | E51: =F22 -> 0 | F51: =G22 -> 0 | G51: =H22 -> 0 | H51: =I22 -> 0 | I51: 13669 | J51: =K22 -> 0 | K51: =L22 -> 0 | L51: =M22 -> 0 | M51: =N22 -> 0 | N51: =B51 -> 0 | O51: =C51 -> 13669 | P51: =D51 -> 0 | Q51: =E51 -> 0 | R51: =F51 -> 0 | S51: =G51 -> 0 | T51: =H51 -> 0 | U51: =I51 -> 13669 | ... BI51: =AW51 -> 0
A52: Production de stock | B52: =B62*'Marges Produits'!$E$49 -> 0 | C52: =C62*'Marges Produits'!$E$49 -> 0 | D52: =D62*'Marges Produits'!$E$49 -> 10487.925 | E52: =E62*'Marges Produits'!$E$49 -> 20975.85 | F52: =F62*'Marges Produits'!$E$49 -> 10487.925 | G52: =G62*'Marges Produits'!$E$49 -> 15731.888 | H52: =H62*'Marges Produits'!$E$49 -> 26219.812 | I52: =I62*'Marges Produits'!$E$49 -> 24122.228 | ... BI52: =BI62*'Marges Produits'!$E$49 -> 0
A53: Remboursement emprunt | B53: ='Emprunt Bancaire'!$B$27 -> 4367 | C53: ='Emprunt Bancaire'!$B$27 -> 4367 | D53: ='Emprunt Bancaire'!$B$27 -> 4367 | E53: ='Emprunt Bancaire'!$B$27 -> 4367 | F53: ='Emprunt Bancaire'!$B$27 -> 4367 | G53: ='Emprunt Bancaire'!$B$27 -> 4367 | H53: ='Emprunt Bancaire'!$B$27 -> 4367 | I53: ='Emprunt Bancaire'!$B$27 -> 4367 | ... AO53: ='Emprunt Bancaire'!$B$27 -> 4367
A54: Assurance RC (0.8% CA) | B54: =B42*0.008 -> 0 | C54: =C42*0.008 -> 0 | D54: =D42*0.008 -> 0 | E54: =E42*0.008 -> 102.88333 | F54: =F42*0.008 -> 288.07333 | G54: =G42*0.008 -> 308.65 | H54: =H42*0.008 -> 411.53333 | I54: =I42*0.008 -> 514.41667 | ... BI54: =BI42*0.008 -> 108.0275
A55: imprévue: 15% de total sortie | B55: =(SUM(B46:B54)*0.15) -> 4402.3603 | C55: =(SUM(C46:C54)*0.15) -> 5385.9409 | D55: =(SUM(D46:D54)*0.15) -> 4753.049 | E55: =(SUM(E46:E54)*0.15) -> 5506.7703 | F55: =(SUM(F46:F54)*0.15) -> 4496.26 | G55: =(SUM(G46:G54)*0.15) -> 4601.0409 | H55: =(SUM(H46:H54)*0.15) -> 7249.5622 | I55: =(SUM(I46:I54)*0.15) -> 8545.9375 | ... BI55: =(SUM(BI46:BI54)*0.15) -> 1563.6144
A56: Total sorties | B56: =SUM(B46:B55) -> 33751.429 | C56: =SUM(C46:C55) -> 41292.214 | D56: =SUM(D46:D55) -> 36440.043 | E56: =SUM(E46:E55) -> 42218.572 | F56: =SUM(F46:F55) -> 34471.327 | G56: =SUM(G46:G55) -> 35274.647 | H56: =SUM(H46:H55) -> 55579.977 | I56: =SUM(I46:I55) -> 65518.854 | ... BI56: =SUM(BI46:BI55) -> 11987.711
A58: FLUX MENSUEL | B58: =B43-B56 -> -33751.429 | C58: =C43-C56 -> -41292.214 | D58: =D43-D56 -> 13559.957 | E58: =E43-E56 -> -29358.156 | F58: =F43-F56 -> 1537.8396 | G58: =G43-G56 -> 3306.6029 | H58: =H43-H56 -> -4138.31 | I58: =I43-I56 -> -1216.771 | ... BI58: =BI43-BI56 -> 1515.7269
A59: TRÉSORERIE CUMULÉE | B59: =N30+B58 -> 101105.34 | C59: =B59+C58 -> 59813.123 | D59: =C59+D58 -> 73373.081 | E59: =D59+E58 -> 44014.925 | F59: =E59+F58 -> 45552.765 | G59: =F59+G58 -> 48859.367 | H59: =G59+H58 -> 44721.057 | I59: =H59+I58 -> 43504.286 | J59: =I59+J58 -> 54983.077 | ... BI59: =BH59+BI58 -> 41860.361
A61: 📦 Volumes
A62: Production (nb ailes) | B62: 0 | C62: 0 | D62: 10 | E62: 20 | F62: 10 | G62: 15 | H62: 25 | I62: 23 | J62: 25 | K62: 25 | L62: 0 | M62: 0 | N62: 22 | O62: 25 | P62: 30 | Q62: 30 | R62: 30 | S62: 30 | T62: 30 | U62: 30 | V62: 25 | W62: 25 | X62: 25 | Y62: 0 | Z62: 0 | AA62: 10 | AB62: 25 | AC62: 30 | AD62: 30 | AE62: 30 | AF62: 30 | AG62: 30 | AH62: 30 | AI62: =W62 -> 25 | AJ62: 0 | AK62: =Y62 -> 0 | AL62: =Z62 -> 0 | AM62: =AA62 -> 10 | AN62: =AB62 -> 25 | AO62: =AC62 -> 30 | AP62: =AD62 -> 30 | AQ62: =AE62 -> 30 | AR62: 20 | AS62: 20 | AT62: 20 | AU62: 15 | AV62: =AJ62 -> 0 | AW62: =AK62 -> 0 | AX62: =AL62 -> 0 | AY62: =AM62 -> 10 | AZ62: =AN62 -> 25 | BA62: =AO62 -> 30 | BB62: =AP62 -> 30 | BC62: =AQ62 -> 30 | ... BI62: =AW62 -> 0
A63: Ventes (nb ailes) | B63: 0 | C63: 0 | D63: 0 | E63: 5 | F63: 14 | G63: 15 | H63: 20 | I63: 25 | J63: 25 | K63: 20 | L63: 10 | M63: 5 | N63: 10 | O63: 20 | P63: 25 | Q63: 25 | R63: 25 | S63: 25 | T63: 25 | U63: 25 | V63: 25 | W63: 25 | X63: 7 | Y63: 5 | Z63: =N63 -> 10 | AA63: =O63 -> 20 | AB63: =P63 -> 25 | AC63: =Q63 -> 25 | AD63: =R63 -> 25 | AE63: =S63 -> 25 | AF63: =T63 -> 25 | AG63: =U63 -> 25 | ... AL63: =Z63 -> 10 | AM63: 15 | AN63: 20 | AO63: 20 | AP63: 20 | AQ63: 20 | AR63: 20 | AS63: 20 | AT63: 15 | AU63: 15 | AV63: =AJ63 -> 7 | AW63: =AK63 -> 5 | AX63: =AL63 -> 10 | AY63: =AM63 -> 15 | AZ63: =AN63 -> 20 | BA63: =AO63 -> 20 | BB63: =AP63 -> 20 | BC63: =AQ63 -> 20 | ... BI63: =AW63 -> 5
A64: Stock fin de mois | B64: 0 | C64: 0 | D64: 0 | E64: =D64+E62-E63 -> 15 | F64: =E64+F62-F63 -> 11 | G64: =F64+G62-G63 -> 11 | H64: =G64+H62-H63 -> 16 | I64: =H64+I62-I63 -> 14 | J64: =I64+J62-J63 -> 14 | K64: =J64+K62-K63 -> 19 | L64: =K64+L62-L63 -> 9 | ... BI64: =BH64+BI62-BI63 -> 88
L65: production | M65: =SUM(B62:M62) -> 153 | X65: production | Y65: =SUM(N62:Y62) -> 302 | AJ65: production | AK65: =SUM(Z62:AK62) -> 240 | AV65: production | AW65: =SUM(AL62:AW62) -> 200 | BH65: production | BI65: =SUM(AX62:BI62) -> 200
L66: vente | M66: =SUM(B63:M63) -> 139 | X66: vente | Y66: =SUM(N63:Y63) -> 242 | AJ66: vente | AK66: =SUM(Z63:AK63) -> 242 | AV66: vente | AW66: =SUM(AL63:AW63) -> 187 | BH66: vente | BI66: =SUM(AX63:BI63) -> 187
A67: 📊 SYNTHÈSE | L67: CA vente HT | M67: =SUM(B42:M42) -> 357519.58 | X67: CA vente HT | Y67: =SUM(N42:Y42) -> 622444.17 | AJ67: CA vente HT | AK67: =SUM(Z42:AK42) -> 622444.17 | AV67: CA vente HT | AW67: =SUM(AL42:AW42) -> 480979.58 | BH67: CA vente HT | BI67: =SUM(AX42:BI42) -> 505028.56
L68: Flux annuel | M68: =SUM(B58:M58) -> -77774.254 | X68: Flux annuel | Y68: =SUM(N58:Y58) -> -44997.572 | AJ68: Flux annuel | AK68: =SUM(Z58:AK58) -> 29781.334 | AV68: Flux annuel | AW68: =SUM(AL58:AW58) -> -21960.921 | BH68: Flux annuel | BI68: =SUM(AX58:BI58) -> 21955.008
A69: CALENDRIER FINANCEMENT
A70: 18 Déc 2025 : Capital social 100 000 €
A71: Janvier 2026 : Comptes courants 89 000 €
A72: Mai 2026 : Emprunt bancaire 189 000 €
A75: Mars 2027 : Avoir EURL JB 50 000 €
A77: ✅ Point bas trésorerie : | B77: =MIN(E30:N30,B59:M59) -> 43504.286
A78: ✅ Trésorerie fin 2026 | B78: =N30 -> 134856.77
A79: ✅ Trésorerie fin 2027 | B79: =M59 -> 57082.512
A85: Information: Le prix de nos produits sera augmenté de 5 % le jour où on aura atteint le barier de 1000 ventes par an. Et si la demande est forte, ça sera augmenté de 5 % par an jusqu'à atteindre un équilibre entre la demande et les ventes
A88: 📝 NOTE MÉTHODOLOGIQUE (TVA) :
A89: Le plan de trésorerie est volontairement présenté en HT. Étant en phase de croissance,
A90: le décalage de TVA (TVA collectée sur ventes > TVA déductible sur achats) générera un excédent
A91: de trésorerie structurel (BFR négatif sur la partie fiscale). La présentation HT constitue donc
A92: un scénario 'conservateur' qui sécurise les besoins de financement.

Sheet Analyse Point Mort
A1: SCÉNARIO POINT MORT - MINIMUM SYNDICAL
A2: Objectif : Trésorerie cumulée ≥ 0 € (survie)
A4: PARAMÈTRES
A5: Marge nette par aile | B5: ='Seuil Rentabilité'!B8 -> 1079.7808
A6: Coût de revient par aile | B6: ='Seuil Rentabilité'!B6 -> 1048.7925
A7: Stock cible (%) | B7: 0.5
A8: Charges fixes annuelles | B8: ='Charges Fixes Plume'!D57 -> 208782.33
A9: Remboursement emprunt | B9: ='Emprunt Bancaire'!D11 -> 52398.71
A10: Marge après BFR initial (marge - 50%×coût) | B10: =B5-B7*B6 -> 555.38458
A12: SCÉNARIO POINT MORT
A13: Année | B13: 2025 | C13: 2026 | D13: 2027 | E13: 2028 | F13: 2029 | G13: 2030 | H13: 2031
A14: Apports | B14: ='Plan Trésorerie Mensuel'!B13 -> 100000 | C14: =SUM('Plan Trésorerie Mensuel'!C8:N9) -> 278000 | D14: 50000 | E14: 0 | F14: 0 | G14: 0 | H14: 0
A15: Charges fixes (€) | B15: 10000 | C15: ='Charges Fixes Plume'!$D$57 -> 208782.33 | D15: ='Charges Fixes Plume'!$D$57 -> 208782.33 | E15: ='Charges Fixes Plume'!$D$57 -> 208782.33 | F15: ='Charges Fixes Plume'!$D$57 -> 208782.33 | G15: ='Charges Fixes Plume'!$D$57 -> 208782.33 | H15: ='Charges Fixes Plume'!$D$57 -> 208782.33
A16: Remboursement emprunt (€) | B16: ='Seuil Rentabilité'!B16 -> 0 | C16: ='Seuil Rentabilité'!C16 -> 5742.63 | D16: ='Seuil Rentabilité'!D16 -> 6941.91 | E16: ='Seuil Rentabilité'!E16 -> 4853.64 | F16: ='Seuil Rentabilité'!F16 -> 2669.42 | G16: ='Seuil Rentabilité'!G16 -> 387.22 | H16: ='Seuil Rentabilité'!H16 -> 0
A17: Total sorties fixes (€) | B17: =SUM(B15:B16) -> 10000 | C17: =SUM(C15:C16) -> 214524.96 | D17: =SUM(D15:D16) -> 215724.24 | E17: =SUM(E15:E16) -> 213635.97 | F17: =SUM(F15:F16) -> 211451.75 | G17: =SUM(G15:G16) -> 209169.55 | H17: =SUM(H15:H16) -> 208782.33
A19: 🎯 VENTES MINIMUM (ailes) | B19: 0 | C19: 0 | D19: ='point mort mensuel'!M66 -> 139 | E19: ='point mort mensuel'!Y66 -> 242 | F19: ='point mort mensuel'!AK66 -> 242 | G19: ='point mort mensuel'!AW66 -> 187 | H19: ='point mort mensuel'!BI66 -> 187
A21: Marge brute générée (€) | B21: 0 | C21: 0 | D21: ='Marges Produits'!$D$49*D19 -> 152949.69 | E21: ='Marges Produits'!$D$49*E19 -> 266286.51 | F21: ='Marges Produits'!$D$49*F19 -> 266286.51 | G21: ='Marges Produits'!$D$49*G19 -> 205766.85 | H21: ='Marges Produits'!$D$49*H19 -> 205766.85
A22: Stock cible (€) | B22: 0 | C22: 0 | D22: ='point mort mensuel'!M64*'Analyse Point Mort'!B6 -> 4195.17 | E22: ='point mort mensuel'!Y64*'Analyse Point Mort'!B6 -> 67122.72 | F22: =B6*'point mort mensuel'!AK64 -> 65025.135 | G22: =B6*'point mort mensuel'!AW64 -> 78659.438 | H22: =B6*'point mort mensuel'!BI64 -> 92293.74
A23: Variation stock (€) | B23: 0 | C23: 0 | D23: =D22-C22 -> 4195.17 | E23: =E22-D22 -> 62927.55 | F23: =F22-E22 -> -2097.585 | G23: =G22-F22 -> 13634.302 | H23: =H22-G22 -> 13634.303
A25: FLUX DE TRÉSORERIE (€) | B25: ='point mort mensuel'!B29 -> 91142.144 | C25: =SUM('point mort mensuel'!C29:N29) -> 43714.622 | D25: =SUM('point mort mensuel'!B58:M58) -> -77774.254 | E25: =SUM('point mort mensuel'!N58:Y58) -> -44997.572 | F25: =SUM('point mort mensuel'!Z58:AK58) -> 29781.334 | G25: =SUM('point mort mensuel'!AL58:AW58) -> -21960.921 | H25: =SUM('point mort mensuel'!AX58:BI58) -> 21955.008
A26: TRÉSORERIE CUMULÉE (€) | B26: ='point mort mensuel'!B30 -> 91142.144 | C26: ='point mort mensuel'!N30 -> 134856.77 | D26: ='point mort mensuel'!M59 -> 57082.512 | E26: ='point mort mensuel'!Y59 -> 12084.94 | F26: ='point mort mensuel'!AK59 -> 41866.274 | G26: ='point mort mensuel'!AW59 -> 19905.353 | H26: ='point mort mensuel'!BI59 -> 41860.361
A28: INDICATEURS
A29: Seuil rentabilité (ailes) | B29: ='Seuil Rentabilité'!B24 -> 8 | C29: ='Seuil Rentabilité'!C24 -> 194 | D29: ='Seuil Rentabilité'!D24 -> 204 | E29: ='Seuil Rentabilité'!E24 -> 196 | F29: ='Seuil Rentabilité'!F24 -> 320 | G29: ='Seuil Rentabilité'!G24 -> 318 | H29: ='Seuil Rentabilité'!H24 -> 318
A30: Écart ventes vs seuil | B30: =B19-B29 -> -8 | C30: =C19-C29 -> -194 | D30: =D19-D29 -> -65 | E30: =E19-E29 -> 46 | F30: =F19-F29 -> -78 | G30: =G19-G29 -> -131 | H30: =H19-H29 -> -131
A32: RÉSUMÉ
A33: Total ventes (7 ans) | B33: =SUM(B19:H19) -> 997
A34: Moyenne annuelle (hors 2025) | B34: =AVERAGE(C19:H19) -> 166.16667
A35: Trésorerie minimum ( valeur de point mort mensuel ) | B35: =MIN('point mort mensuel'!B59:BI59) -> 1432.7888
A37: 📅 CALENDRIER DES APPORTS
A38: • Déc 2025 : Capital social = 100 000€
A39: • Jan 2026 : Comptes courants associés = 89 000€
A40: • Mai 2026 : Emprunt Banque Populaire = 189 000€
A41: • mars 2027 : Avoir EURL JB = 50 000€
A43: 📌 MODE D'EMPLOI
A44: 1. Les cellules JAUNES (ventes) sont modifiables
A45: 2. La TRÉSORERIE CUMULÉE doit rester ≥ 0€
A46: 3. Remboursement emprunt : 9 mois en 2026, 12 mois/an 2027-2029
A48: ⚠️ Ce scénario est le STRICT MINIMUM pour survivre !

Sheet Conditions & risques 
A1: 📋 CONDITIONS COMMERCIALES & GESTION DES RISQUES
A3: 💳 DÉLAIS DE PAIEMENT
A4: Flux | B4: Délai | C4: Impact BFR | D4: Commentaire
A5: 🟢 Encaissement client B2C | B5: Comptant (J+2) | C5: BFR = 0 | D5: Paiement Stripe/Briddge, fonds reçus sous 48h
A6: 🟢 Encaissement client School Pack | B6: Comptant à la commande | C6: BFR = 0 | D6: Prépaiement par les écoles partenaires
A7: 🟢 Paiement usine (A&C Thai) | B7: 3 semaines après expédition | C7: BFR très favorable | D7: On reçoit les ailes, puis on paie 3 semaines après. Possibilité de vendre avant de payer le fournisseur.
A8: ⬜ Fournisseur tissus (Porcher) | B8: Non applicable | C8: Aucun impact | D8: L'usine A&C gère directement l'approvisionnement tissus. Plume n'a aucune relation de paiement avec Porcher.
A9: 🟡 Paiement logistique | B9: À la livraison | C9: BFR neutre | D9: Facture automatisée au transporteur à réception. Aucune gestion manuelle.
A11: ✅ BFR structurellement négatif (= favorable) : le client paie comptant, l'usine est payée 3 semaines après expédition. Plume peut encaisser la vente AVANT de payer le fournisseur. Zéro risque d'impayé client, zéro gestion de créance.
A13: ⚠️ ANALYSE DES RISQUES
A14: Risque identifié | B14: Probabilité | C14: Impact | D14: Réponse / Mitigation
A15: Retard homologation EN (1,5 mois) | B15: Faible | C15: Modéré | D15: Scénario point mort prévoit 0 vente en 2026. Trésorerie absorbe un retard de 6 mois.
A16: Risque de change (EUR/USD ou EUR/THB) | B16: Moyen | C16: Modéré | D16: L'usine gère les approvisionnements tissus. Prix de vente usine négocié par lot. Marge brute de 42% absorbe les variations.
A17: Concentration fournisseur (1 usine) | B17: Faible | C17: Fort | D17: 2 usines qualifiées (A&C Thai + Sky Sport Lanka). Backup opérationnel en cas de défaillance.
A18: Saisonnalité forte (70% CA mars-sept) | B18: Élevé | C18: Modéré | D18: Production lissée sur 10 mois. Stock tampon absorbe les pics. Charges fixes mensualisées.
A19: Dépendance notoriété fondateur | B19: Faible | C19: Modéré | D19: Marque PLUME construite pour exister indépendamment. Réseau d'écoles partenaires = canal récurrent.
A20: Entrée d'un concurrent premium | B20: Faible | C20: Modéré | D20: Brevet ACS (FR2503019) protège l'avantage technologique. Track record 15 ans = barrière de réputation.
